Workbook

Sheet Export Summary
B3: This document was exported from Numbers. Each table was converted to an Excel worksheet. All other objects on each Numbers sheet were placed on separate worksheets. Please be aware that formula calculations may differ in Excel.
B7: Numbers Sheet Name | C7: Numbers Table Name | D7: Excel Worksheet Name
B9: RECOMMENDED PRICES
C10: Table 1 | D10: RECOMMENDED PRICES
B11: PnL 2026 Plan-Forecast
C12: Table 1 | D12: PnL 2026 Plan-Forecast
B13: FCF 2025-2026 Forecast
C14: Table 1 | D14: FCF 2025-2026 Forecast
B15: Private Boats 2026 Target
C16: Table 1 | D16: Private Boats 2026 Target
B17: Shared Boats 2026 Target
C18: Table 1 | D18: Shared Boats 2026 Target
B19: Premium Shared 2026 Target
C20: Table 1 | D20: Premium Shared 2026 Target
B21: Premium for Couples 2026 Target
C22: Table 1 | D22: Premium for Couples 2026 Target
B23: Standard Diving Tour 2026
C24: Table 1 | D24: Standard Diving Tour 2026
B25: Premium Diving Tour 2026
C26: Table 1 | D26: Premium Diving Tour 2026
B27: Fishing Tour 2026 Target
C28: Table 1 | D28: Fishing Tour 2026 Target
B29: Project Eldorado ROI in IDR
C30: Table 1 | D30: Project Eldorado ROI in IDR
B31: Project Eldorado ROI in USD
C32: Table 1 | D32: Project Eldorado ROI in USD
B33: Project Eldorado IRR 50-50
C34: Table 1 | D34: Project Eldorado IRR 50-50
B35: Project Eldorado IRR 80-20
C36: Table 1 | D36: Project Eldorado IRR 80-20
B37: Direct Costs 2026
C38: Table 1 | D38: Direct Costs 2026
B39: Trasnfers, Extras, Alco 2026
C40: Table 1 | D40: Trasnfers, Extras, Alco 2026
B41: Boats Data Sheet 2026
C42: Table 1 | D42: Boats Data Sheet 2026
B43: Allocation OH and Target 2026
C44: Table 1 | D44: Allocation OH and Target 2026
B45: Boats Data Sheet 2025
C46: Table 1 | D46: Boats Data Sheet 2025
B47: Allocation OH and Target 2025
C48: Table 1 | D48: Allocation OH and Target 2025
B49: Admin Expenses 2026
C50: Table 1 | D50: Admin Expenses 2026
B51: Admin Expenses 2025
C52: Table 1 | D52: Admin Expenses 2025
B53: Admin Expenses 2024
C54: Table 1 | D54: Admin Expenses 2024
B55: Payroll 2026
C56: Table 1 | D56: Payroll 2026
B57: Payroll 2025
C58: Table 1 | D58: Payroll 2025
B59: Actual Sales 2025
C60: Table 1 | D60: Actual Sales 2025
B61: NEW Actual Sales Jan-Nov 2024
C62: Table 1 | D62: NEW Actual Sales Jan-Nov 2024
B63: OLD Actual Sales Jan-Mar 2024
C64: Table 1 | D64: OLD Actual Sales Jan-Mar 2024
B65: Cash Flow Statement 6M 2025
C66: Table 1 | D66: Cash Flow Statement 6M 2025
B67: Cash Flow Statement 2024
C68: Table 1 | D68: Cash Flow Statement 2024
B69: BS 6M 2025
C70: Table 1 | D70: BS 6M 2025
B71: BS 2024
C72: Table 1 | D72: BS 2024
B73: PnL 6M 2025
C74: Table 1 | D74: PnL 6M 2025
B75: PnL 2025
C76: Table 1 | D76: PnL 2025
B77: PnL 2024
C78: Table 1 | D78: PnL 2024
B79: PnL 2023
C80: Table 1 | D80: PnL 2023
B81: Monthly PnL 2024
C82: Table 1 | D82: Monthly PnL 2024
B83: PnL 2024 (Old)
C84: Table 1 | D84: PnL 2024 (Old)
B85: MOD - Discount Options
C86: Table 1 | D86: MOD - Discount Options
B87: MBT Private Tours
C88: Table 1 | D88: MBT Private Tours
B89: ANC and JA20 Pricing
C90: Table 1 | D90: ANC and JA20 Pricing
B91: Klook - Land Tour Only
C92: Table 1 | D92: Klook - Land Tour Only
B93: Restaurants
C94: Table 1 | D94: Restaurants
B95: Old NP.one and Odoo Boat Prices
C96: Table 1 | D96: Old NP.one and Odoo Boat Prices

Sheet RECOMMENDED PRICES
X1: Hidden comments
B2: TOUR | C2: BOAT CLASS | D2: AVERAGE TARGET TRIP RATE | E2: AVERAGE TARGET BOAT OCCUPANCY
B3: Shared | C3: Primary | D3: {=AVERAGE('Allocation OH and Target 2026'!I3:I23)} -> 0.6547619 | E3: {=AVERAGE('Allocation OH and Target 2026'!J3:J23)} -> 0.8047619
B4: Private | C4: Primary | D4: {=AVERAGE('Allocation OH and Target 2026'!I35:I53)} -> 0.66315789 | E4: N/A
B5: Private | C5: Secondary | D5: {=AVERAGE('Allocation OH and Target 2026'!I54,'Allocation OH and Target 2026'!I57:I59,'Allocation OH and Target 2026'!I62:I64,'Allocation OH and Target 2026'!I66,'Allocation OH and Target 2026'!I71:I77,'Allocation OH and Target 2026'!I82:I86,'Allocation OH and Target 2026'!I88:I91)} -> 0.1325 | E5: N/A
B7: STANDARD SHARED TOURS | C7: RECOMMENDED | D7: Actual Updated Prices | E7: TOTAL BASE for TripAdvisor (25%) | F7: TOTAL BASE for Klook (25%) | G7: TOTAL BASE for AirBnB (20%)
B8: PRICE PER PASSENGER | C8: {=ROUNDUP(AVERAGE('Shared Boats 2026 Target'!AG5:AG183,'Shared Boats 2026 Target'!AG212:AG367),-4)} -> 1460000 | D8: 1390000 | E8: {=D8/(100%-25%)} -> 1853333.3 | F8: {=D8/(100%-25%)} -> 1853333.3 | G8: {=D8/(100%-20%)} -> 1737500
B9: PRICES FOR HIGH SEASON +10% | D9: {=D8*110%} -> 1529000 | E9: {=E8*110%} -> 2038666.7 | F9: {=F8*110%} -> 2038666.7 | G9: {=G8*110%} -> 1911250
B11: PREMIUM SHARED TOURS | C11: RECOMMENDED | D11: Actual Updated Prices | E11: TOTAL BASE for TripAdvisor (25%) | F11: TOTAL BASE for Klook (25%) | G11: TOTAL BASE for AirBnB (20%)
B12: PRICE PER PASSENGER | C12: {=ROUNDUP(AVERAGE('Premium Shared 2026 Target'!AI1:AI183),-4)} -> 1910000 | D12: 2050000 | E12: {=D12/(100%-25%)} -> 2733333.3 | F12: {=D12/(100%-25%)} -> 2733333.3 | G12: {=D12/(100%-20%)} -> 2562500
B13: PRICES FOR HIGH SEASON +10% | D13: {=D12*110%} -> 2255000 | E13: {=E12*110%} -> 3006666.7 | F13: {=F12*110%} -> 3006666.7 | G13: {=G12*110%} -> 2818750
B15: PRIVATE TOURS | C15: Recommended | D15: Actual Updated Prices | E15: PRICES FOR HIGH SEASON +10% | F15: Actual Price at Bluuu.tours | G15: TO INCREASE/ TO DECREASE | H15: DTB10 Code NP.ONE Price | I15: PUBLISHED PRICE | K15: NET PROFIT | L15: NPM | M15: AGENT FEE % | N15: AGENT FEE | P15: PRICES FOR GETMYBOAT | R15: ABSOLUTE MINIMUM | Z15: PRICES FOR BALICOPTER
B16: Recommended Base Price:
B17: RECOMMENED BASE PRICE PER TOUR | C17: {=ROUNDUP(AVERAGE('Private Boats 2026 Target'!Z5,'Private Boats 2026 Target'!Z28,'Private Boats 2026 Target'!Z51,'Private Boats 2026 Target'!Z97,'Private Boats 2026 Target'!Z168,'Private Boats 2026 Target'!Z214,'Private Boats 2026 Target'!Z817,'Private Boats 2026 Target'!Z1008,'Private Boats 2026 Target'!Z1031,'Private Boats 2026 Target'!Z1054,'Private Boats 2026 Target'!Z1146),-4)} -> 12890000 | D17: {=10600000+500000+400000+400000+395000} -> 12295000 | E17: {=D17*110%} -> 13524500 | F17: {=12295000} -> 12295000 | G17: {=_xlfn.IFERROR((D17-F17),"not listed")} -> 0
B19: Recommended Boat Upgrade Price:
A20: O | B20: {='Boats Data Sheet 2025'!C3} -> Sweetheart 4 | C20: {=IF(ROUNDUP((AVERAGE('Private Boats 2026 Target'!AC5:AC22)-$C$17),-2)<0,0,ROUNDUP((AVERAGE('Private Boats 2026 Target'!AC5:AC22)-$C$17),-2))} -> 1190300 | D20: {=13000000-D17} -> 705000 | E20: {=D20*110%} -> 775500 | F20: 1500000 | G20: {=_xlfn.IFERROR((D20-F20),"not listed")} -> -795000 | H20: {=IF(A20="O",ROUND((F20+$F$17)/0.9-$F$17,-3),F20)} -> 3033000 | I20: {=$F$17+F20} -> 13795000 | K20: {=$F$17+F20-VLOOKUP(B20,'Private Boats 2026 Target'!$C$2:$AN$1501,38,0)} -> 3053191.4 | L20: {=K20/VLOOKUP(B20,'Private Boats 2026 Target'!$C$2:$AN$1501,38,0)} -> 0.28423439 | M20: 0.1 | N20: {=ROUND(($F$17+F20)*M20,-3)} -> 1380000 | P20: {=($F$17+F20)/14500} -> 951.37931 | R20: {=IF((C20-VLOOKUP(B20,'Private Boats 2026 Target'!$C$2:$AJ$714,32,0))<0,0,(C20-VLOOKUP(B20,'Private Boats 2026 Target'!$C$2:$AJ$714,32,0)))} -> 0 | Z20: {=($F$17+F20+($E$89-$E$88)-200000)*0.9} -> 12496500
A21: O | B21: {='Boats Data Sheet 2025'!C4} -> Riki J | C21: {=IF(ROUNDUP((AVERAGE('Private Boats 2026 Target'!AC28:AC45)-$C$17),-2)<0,0,ROUNDUP((AVERAGE('Private Boats 2026 Target'!AC28:AC45)-$C$17),-2))} -> 1886000 | D21: {=14500000-D17} -> 2205000 | E21: {=D21*110%} -> 2425500 | F21: 2700000 | G21: {=_xlfn.IFERROR((D21-F21),"not listed")} -> -495000 | H21: {=IF(A21="O",ROUND((F21+$F$17)/0.9-$F$17,-3),F21)} -> 4366000 | I21: {=$F$17+F21} -> 14995000 | K21: {=$F$17+F21-VLOOKUP(B21,'Private Boats 2026 Target'!$C$2:$AN$1501,38,0)} -> 3698814.7 | L21: {=K21/VLOOKUP(B21,'Private Boats 2026 Target'!$C$2:$AN$1501,38,0)} -> 0.32743927 | M21: 0.1 | N21: {=ROUND(($F$17+F21)*M21,-3)} -> 1500000 | P21: {=($F$17+F21)/14500} -> 1034.1379 | R21: {=IF((C21-VLOOKUP(B21,'Private Boats 2026 Target'!$C$2:$AJ$714,32,0))<0,0,(C21-VLOOKUP(B21,'Private Boats 2026 Target'!$C$2:$AJ$714,32,0)))} -> 0 | Z21: {=($F$17+F21+($E$89-$E$88)-200000)*0.95} -> 14330750
A22: O | B22: {='Boats Data Sheet 2025'!C11} -> Sanjaya | C22: {=IF(ROUNDUP((AVERAGE('Private Boats 2026 Target'!AC51:AC68)-$C$17),-2)<0,0,ROUNDUP((AVERAGE('Private Boats 2026 Target'!AC51:AC68)-$C$17),-2))} -> 614400 | D22: {=ROUNDUP(C22,-4)} -> 620000 | E22: {=D22*110%} -> 682000 | F22: 820000 | G22: {=_xlfn.IFERROR((D22-F22),"not listed")} -> -200000 | H22: {=IF(A22="O",ROUND((F22+$F$17)/0.9-$F$17,-3),F22)} -> 2277000 | I22: {=$F$17+F22} -> 13115000 | K22: {=$F$17+F22-VLOOKUP(B22,'Private Boats 2026 Target'!$C$2:$AN$1501,38,0)} -> 2744552.8 | L22: {=K22/VLOOKUP(B22,'Private Boats 2026 Target'!$C$2:$AN$1501,38,0)} -> 0.26465135 | M22: 0.1 | N22: {=ROUND(($F$17+F22)*M22,-3)} -> 1312000 | P22: {=($F$17+F22)/14500} -> 904.48276 | R22: {=IF((C22-VLOOKUP(B22,'Private Boats 2026 Target'!$C$2:$AJ$714,32,0))<0,0,(C22-VLOOKUP(B22,'Private Boats 2026 Target'!$C$2:$AJ$714,32,0)))} -> 0 | Z22: {=($F$17+F22+($E$89-$E$88)-200000)*0.95} -> 12544750
A23: O | B23: {='Boats Data Sheet 2025'!C24} -> Lady Manta | C23: {=IF(ROUNDUP((AVERAGE('Shared Boats 2026 Target'!AD143:AD148)-$C$17),-2)<0,0,ROUNDUP((AVERAGE('Shared Boats 2026 Target'!AD143:AD148)-$C$17),-2))} -> 0 | D23: {=ROUNDUP(C23,-4)} -> 0 | E23: {=D23*110%} -> 0 | F23: 1200000 | G23: {=_xlfn.IFERROR((D23-F23),"not listed")} -> -1200000 | H23: {=IF(A23="O",ROUND((F23+$F$17)/0.9-$F$17,-3),F23)} -> 2699000 | I23: {=$F$17+F23} -> 13495000 | K23: {=$F$17+F23-AVERAGE('Shared Boats 2026 Target'!Z143:AA148)} -> 5167952.6 | L23: {=K23/AVERAGE('Shared Boats 2026 Target'!AA143:AA148)} -> 0.62062246 | M23: 0.1 | N23: {=ROUND(($F$17+F23)*M23,-3)} -> 1350000 | P23: {=($F$17+F23)/14500} -> 930.68966 | Z23: {=($F$17+F23+($E$89-$E$88)-200000)*0.9} -> 12226500
A24: O | B24: {='Boats Data Sheet 2025'!C12} -> Jayanadi | C24: {=IF(ROUNDUP((AVERAGE('Private Boats 2026 Target'!AC74:AC91)-$C$17),-2)<0,0,ROUNDUP((AVERAGE('Private Boats 2026 Target'!AC74:AC91)-$C$17),-2))} -> 1894500 | D24: {=13000000-D17} -> 705000 | E24: {=D24*110%} -> 775500 | F24: 1835000 | G24: {=_xlfn.IFERROR((D24-F24),"not listed")} -> -1130000 | H24: {=IF(A24="O",ROUND((F24+$F$17)/0.9-$F$17,-3),F24)} -> 3405000 | I24: {=$F$17+F24} -> 14130000 | K24: {=$F$17+F24-VLOOKUP(B24,'Private Boats 2026 Target'!$C$2:$AN$1501,38,0)} -> 2739552.8 | L24: {=K24/VLOOKUP(B24,'Private Boats 2026 Target'!$C$2:$AN$1501,38,0)} -> 0.2405132 | M24: 0.1 | N24: {=ROUND(($F$17+F24)*M24,-3)} -> 1413000 | P24: {=($F$17+F24)/14500} -> 974.48276 | R24: {=IF((C24-VLOOKUP(B24,'Private Boats 2026 Target'!$C$2:$AJ$714,32,0))<0,0,(C24-VLOOKUP(B24,'Private Boats 2026 Target'!$C$2:$AJ$714,32,0)))} -> 36437.5 | Z24: {=($F$17+F24+($E$89-$E$88)-200000)*0.95} -> 13509000
A25: O | B25: {='Boats Data Sheet 2025'!C13} -> Sea Dragon | C25: {=IF(ROUNDUP((AVERAGE('Private Boats 2026 Target'!AC97:AC114)-$C$17),-2)<0,0,ROUNDUP((AVERAGE('Private Boats 2026 Target'!AC97:AC114)-$C$17),-2))} -> 614400 | D25: {=ROUNDUP(C25,-4)} -> 620000 | E25: {=D25*110%} -> 682000 | F25: 820000 | G25: {=_xlfn.IFERROR((D25-F25),"not listed")} -> -200000 | H25: {=IF(A25="O",ROUND((F25+$F$17)/0.9-$F$17,-3),F25)} -> 2277000 | I25: {=$F$17+F25} -> 13115000 | K25: {=$F$17+F25-VLOOKUP(B25,'Private Boats 2026 Target'!$C$2:$AN$1501,38,0)} -> 2744552.8 | L25: {=K25/VLOOKUP(B25,'Private Boats 2026 Target'!$C$2:$AN$1501,38,0)} -> 0.26465135 | M25: 0.1 | N25: {=ROUND(($F$17+F25)*M25,-3)} -> 1312000 | P25: {=($F$17+F25)/14500} -> 904.48276 | R25: {=IF((C25-VLOOKUP(B25,'Private Boats 2026 Target'!$C$2:$AJ$714,32,0))<0,0,(C25-VLOOKUP(B25,'Private Boats 2026 Target'!$C$2:$AJ$714,32,0)))} -> 0 | Z25: {=($F$17+F25+($E$89-$E$88)-200000)*0.95} -> 12544750
A26: O | B26: Sanjaya O4 | C26: {=IF(ROUNDUP((AVERAGE('Private Boats 2026 Target'!AC916:AC933)-$C$17),-2)<0,0,ROUNDUP((AVERAGE('Private Boats 2026 Target'!AC916:AC933)-$C$17),-2))} -> 3359500 | D26: {=ROUNDUP(C26,-4)} -> 3360000 | E26: {=D26*110%} -> 3696000 | F26: 4460000 | G26: {=_xlfn.IFERROR((D26-F26),"not listed")} -> -1100000 | H26: {=IF(A26="O",ROUND((F26+$F$17)/0.9-$F$17,-3),F26)} -> 6322000 | I26: {=$F$17+F26} -> 16755000 | K26: {=$F$17+F26-VLOOKUP(B26,'Private Boats 2026 Target'!$C$2:$AN$1501,38,0)} -> 4284719.5 | L26: {=K26/VLOOKUP(B26,'Private Boats 2026 Target'!$C$2:$AN$1501,38,0)} -> 0.34359448 | M26: 0.1 | N26: {=ROUND(($F$17+F26)*M26,-3)} -> 1676000 | P26: {=($F$17+F26)/14500} -> 1155.5172 | R26: {=IF((C26-VLOOKUP(B26,'Private Boats 2026 Target'!$C$2:$AJ$714,32,0))<0,0,(C26-VLOOKUP(B26,'Private Boats 2026 Target'!$C$2:$AJ$714,32,0)))} | Z26: {=($F$17+F26+($E$89-$E$88)-200000)*0.95} -> 16002750
A27: O | B27: Sanjaya O5 | C27: {=IF(ROUNDUP((AVERAGE('Private Boats 2026 Target'!AC962:AC979)-$C$17),-2)<0,0,ROUNDUP((AVERAGE('Private Boats 2026 Target'!AC962:AC979)-$C$17),-2))} -> 3359500 | D27: {=ROUNDUP(C27,-4)} -> 3360000 | E27: {=D27*110%} -> 3696000 | F27: 4460000 | G27: {=_xlfn.IFERROR((D27-F27),"not listed")} -> -1100000 | H27: {=IF(A27="O",ROUND((F27+$F$17)/0.9-$F$17,-3),F27)} -> 6322000 | I27: {=$F$17+F27} -> 16755000 | K27: {=$F$17+F27-VLOOKUP(B27,'Private Boats 2026 Target'!$C$2:$AN$1501,38,0)} -> 4284719.5 | L27: {=K27/VLOOKUP(B27,'Private Boats 2026 Target'!$C$2:$AN$1501,38,0)} -> 0.34359448 | M27: 0.1 | N27: {=ROUND(($F$17+F27)*M27,-3)} -> 1676000 | P27: {=($F$17+F27)/14500} -> 1155.5172 | R27: {=IF((C27-VLOOKUP(B27,'Private Boats 2026 Target'!$C$2:$AJ$714,32,0))<0,0,(C27-VLOOKUP(B27,'Private Boats 2026 Target'!$C$2:$AJ$714,32,0)))} | Z27: {=($F$17+F27+($E$89-$E$88)-200000)*0.95} -> 16002750
A28: O | B28: Almond Milk | C28: {=IF(ROUNDUP((AVERAGE('Private Boats 2026 Target'!AC1008:AC1025)-$C$17),-2)<0,0,ROUNDUP((AVERAGE('Private Boats 2026 Target'!AC1008:AC1025)-$C$17),-2))} -> 1085000 | D28: {=ROUNDUP(C28,-4)} -> 1090000 | E28: {=D28*110%} -> 1199000 | F28: 4160000 | G28: {=_xlfn.IFERROR((D28-F28),"not listed")} -> -3070000 | H28: {=IF(A28="O",ROUND((F28+$F$17)/0.9-$F$17,-3),F28)} -> 5988000 | I28: {=$F$17+F28} -> 16455000 | K28: {=$F$17+F28-VLOOKUP(B28,'Private Boats 2026 Target'!$C$2:$AN$1501,38,0)} -> 5797112.6 | L28: {=K28/VLOOKUP(B28,'Private Boats 2026 Target'!$C$2:$AN$1501,38,0)} -> 0.54392698 | M28: 0.1 | N28: {=ROUND(($F$17+F28)*M28,-3)} -> 1646000 | P28: {=($F$17+F28)/14500} -> 1134.8276 | R28: {=IF((C28-VLOOKUP(B28,'Private Boats 2026 Target'!$C$2:$AJ$714,32,0))<0,0,(C28-VLOOKUP(B28,'Private Boats 2026 Target'!$C$2:$AJ$714,32,0)))} | Z28: {=($F$17+F28+($E$89-$E$88)-200000)*0.9} -> 14890500
A29: O | B29: Honey Milk | C29: {=IF(ROUNDUP((AVERAGE('Private Boats 2026 Target'!AC1031:AC1048)-$C$17),-2)<0,0,ROUNDUP((AVERAGE('Private Boats 2026 Target'!AC1031:AC1048)-$C$17),-2))} -> 1085000 | D29: {=ROUNDUP(C29,-4)} -> 1090000 | E29: {=D29*110%} -> 1199000 | F29: 4160000 | G29: {=_xlfn.IFERROR((D29-F29),"not listed")} -> -3070000 | H29: {=IF(A29="O",ROUND((F29+$F$17)/0.9-$F$17,-3),F29)} -> 5988000 | I29: {=$F$17+F29} -> 16455000 | K29: {=$F$17+F29-VLOOKUP(B29,'Private Boats 2026 Target'!$C$2:$AN$1501,38,0)} -> 5797112.6 | L29: {=K29/VLOOKUP(B29,'Private Boats 2026 Target'!$C$2:$AN$1501,38,0)} -> 0.54392698 | M29: 0.1 | N29: {=ROUND(($F$17+F29)*M29,-3)} -> 1646000 | P29: {=($F$17+F29)/14500} -> 1134.8276 | R29: {=IF((C29-VLOOKUP(B29,'Private Boats 2026 Target'!$C$2:$AJ$714,32,0))<0,0,(C29-VLOOKUP(B29,'Private Boats 2026 Target'!$C$2:$AJ$714,32,0)))} | Z29: {=($F$17+F29+($E$89-$E$88)-200000)*0.9} -> 14890500
A30: O | B30: Eldorado 1 | C30: {=IF(ROUNDUP((AVERAGE('Private Boats 2026 Target'!AC1054:AC1071)-$C$17),-2)<0,0,ROUNDUP((AVERAGE('Private Boats 2026 Target'!AC1054:AC1071)-$C$17),-2))} -> 745700 | D30: {=ROUNDUP(C30,-4)} -> 750000 | E30: {=D30*110%} -> 825000 | F30: 4160000 | G30: {=_xlfn.IFERROR((D30-F30),"not listed")} -> -3410000 | H30: {=IF(A30="O",ROUND((F30+$F$17)/0.9-$F$17,-3),F30)} -> 5988000 | I30: {=$F$17+F30} -> 16455000 | K30: {=$F$17+F30-VLOOKUP(B30,'Private Boats 2026 Target'!$C$2:$AN$1501,38,0)} -> 6067457.4 | L30: {=K30/VLOOKUP(B30,'Private Boats 2026 Target'!$C$2:$AN$1501,38,0)} -> 0.58410903 | M30: 0.1 | N30: {=ROUND(($F$17+F30)*M30,-3)} -> 1646000 | P30: {=($F$17+F30)/14500} -> 1134.8276 | R30: {=IF((C30-VLOOKUP(B30,'Private Boats 2026 Target'!$C$2:$AJ$714,32,0))<0,0,(C30-VLOOKUP(B30,'Private Boats 2026 Target'!$C$2:$AJ$714,32,0)))} | Z30: {=($F$17+F30+($E$89-$E$88)-200000)*0.9} -> 14890500
A31: O | B31: Eldorado 2 - Arya | C31: {=IF(ROUNDUP((AVERAGE('Private Boats 2026 Target'!AC1077:AC1094)-$C$17),-2)<0,0,ROUNDUP((AVERAGE('Private Boats 2026 Target'!AC1100:AC1117)-$C$17),-2))} -> 986400 | D31: {=ROUNDUP(C31,-4)} -> 990000 | E31: {=D31*110%} -> 1089000 | F31: 4160000 | G31: {=_xlfn.IFERROR((D31-F31),"not listed")} -> -3170000 | H31: {=IF(A31="O",ROUND((F31+$F$17)/0.9-$F$17,-3),F31)} -> 5988000 | I31: {=$F$17+F31} -> 16455000 | K31: {=$F$17+F31-VLOOKUP(B31,'Private Boats 2026 Target'!$C$2:$AN$1501,38,0)} -> 5875613 | L31: {=K31/VLOOKUP(B31,'Private Boats 2026 Target'!$C$2:$AN$1501,38,0)} -> 0.55538312 | M31: 0.1 | N31: {=ROUND(($F$17+F31)*M31,-3)} -> 1646000 | P31: {=($F$17+F31)/14500} -> 1134.8276 | R31: {=IF((C31-VLOOKUP(B31,'Private Boats 2026 Target'!$C$2:$AJ$714,32,0))<0,0,(C31-VLOOKUP(B31,'Private Boats 2026 Target'!$C$2:$AJ$714,32,0)))} | Z31: {=($F$17+F31+($E$89-$E$88)-200000)*0.9} -> 14890500
A32: O | B32: Eldorado 3 - Evgenii | C32: {=IF(ROUNDUP((AVERAGE('Private Boats 2026 Target'!AC1100:AC1117)-$C$17),-2)<0,0,ROUNDUP((AVERAGE('Private Boats 2026 Target'!AC1100:AC1117)-$C$17),-2))} -> 986400 | D32: {=ROUNDUP(C32,-4)} -> 990000 | E32: {=D32*110%} -> 1089000 | F32: 4160000 | G32: {=_xlfn.IFERROR((D32-F32),"not listed")} -> -3170000 | H32: {=IF(A32="O",ROUND((F32+$F$17)/0.9-$F$17,-3),F32)} -> 5988000 | I32: {=$F$17+F32} -> 16455000 | K32: {=$F$17+F32-VLOOKUP(B32,'Private Boats 2026 Target'!$C$2:$AN$1501,38,0)} -> 5875613 | L32: {=K32/VLOOKUP(B32,'Private Boats 2026 Target'!$C$2:$AN$1501,38,0)} -> 0.55538312 | M32: 0.1 | N32: {=ROUND(($F$17+F32)*M32,-3)} -> 1646000 | P32: {=($F$17+F32)/14500} -> 1134.8276 | R32: {=IF((C32-VLOOKUP(B32,'Private Boats 2026 Target'!$C$2:$AJ$714,32,0))<0,0,(C32-VLOOKUP(B32,'Private Boats 2026 Target'!$C$2:$AJ$714,32,0)))} | Z32: {=($F$17+F32+($E$89-$E$88)-200000)*0.9} -> 14890500
A33: O | B33: Eldorado 4 - Vadim | C33: {=IF(ROUNDUP((AVERAGE('Private Boats 2026 Target'!AC1123:AC1140)-$C$17),-2)<0,0,ROUNDUP((AVERAGE('Private Boats 2026 Target'!AC1123:AC1140)-$C$17),-2))} -> 1431200 | D33: {=ROUNDUP(C33,-4)} -> 1440000 | E33: {=D33*110%} -> 1584000 | F33: 4160000 | G33: {=_xlfn.IFERROR((D33-F33),"not listed")} -> -2720000 | H33: {=IF(A33="O",ROUND((F33+$F$17)/0.9-$F$17,-3),F33)} -> 5988000 | I33: {=$F$17+F33} -> 16455000 | K33: {=$F$17+F33-VLOOKUP(B33,'Private Boats 2026 Target'!$C$2:$AN$1501,38,0)} -> 5521186.6 | L33: {=K33/VLOOKUP(B33,'Private Boats 2026 Target'!$C$2:$AN$1501,38,0)} -> 0.50496441 | M33: 0.1 | N33: {=ROUND(($F$17+F33)*M33,-3)} -> 1646000 | P33: {=($F$17+F33)/14500} -> 1134.8276 | R33: {=IF((C33-VLOOKUP(B33,'Private Boats 2026 Target'!$C$2:$AJ$714,32,0))<0,0,(C33-VLOOKUP(B33,'Private Boats 2026 Target'!$C$2:$AJ$714,32,0)))} | Z33: {=($F$17+F33+($E$89-$E$88)-200000)*0.9} -> 14890500
B34: Eldorado 5 - Robert | C34: {=IF(ROUNDUP((AVERAGE('Private Boats 2026 Target'!AC1286:AC1303)-$C$17),-2)<0,0,ROUNDUP((AVERAGE('Private Boats 2026 Target'!AC1286:AC1303)-$C$17),-2))} -> 4438800 | D34: {=ROUNDUP(C34,-4)} -> 4440000 | E34: {=D34*110%} -> 4884000 | F34: 4160000 | G34: {=_xlfn.IFERROR((D34-F34),"not listed")} -> 280000 | H34: {=IF(A34="O",ROUND((F34+$F$17)/0.9-$F$17,-3),F34)} -> 4160000 | I34: {=$F$17+F34} -> 16455000 | K34: {=$F$17+F34-VLOOKUP(B34,'Private Boats 2026 Target'!$C$2:$AN$1501,38,0)} -> 3124719.5 | L34: {=K34/VLOOKUP(B34,'Private Boats 2026 Target'!$C$2:$AN$1501,38,0)} -> 0.23440763 | M34: 0.1 | N34: {=ROUND(($F$17+F34)*M34,-3)} -> 1646000 | P34: {=($F$17+F34)/14500} -> 1134.8276 | R34: {=IF((C34-VLOOKUP(B34,'Private Boats 2026 Target'!$C$2:$AJ$714,32,0))<0,0,(C34-VLOOKUP(B34,'Private Boats 2026 Target'!$C$2:$AJ$714,32,0)))} | Z34: {=($F$17+F34+($E$89-$E$88)-200000)*0.9} -> 14890500
B35: Eldorado 6 - Vadim | C35: {=IF(ROUNDUP((AVERAGE('Private Boats 2026 Target'!AC1309:AC1326)-$C$17),-2)<0,0,ROUNDUP((AVERAGE('Private Boats 2026 Target'!AC1309:AC1326)-$C$17),-2))} -> 4438800 | D35: {=ROUNDUP(C35,-4)} -> 4440000 | E35: {=D35*110%} -> 4884000 | F35: 4160000 | G35: {=_xlfn.IFERROR((D35-F35),"not listed")} -> 280000 | H35: {=IF(A35="O",ROUND((F35+$F$17)/0.9-$F$17,-3),F35)} -> 4160000 | I35: {=$F$17+F35} -> 16455000 | K35: {=$F$17+F35-VLOOKUP(B35,'Private Boats 2026 Target'!$C$2:$AN$1501,38,0)} -> 3124719.5 | L35: {=K35/VLOOKUP(B35,'Private Boats 2026 Target'!$C$2:$AN$1501,38,0)} -> 0.23440763 | M35: 0.1 | N35: {=ROUND(($F$17+F35)*M35,-3)} -> 1646000 | P35: {=($F$17+F35)/14500} -> 1134.8276 | R35: {=IF((C35-VLOOKUP(B35,'Private Boats 2026 Target'!$C$2:$AJ$714,32,0))<0,0,(C35-VLOOKUP(B35,'Private Boats 2026 Target'!$C$2:$AJ$714,32,0)))} | Z35: {=($F$17+F35+($E$89-$E$88)-200000)*0.9} -> 14890500
B36: Boat Angels | C36: {=IF(ROUNDUP((AVERAGE('Private Boats 2026 Target'!AC1263:AC1280)-$C$17),-2)<0,0,ROUNDUP((AVERAGE('Private Boats 2026 Target'!AC1263:AC1280)-$C$17),-2))} -> 0 | D36: {=ROUNDUP(C36,-4)} -> 0 | E36: {=D36*110%} -> 0 | F36: 4160000 | G36: {=_xlfn.IFERROR((D36-F36),"not listed")} -> -4160000 | H36: {=IF(A36="O",ROUND((F36+$F$17)/0.9-$F$17,-3),F36)} -> 4160000 | I36: {=$F$17+F36} -> 16455000 | K36: {=$F$17+F36-VLOOKUP(B36,'Private Boats 2026 Target'!$C$2:$AN$1501,38,0)} -> 6847319.5 | L36: {=K36/VLOOKUP(B36,'Private Boats 2026 Target'!$C$2:$AN$1501,38,0)} -> 0.71269226 | M36: 0.1 | N36: {=ROUND(($F$17+F36)*M36,-3)} -> 1646000 | P36: {=($F$17+F36)/14500} -> 1134.8276 | R36: {=IF((C36-VLOOKUP(B36,'Private Boats 2026 Target'!$C$2:$AJ$714,32,0))<0,0,(C36-VLOOKUP(B36,'Private Boats 2026 Target'!$C$2:$AJ$714,32,0)))} | Z36: {=($F$17+F36+($E$89-$E$88)-200000)*0.9} -> 14890500
A37: D | B37: {='Boats Data Sheet 2025'!C19} -> Seven Heaven | C37: {=IF(ROUNDUP((AVERAGE('Private Boats 2026 Target'!AC120:AC139)-$C$17),-2)<0,0,ROUNDUP((AVERAGE('Private Boats 2026 Target'!AC120:AC139)-$C$17),-2))} -> 2304300 | D37: {=26000000-D17} -> 13705000 | E37: {=D37*110%} -> 15075500 | F37: Delisted | G37: Delisted | H37: Delisted | I37: Delisted | K37: Delisted | L37: Delisted | M37: Delisted | N37: Delisted | P37: Delisted | R37: Delisted
A38: D | B38: {='Boats Data Sheet 2025'!C20} -> Mironia | C38: {=IF(ROUNDUP((AVERAGE('Private Boats 2026 Target'!AC145:AC162)-$C$17),-2)<0,0,ROUNDUP((AVERAGE('Private Boats 2026 Target'!AC145:AC162)-$C$17),-2))} -> 4908400 | D38: {=ROUNDUP(C38,-4)} -> 4910000 | E38: {=D38*110%} -> 5401000 | F38: Delisted | G38: Delisted | H38: Delisted | I38: Delisted | K38: Delisted | L38: Delisted | M38: Delisted | N38: Delisted | P38: Delisted | R38: Delisted
A39: O | B39: {='Boats Data Sheet 2025'!C21} -> Little Star | C39: {=IF(ROUNDUP((AVERAGE('Private Boats 2026 Target'!AC168:AC185)-$C$17),-2)<0,0,ROUNDUP((AVERAGE('Private Boats 2026 Target'!AC168:AC185)-$C$17),-2))} -> 6400 | D39: {=ROUNDUP(C39,-4)} -> 10000 | E39: {=D39*110%} -> 11000 | F39: -1000000 | G39: {=_xlfn.IFERROR((D39-F39),"not listed")} -> 1010000 | H39: {=IF(A39="O",ROUND((F39+$F$17)/0.9-$F$17,-3),F39)} -> 255000 | I39: {=$F$17+F39} -> 11295000 | K39: {=$F$17+F39-VLOOKUP(B39,'Private Boats 2026 Target'!$C$2:$AN$1501,38,0)} -> 1409052.8 | L39: {=K39/VLOOKUP(B39,'Private Boats 2026 Target'!$C$2:$AN$1501,38,0)} -> 0.14253089 | M39: No fee | N39: No fee | P39: {=($F$17+F39)/14500} -> 778.96552 | R39: {=IF((C39-VLOOKUP(B39,'Private Boats 2026 Target'!$C$2:$AJ$714,32,0))<0,0,(C39-VLOOKUP(B39,'Private Boats 2026 Target'!$C$2:$AJ$714,32,0)))} -> 6400 | Z39: {=($F$17+F39+($E$89-$E$88)-200000)*0.95} -> 10815750 | AA39: Notes KT:
A40: P | B40: {='Boats Data Sheet 2025'!C22} -> Rara | C40: {=IF(ROUNDUP((AVERAGE('Private Boats 2026 Target'!AC191:AC208)-$C$17),-2)<0,0,ROUNDUP((AVERAGE('Private Boats 2026 Target'!AC191:AC208)-$C$17),-2))} -> 1670500 | D40: {=ROUNDUP(C40,-4)} -> 1680000 | E40: {=D40*110%} -> 1848000 | F40: 1740000 | G40: {=_xlfn.IFERROR((D40-F40),"not listed")} -> -60000 | H40: {=IF(A40="O",ROUND((F40+$F$17)/0.9-$F$17,-3),F40)} -> 1740000 | I40: {=$F$17+F40} -> 14035000 | K40: {=$F$17+F40-VLOOKUP(B40,'Private Boats 2026 Target'!$C$2:$AN$1501,38,0)} -> 2823052.8 | L40: {=K40/VLOOKUP(B40,'Private Boats 2026 Target'!$C$2:$AN$1501,38,0)} -> 0.2517897 | M40: No fee | N40: No fee | P40: {=($F$17+F40)/14500} -> 967.93103 | R40: {=IF((C40-VLOOKUP(B40,'Private Boats 2026 Target'!$C$2:$AJ$714,32,0))<0,0,(C40-VLOOKUP(B40,'Private Boats 2026 Target'!$C$2:$AJ$714,32,0)))} -> 233875 | AA40: Rara was decreased by 1.3 jt. as recommended (old boat with too many complains) -> confirmed with Viod and Rozen
A41: O | B41: {='Boats Data Sheet 2025'!C23} -> Small Sweetheart | C41: {=IF(ROUNDUP((AVERAGE('Private Boats 2026 Target'!AC214:AC231)-$C$17),-2)<0,0,ROUNDUP((AVERAGE('Private Boats 2026 Target'!AC214:AC231)-$C$17),-2))} -> 0 | D41: {=ROUNDUP(C41,-4)} -> 0 | E41: {=D41*110%} -> 0 | F41: -1100000 | G41: {=_xlfn.IFERROR((D41-F41),"not listed")} -> 1100000 | H41: {=IF(A41="O",ROUND((F41+$F$17)/0.9-$F$17,-3),F41)} -> 144000 | I41: {=$F$17+F41} -> 11195000 | K41: {=$F$17+F41-VLOOKUP(B41,'Private Boats 2026 Target'!$C$2:$AN$1501,38,0)} -> 1615052.8 | L41: {=K41/VLOOKUP(B41,'Private Boats 2026 Target'!$C$2:$AN$1501,38,0)} -> 0.16858682 | M41: No fee | N41: No fee | P41: {=($F$17+F41)/14500} -> 772.06897 | R41: {=IF((C41-VLOOKUP(B41,'Private Boats 2026 Target'!$C$2:$AJ$714,32,0))<0,0,(C41-VLOOKUP(B41,'Private Boats 2026 Target'!$C$2:$AJ$714,32,0)))} -> 0 | Z41: {=($F$17+F41+($E$89-$E$88)-200000)*0.95} -> 10720750
A42: O | B42: {='Boats Data Sheet 2025'!C26} -> Dedean | C42: {=IF(ROUNDUP((AVERAGE('Private Boats 2026 Target'!AC237:AC254)-$C$17),-2)<0,0,ROUNDUP((AVERAGE('Private Boats 2026 Target'!AC237:AC254)-$C$17),-2))} -> 710400 | D42: {=14500000-D17} -> 2205000 | E42: {=D42*110%} -> 2425500 | F42: Delisted | G42: Delisted | H42: Delisted | I42: Delisted | K42: Delisted | L42: Delisted | M42: Delisted | N42: Delisted | P42: {=($F$17+F42)/14500} | R42: {=IF((C42-VLOOKUP(B42,'Private Boats 2026 Target'!$C$2:$AJ$714,32,0))<0,0,(C42-VLOOKUP(B42,'Private Boats 2026 Target'!$C$2:$AJ$714,32,0)))} -> 0
A43: P | B43: {='Boats Data Sheet 2025'!C27} -> King Fish | C43: {=IF(ROUNDUP((AVERAGE('Private Boats 2026 Target'!AC260:AC277)-$C$17),-2)<0,0,ROUNDUP((AVERAGE('Private Boats 2026 Target'!AC260:AC277)-$C$17),-2))} -> 11948900 | D43: {=ROUNDUP(C43,-4)} -> 11950000 | E43: {=D43*110%} -> 13145000 | F43: 10840000 | G43: {=_xlfn.IFERROR((D43-F43),"not listed")} -> 1110000 | H43: {=IF(A43="O",ROUND((F43+$F$17)/0.9-$F$17,-3),F43)} -> 10840000 | I43: {=$F$17+F43} -> 23135000 | K43: {=$F$17+F43-VLOOKUP(B43,'Private Boats 2026 Target'!$C$2:$AN$1501,38,0)} -> 3733052.8 | L43: {=K43/VLOOKUP(B43,'Private Boats 2026 Target'!$C$2:$AN$1501,38,0)} -> 0.19240609 | M43: 0.05 | N43: {=ROUND(($F$17+F43)*M43,-3)} -> 1157000 | P43: {=($F$17+F43)/14500} -> 1595.5172 | R43: {=IF((C43-VLOOKUP(B43,'Private Boats 2026 Target'!$C$2:$AJ$714,32,0))<0,0,(C43-VLOOKUP(B43,'Private Boats 2026 Target'!$C$2:$AJ$714,32,0)))} -> 10184471 | AA43: Increased by 1.5 jt. tho we still accept it's a lower margin boat -> to follow up bookings stats in May -> confirmed with Void
A44: O | B44: {='Boats Data Sheet 2025'!C28} -> Big Little Star | C44: {=IF(ROUNDUP((AVERAGE('Private Boats 2026 Target'!AC283:AC300)-$C$17),-2)<0,0,ROUNDUP((AVERAGE('Private Boats 2026 Target'!AC283:AC300)-$C$17),-2))} -> 652100 | D44: {=ROUNDUP(C44,-4)} -> 660000 | E44: {=D44*110%} -> 726000 | F44: 920000 | G44: {=_xlfn.IFERROR((D44-F44),"not listed")} -> -260000 | H44: {=IF(A44="O",ROUND((F44+$F$17)/0.9-$F$17,-3),F44)} -> 2388000 | I44: {=$F$17+F44} -> 13215000 | K44: {=$F$17+F44-VLOOKUP(B44,'Private Boats 2026 Target'!$C$2:$AN$1501,38,0)} -> 2814552.8 | L44: {=K44/VLOOKUP(B44,'Private Boats 2026 Target'!$C$2:$AN$1501,38,0)} -> 0.27061845 | M44: 0.1 | N44: {=ROUND(($F$17+F44)*M44,-3)} -> 1322000 | P44: {=($F$17+F44)/14500} -> 911.37931 | R44: {=IF((C44-VLOOKUP(B44,'Private Boats 2026 Target'!$C$2:$AJ$714,32,0))<0,0,(C44-VLOOKUP(B44,'Private Boats 2026 Target'!$C$2:$AJ$714,32,0)))} -> 652100 | Z44: {=($F$17+F44+($E$89-$E$88)-200000)*0.95} -> 12639750
A45: P | B45: {='Boats Data Sheet 2025'!C29} -> Dhea | C45: {=IF(ROUNDUP((AVERAGE('Private Boats 2026 Target'!AC306:AC323)-$C$17),-2)<0,0,ROUNDUP((AVERAGE('Private Boats 2026 Target'!AC306:AC323)-$C$17),-2))} -> 3628300 | D45: {=ROUNDUP(C45,-4)} -> 3630000 | E45: {=D45*110%} -> 3993000 | F45: 3340000 | G45: {=_xlfn.IFERROR((D45-F45),"not listed")} -> 290000 | H45: {=IF(A45="O",ROUND((F45+$F$17)/0.9-$F$17,-3),F45)} -> 3340000 | I45: {=$F$17+F45} -> 15635000 | K45: {=$F$17+F45-VLOOKUP(B45,'Private Boats 2026 Target'!$C$2:$AN$1501,38,0)} -> 2863052.8 | L45: {=K45/VLOOKUP(B45,'Private Boats 2026 Target'!$C$2:$AN$1501,38,0)} -> 0.22416729 | M45: 0.1 | N45: {=ROUND(($F$17+F45)*M45,-3)} -> 1564000 | P45: {=($F$17+F45)/14500} -> 1078.2759 | R45: {=IF((C45-VLOOKUP(B45,'Private Boats 2026 Target'!$C$2:$AJ$714,32,0))<0,0,(C45-VLOOKUP(B45,'Private Boats 2026 Target'!$C$2:$AJ$714,32,0)))} -> 1770237.5 | AA45: Decrease by 1.5 jt. On website
A46: D | B46: {='Boats Data Sheet 2025'!C30} -> Big Blue | C46: {=IF(ROUNDUP((AVERAGE('Private Boats 2026 Target'!AC329:AC346)-$C$17),-2)<0,0,ROUNDUP((AVERAGE('Private Boats 2026 Target'!AC329:AC346)-$C$17),-2))} -> 0 | D46: {=ROUNDUP(C46,-4)} -> 0 | E46: {=D46*110%} -> 0 | F46: Delisted | G46: Delisted | H46: Delisted | I46: Delisted | K46: Delisted | L46: Delisted | M46: Delisted | N46: Delisted | P46: {=($F$17+F46)/14500} | R46: {=IF((C46-VLOOKUP(B46,'Private Boats 2026 Target'!$C$2:$AJ$714,32,0))<0,0,(C46-VLOOKUP(B46,'Private Boats 2026 Target'!$C$2:$AJ$714,32,0)))} -> 0
A47: P | B47: {='Boats Data Sheet 2025'!C31} -> Seahorse | C47: {=IF(ROUNDUP((AVERAGE('Private Boats 2026 Target'!AC352:AC369)-$C$17),-2)<0,0,ROUNDUP((AVERAGE('Private Boats 2026 Target'!AC352:AC369)-$C$17),-2))} -> 3206600 | D47: {=ROUNDUP(C47,-4)} -> 3210000 | E47: {=D47*110%} -> 3531000 | F47: {=1620000+800000} -> 2420000 | G47: {=_xlfn.IFERROR((D47-F47),"not listed")} -> 790000 | H47: {=IF(A47="O",ROUND((F47+$F$17)/0.9-$F$17,-3),F47)} -> 2420000 | I47: {=$F$17+F47} -> 14715000 | K47: {=$F$17+F47-VLOOKUP(B47,'Private Boats 2026 Target'!$C$2:$AN$1501,38,0)} -> 2279052.8 | L47: {=K47/VLOOKUP(B47,'Private Boats 2026 Target'!$C$2:$AN$1501,38,0)} -> 0.18326331 | M47: No fee | N47: No fee | P47: {=($F$17+F47)/14500} -> 1014.8276 | R47: {=IF((C47-VLOOKUP(B47,'Private Boats 2026 Target'!$C$2:$AJ$714,32,0))<0,0,(C47-VLOOKUP(B47,'Private Boats 2026 Target'!$C$2:$AJ$714,32,0)))} -> 1541016.7
A48: D | B48: {='Boats Data Sheet 2025'!C32} -> Paradise Catamaran 4h | C48: {=IF(ROUNDUP((AVERAGE('Private Boats 2026 Target'!AC375:AC392)-$C$17),-2)<0,0,ROUNDUP((AVERAGE('Private Boats 2026 Target'!AC375:AC392)-$C$17),-2))} -> 16429300 | D48: {=ROUNDUP(C48,-4)} -> 16430000 | E48: {=D48*110%} -> 18073000 | F48: Delisted | G48: Delisted | H48: Delisted | I48: Delisted | K48: Delisted | L48: Delisted | M48: Delisted | N48: Delisted | P48: Delisted | R48: {=IF((C48-VLOOKUP(B48,'Private Boats 2026 Target'!$C$2:$AJ$714,32,0))<0,0,(C48-VLOOKUP(B48,'Private Boats 2026 Target'!$C$2:$AJ$714,32,0)))} -> 16429300
A49: D | B49: {='Boats Data Sheet 2025'!C33} -> Paradise Catamaran 8h | C49: {=IF(ROUNDUP((AVERAGE('Private Boats 2026 Target'!AC398:AC415)-$C$17),-2)<0,0,ROUNDUP((AVERAGE('Private Boats 2026 Target'!AC398:AC415)-$C$17),-2))} -> 26670100 | D49: {=ROUNDUP(C49,-4)} -> 26680000 | E49: {=D49*110%} -> 29348000 | F49: Delisted | G49: Delisted | H49: Delisted | I49: Delisted | K49: Delisted | L49: Delisted | M49: Delisted | N49: Delisted | P49: Delisted | R49: {=IF((C49-VLOOKUP(B49,'Private Boats 2026 Target'!$C$2:$AJ$714,32,0))<0,0,(C49-VLOOKUP(B49,'Private Boats 2026 Target'!$C$2:$AJ$714,32,0)))} -> 26670100
A50: D | B50: {='Boats Data Sheet 2025'!C34} -> Rising | C50: {=IF(ROUNDUP((AVERAGE('Private Boats 2026 Target'!AC421:AC438)-$C$17),-2)<0,0,ROUNDUP((AVERAGE('Private Boats 2026 Target'!AC421:AC438)-$C$17),-2))} -> 7468600 | D50: {=ROUNDUP(C50,-4)} -> 7470000 | E50: {=D50*110%} -> 8217000 | F50: Delisted | G50: Delisted | H50: Delisted | I50: Delisted | K50: Delisted | L50: Delisted | M50: Delisted | N50: Delisted | P50: Delisted | R50: {=IF((C50-VLOOKUP(B50,'Private Boats 2026 Target'!$C$2:$AJ$714,32,0))<0,0,(C50-VLOOKUP(B50,'Private Boats 2026 Target'!$C$2:$AJ$714,32,0)))} -> 5803016.7 | AA50: No bookings for this boat
A51: D | B51: {='Boats Data Sheet 2025'!C35} -> Wahoo | C51: {=IF(ROUNDUP((AVERAGE('Private Boats 2026 Target'!AC444:AC461)-$C$17),-2)<0,0,ROUNDUP((AVERAGE('Private Boats 2026 Target'!AC444:AC461)-$C$17),-2))} -> 3628300 | D51: {=ROUNDUP(C51,-4)} -> 3630000 | E51: {=D51*110%} -> 3993000 | F51: Delisted | G51: Delisted | H51: Delisted | I51: Delisted | K51: Delisted | L51: Delisted | M51: Delisted | N51: Delisted | P51: {=($F$17+F51)/14500} | R51: {=IF((C51-VLOOKUP(B51,'Private Boats 2026 Target'!$C$2:$AJ$714,32,0))<0,0,(C51-VLOOKUP(B51,'Private Boats 2026 Target'!$C$2:$AJ$714,32,0)))} -> 1962716.7 | AA51: Decrease by 1.3 jt. On website
A52: P | B52: {='Boats Data Sheet 2025'!C36} -> Queen Ruizi 18 | C52: {=IF(ROUNDUP((AVERAGE('Private Boats 2026 Target'!AC467:AC484)-$C$17),-2)<0,0,ROUNDUP((AVERAGE('Private Boats 2026 Target'!AC467:AC484)-$C$17),-2))} -> 16316300 | D52: {=ROUNDUP(C52,-4)} -> 16320000 | E52: {=D52*110%} -> 17952000 | F52: 14240000 | G52: {=_xlfn.IFERROR((D52-F52),"not listed")} -> 2080000 | H52: {=IF(A52="O",ROUND((F52+$F$17)/0.9-$F$17,-3),F52)} -> 14240000 | I52: {=$F$17+F52} -> 26535000 | K52: {=$F$17+F52-VLOOKUP(B52,'Private Boats 2026 Target'!$C$2:$AN$1501,38,0)} -> 3653052.8 | L52: {=K52/VLOOKUP(B52,'Private Boats 2026 Target'!$C$2:$AN$1501,38,0)} -> 0.15964781 | M52: No fee | N52: No fee | P52: Delisted | R52: {=IF((C52-VLOOKUP(B52,'Private Boats 2026 Target'!$C$2:$AJ$714,32,0))<0,0,(C52-VLOOKUP(B52,'Private Boats 2026 Target'!$C$2:$AJ$714,32,0)))} -> 14551871 | AA52: Boat was delisted, inadequate boat owner -> confirmed with Rozen and Void
A53: P | B53: {='Boats Data Sheet 2025'!C37} -> Yacht F-13 meters | C53: {=IF(ROUNDUP((AVERAGE('Private Boats 2026 Target'!AC490:AC507)-$C$17),-2)<0,0,ROUNDUP((AVERAGE('Private Boats 2026 Target'!AC490:AC507)-$C$17),-2))} -> 13229000 | D53: {=ROUNDUP(C53,-4)} -> 13230000 | E53: {=D53*110%} -> 14553000 | F53: 11740000 | G53: {=_xlfn.IFERROR((D53-F53),"not listed")} -> 1490000 | H53: {=IF(A53="O",ROUND((F53+$F$17)/0.9-$F$17,-3),F53)} -> 11740000 | I53: {=$F$17+F53} -> 24035000 | K53: {=$F$17+F53-VLOOKUP(B53,'Private Boats 2026 Target'!$C$2:$AN$1501,38,0)} -> 3613052.8 | L53: {=K53/VLOOKUP(B53,'Private Boats 2026 Target'!$C$2:$AN$1501,38,0)} -> 0.1769201 | M53: No fee | N53: No fee | P53: {=($F$17+F53)/14500} -> 1657.5862 | R53: {=IF((C53-VLOOKUP(B53,'Private Boats 2026 Target'!$C$2:$AJ$714,32,0))<0,0,(C53-VLOOKUP(B53,'Private Boats 2026 Target'!$C$2:$AJ$714,32,0)))} -> 11563417 | W53: Yacht F-13 deacreased by 1.0 jt. And another 1.0 jt. And another 2.5 jt. | AA53: Decrease by 2.0 jt. On website
A54: O | B54: {='Boats Data Sheet 2025'!C38} -> My Darling | C54: {=IF(ROUNDUP((AVERAGE('Private Boats 2026 Target'!AC513:AC530)-$C$17),-2)<0,0,ROUNDUP((AVERAGE('Private Boats 2026 Target'!AC513:AC530)-$C$17),-2))} -> 2566600 | D54: {=12500000-D17} -> 205000 | E54: {=D54*110%} -> 225500 | F54: 1800000 | G54: {=_xlfn.IFERROR((D54-F54),"not listed")} -> -1595000 | H54: {=IF(A54="O",ROUND((F54+$F$17)/0.9-$F$17,-3),F54)} -> 3366000 | I54: {=$F$17+F54} -> 14095000 | K54: {=$F$17+F54-VLOOKUP(B54,'Private Boats 2026 Target'!$C$2:$AN$1501,38,0)} -> 2169052.8 | L54: {=K54/VLOOKUP(B54,'Private Boats 2026 Target'!$C$2:$AN$1501,38,0)} -> 0.18187678 | M54: 0.1 | N54: {=ROUND(($F$17+F54)*M54,-3)} -> 1410000 | P54: {=($F$17+F54)/14500} -> 972.06897 | R54: {=IF((C54-VLOOKUP(B54,'Private Boats 2026 Target'!$C$2:$AJ$714,32,0))<0,0,(C54-VLOOKUP(B54,'Private Boats 2026 Target'!$C$2:$AJ$714,32,0)))} -> 901016.67 | Z54: {=($F$17+F54+($E$89-$E$88)-200000)*0.95} -> 13475750 | AA54: Boat to be listed on nusapenida.one separately from Jayanadi -> TO DO: ask Geebran to make photo and list with 2.6 jt. upgrade price
A55: D | B55: {='Boats Data Sheet 2025'!C43} -> Yacht R42 | C55: {=IF(ROUNDUP((AVERAGE('Private Boats 2026 Target'!AC628:AC645)-$C$17),-2)<0,0,ROUNDUP((AVERAGE('Private Boats 2026 Target'!AC628:AC645)-$C$17),-2))} -> 11116900 | D55: {=ROUNDUP(C55,-4)} -> 11120000 | E55: {=D55*110%} -> 12232000 | F55: Delisted | G55: Delisted | H55: Delisted | I55: Delisted | K55: Delisted | L55: Delisted | M55: Delisted | N55: Delisted | P55: {=($F$17+F55)/14500} | R55: {=IF((C55-VLOOKUP(B55,'Private Boats 2026 Target'!$C$2:$AJ$714,32,0))<0,0,(C55-VLOOKUP(B55,'Private Boats 2026 Target'!$C$2:$AJ$714,32,0)))} -> 9451316.7 | AA55: This boat is listed at nusapenida.one for a variety -> don't change
A56: D | B56: {='Boats Data Sheet 2025'!C45} -> Yacht S49 | C56: {=IF(ROUNDUP((AVERAGE('Private Boats 2026 Target'!AC651:AC668)-$C$17),-2)<0,0,ROUNDUP((AVERAGE('Private Boats 2026 Target'!AC651:AC668)-$C$17),-2))} -> 18989500 | D56: {=ROUNDUP(C56,-4)} -> 18990000 | E56: {=D56*110%} -> 20889000 | F56: Delisted | G56: Delisted | H56: Delisted | I56: Delisted | K56: Delisted | L56: Delisted | M56: Delisted | N56: Delisted | P56: {=($F$17+F56)/14500} | R56: {=IF((C56-VLOOKUP(B56,'Private Boats 2026 Target'!$C$2:$AJ$714,32,0))<0,0,(C56-VLOOKUP(B56,'Private Boats 2026 Target'!$C$2:$AJ$714,32,0)))} -> 17131438
A57: P | B57: {='Boats Data Sheet 2025'!C53} -> Yacht Lux O17 | C57: {=IF(ROUNDUP((AVERAGE('Private Boats 2026 Target'!AC674:AC691)-$C$17),-2)<0,0,ROUNDUP((AVERAGE('Private Boats 2026 Target'!AC674:AC691)-$C$17),-2))} -> 29881600 | D57: {=ROUNDUP(C57,-4)} -> 29890000 | E57: {=D57*110%} -> 32879000 | F57: 28040000 | G57: {=_xlfn.IFERROR((D57-F57),"not listed")} -> 1850000 | H57: {=IF(A57="O",ROUND((F57+$F$17)/0.9-$F$17,-3),F57)} -> 28040000 | I57: {=$F$17+F57} -> 40335000 | K57: {=$F$17+F57-VLOOKUP(B57,'Private Boats 2026 Target'!$C$2:$AN$1501,38,0)} -> 6629052.8 | L57: {=K57/VLOOKUP(B57,'Private Boats 2026 Target'!$C$2:$AN$1501,38,0)} -> 0.19667309 | M57: 0.05 | N57: {=ROUND(($F$17+F57)*M57,-3)} -> 2017000 | P57: {=($F$17+F57)/14500} -> 2781.7241 | R57: {=IF((C57-VLOOKUP(B57,'Private Boats 2026 Target'!$C$2:$AJ$714,32,0))<0,0,(C57-VLOOKUP(B57,'Private Boats 2026 Target'!$C$2:$AJ$714,32,0)))} -> 28065538 | W57: Yacht T13 decreased by 1.2 jt. -> Confirmed by Void and Rozen | AA57: Yacht Lux O17 increased by 3.8 jt. -> confirmed with Void
A58: D | B58: {='Boats Data Sheet 2025'!C57} -> Yacht T13 | C58: {=IF(ROUNDUP((AVERAGE('Private Boats 2026 Target'!AC697:AC714)-$C$17),-2)<0,0,ROUNDUP((AVERAGE('Private Boats 2026 Target'!AC697:AC714)-$C$17),-2))} | D58: {=ROUNDUP(C58,-4)} | E58: {=D58*110%} | F58: Delisted | G58: Delisted | H58: Delisted | I58: Delisted | K58: Delisted | L58: Delisted | M58: Delisted | N58: Delisted | P58: {=($F$17+F58)/14500} | R58: {=IF((C58-VLOOKUP(B58,'Private Boats 2026 Target'!$C$2:$AJ$714,32,0))<0,0,(C58-VLOOKUP(B58,'Private Boats 2026 Target'!$C$2:$AJ$714,32,0)))} | AA58: Decrease by 1.1 jt. On website
A59: D | B59: Yacht Lux WL 14 | C59: {=IF(ROUNDUP((AVERAGE('Private Boats 2026 Target'!AC720:AC734)-$C$17),-2)<0,0,ROUNDUP((AVERAGE('Private Boats 2026 Target'!AC720:AC734)-$C$17),-2))} -> 16542200 | D59: {=ROUNDUP(C59,-4)} -> 16550000 | E59: {=D59*110%} -> 18205000 | F59: Delisted | G59: Delisted | H59: Delisted | I59: Delisted | K59: Delisted | L59: Delisted | M59: Delisted | N59: Delisted | P59: {=($F$17+F59)/14500} | R59: {=IF((C59-VLOOKUP(B59,'Private Boats 2026 Target'!C717:AJ737,32,0))<0,0,(C59-VLOOKUP(B59,'Private Boats 2026 Target'!C717:AJ737,32,0)))} -> 14684138 | AA59: Ok, we go with a lower margin here
A60: P | B60: Aneecha Catamaran | C60: {=IF(ROUNDUP((AVERAGE('Private Boats 2026 Target'!AC766:AC810)-$C$17),-2)<0,0,ROUNDUP((AVERAGE('Private Boats 2026 Target'!AC766:AC810)-$C$17),-2))} -> 35743700 | D60: {=ROUNDUP(C60,-4)} -> 35750000 | E60: {=D60*110%} -> 39325000 | F60: 29940000 | G60: {=_xlfn.IFERROR((D60-F60),"not listed")} -> 5810000 | H60: {=IF(A60="O",ROUND((F60+$F$17)/0.9-$F$17,-3),F60)} -> 29940000 | I60: {=$F$17+F60} -> 42235000 | K60: {=$F$17+F60-VLOOKUP(B60,'Private Boats 2026 Target'!$C$2:$AN$1501,38,0)} -> 3873052.8 | L60: {=K60/VLOOKUP(B60,'Private Boats 2026 Target'!$C$2:$AN$1501,38,0)} -> 0.1009608 | M60: No fee | N60: No fee | P60: {=($F$17+F60)/14500} -> 2912.7586
A61: D | B61: Pula Catamaran (small) | C61: {=IF(ROUNDUP((AVERAGE('Private Boats 2026 Target'!AC743:AC760)-$C$17),-2)<0,0,ROUNDUP((AVERAGE('Private Boats 2026 Target'!AC743:AC760)-$C$17),-2))} -> 16542200 | D61: {=ROUNDUP(C61,-4)} -> 16550000 | E61: {=D61*110%} -> 18205000 | F61: Delisted | G61: Delisted | H61: Delisted | I61: Delisted | K61: Delisted | L61: Delisted | M61: Delisted | N61: Delisted | P61: {=($F$17+F61)/14500}
A62: O | B62: Queen Ruizi 10 | C62: {=IF(ROUNDUP((AVERAGE('Private Boats 2026 Target'!AC817:AC836)-$C$17),-2)<0,0,ROUNDUP((AVERAGE('Private Boats 2026 Target'!AC817:AC836)-$C$17),-2))} -> 0 | D62: {=ROUNDUP(C62,-4)} -> 0 | E62: {=D62*110%} -> 0 | F62: 600000 | G62: {=_xlfn.IFERROR((D62-F62),"not listed")} -> -600000 | H62: {=IF(A62="O",ROUND((F62+$F$17)/0.9-$F$17,-3),F62)} -> 2033000 | I62: {=$F$17+F62} -> 12895000 | K62: {=$F$17+F62-VLOOKUP(B62,'Private Boats 2026 Target'!$C$2:$AN$1501,38,0)} -> 3865652.8 | L62: {=K62/VLOOKUP(B62,'Private Boats 2026 Target'!$C$2:$AN$1501,38,0)} -> 0.42812097 | M62: 0.1 | N62: {=ROUND(($F$17+F62)*M62,-3)} -> 1290000 | P62: {=($F$17+F62)/14500} -> 889.31034 | Z62: {=($F$17+F62+($E$89-$E$88)-200000)*0.95} -> 12335750
A63: O | B63: Queen Ruizi 12 | C63: {=IF(ROUNDUP((AVERAGE('Private Boats 2026 Target'!AC1146:AC1163)-$C$17),-2)<0,0,ROUNDUP((AVERAGE('Private Boats 2026 Target'!AC1146:AC1163)-$C$17),-2))} -> 184200 | D63: {=ROUNDUP(C63,-4)} -> 190000 | E63: {=D63*110%} -> 209000 | F63: 3215000 | G63: {=_xlfn.IFERROR((D63-F63),"not listed")} -> -3025000 | H63: {=IF(A63="O",ROUND((F63+$F$17)/0.9-$F$17,-3),F63)} -> 4938000 | I63: {=$F$17+F63} -> 15510000 | K63: {=$F$17+F63-VLOOKUP(B63,'Private Boats 2026 Target'!$C$2:$AN$1501,38,0)} -> 5569819.5 | L63: {=K63/VLOOKUP(B63,'Private Boats 2026 Target'!$C$2:$AN$1501,38,0)} -> 0.56033384 | M63: 0.1 | N63: {=ROUND(($F$17+F63)*M63,-3)} -> 1551000 | P63: {=($F$17+F63)/14500} -> 1069.6552 | Z63: {=($F$17+F63+($E$89-$E$88)-200000)*0.95} -> 14820000
A64: P | B64: Jet Asia Yacht | C64: {=IF(ROUNDUP((AVERAGE('Private Boats 2026 Target'!AC842:AC886)-$C$17),-2)<0,0,ROUNDUP((AVERAGE('Private Boats 2026 Target'!AC842:AC886)-$C$17),-2))} -> 33233700 | D64: {=ROUNDUP(C64,-4)} -> 33240000 | E64: {=D64*110%} -> 36564000 | F64: 27840000 | G64: {=_xlfn.IFERROR((D64-F64),"not listed")} -> 5400000 | H64: {=IF(A64="O",ROUND((F64+$F$17)/0.9-$F$17,-3),F64)} -> 27840000 | I64: {=$F$17+F64} -> 40135000 | K64: {=$F$17+F64-VLOOKUP(B64,'Private Boats 2026 Target'!$C$2:$AN$1501,38,0)} -> 3773052.8 | L64: {=K64/VLOOKUP(B64,'Private Boats 2026 Target'!$C$2:$AN$1501,38,0)} -> 0.10376377 | M64: No fee | N64: No fee | P64: {=($F$17+F64)/14500} -> 2767.931
A65: P | B65: Lux Yacht AR55 | C65: {=IF(ROUNDUP((AVERAGE('Private Boats 2026 Target'!AC893:AC910)-$C$17),-2)<0,0,ROUNDUP((AVERAGE('Private Boats 2026 Target'!AC893:AC910)-$C$17),-2))} -> 35568000 | D65: {=ROUNDUP(C65,-4)} -> 35570000 | E65: {=D65*110%} -> 39127000 | F65: 30940000 | G65: {=_xlfn.IFERROR((D65-F65),"not listed")} -> 4630000 | H65: {=IF(A65="O",ROUND((F65+$F$17)/0.9-$F$17,-3),F65)} -> 30940000 | I65: {=$F$17+F65} -> 43235000 | K65: {=$F$17+F65-VLOOKUP(B65,'Private Boats 2026 Target'!$C$2:$AN$1501,38,0)} -> 5013052.8 | L65: {=K65/VLOOKUP(B65,'Private Boats 2026 Target'!$C$2:$AN$1501,38,0)} -> 0.1311564 | M65: No fee | N65: No fee | P65: {=($F$17+F65)/14500} -> 2981.7241
A66: P | B66: Yacht AM37 | C66: {=IF(ROUNDUP((AVERAGE('Private Boats 2026 Target'!AC985:AC994)-$C$17),-2)<0,0,ROUNDUP((AVERAGE('Private Boats 2026 Target'!AC985:AC994)-$C$17),-2))} -> 8045900 | D66: {=ROUNDUP(C66,-4)} -> 8050000 | E66: {=D66*110%} -> 8855000 | F66: 7240000 | G66: {=_xlfn.IFERROR((D66-F66),"not listed")} -> 810000 | H66: {=IF(A66="O",ROUND((F66+$F$17)/0.9-$F$17,-3),F66)} -> 7240000 | I66: {=$F$17+F66} -> 19535000 | K66: {=$F$17+F66-VLOOKUP(B66,'Private Boats 2026 Target'!$C$2:$AN$1501,38,0)} -> 3243052.8 | L66: {=K66/VLOOKUP(B66,'Private Boats 2026 Target'!$C$2:$AN$1501,38,0)} -> 0.19905864 | M66: No fee | N66: No fee | P66: {=($F$17+F66)/14500} -> 1347.2414
A67: P | B67: Boat BD99 | C67: {=IF(ROUNDUP((AVERAGE('Private Boats 2026 Target'!AC1169:AC1186)-$C$17),-2)<0,0,ROUNDUP((AVERAGE('Private Boats 2026 Target'!AC1169:AC1186)-$C$17),-2))} -> 4406400 | D67: {=ROUNDUP(C67,-4)} -> 4410000 | E67: {=D67*110%} -> 4851000 | F67: 4240000 | G67: {=_xlfn.IFERROR((D67-F67),"not listed")} -> 170000 | H67: {=IF(A67="O",ROUND((F67+$F$17)/0.9-$F$17,-3),F67)} -> 4240000 | I67: {=$F$17+F67} -> 16535000 | K67: {=$F$17+F67-VLOOKUP(B67,'Private Boats 2026 Target'!$C$2:$AN$1501,38,0)} -> 3143052.8 | L67: {=K67/VLOOKUP(B67,'Private Boats 2026 Target'!$C$2:$AN$1501,38,0)} -> 0.23469723 | M67: No fee | N67: No fee | P67: {=($F$17+F67)/14500} -> 1140.3448
A68: P | B68: Yacht RZ50 | C68: {=IF(ROUNDUP((AVERAGE('Private Boats 2026 Target'!AC939:AC956)-$C$17),-2)<0,0,ROUNDUP((AVERAGE('Private Boats 2026 Target'!AC939:AC956)-$C$17),-2))} -> 30058600 | D68: {=ROUNDUP(C68,-4)} -> 30060000 | E68: {=D68*110%} -> 33066000 | F68: 36490000 | G68: {=_xlfn.IFERROR((D68-F68),"not listed")} -> -6430000 | H68: {=IF(A68="O",ROUND((F68+$F$17)/0.9-$F$17,-3),F68)} -> 36490000 | I68: {=$F$17+F68} -> 48785000 | K68: {=$F$17+F68-VLOOKUP(B68,'Private Boats 2026 Target'!$C$2:$AN$1501,38,0)} -> 14953053 | L68: {=K68/VLOOKUP(B68,'Private Boats 2026 Target'!$C$2:$AN$1501,38,0)} -> 0.44198026 | M68: No fee | N68: No fee | P68: {=($F$17+F68)/14500} -> 3364.4828
B69: Premium Yacht AZ50 | C69: {=IF(ROUNDUP((AVERAGE('Private Boats 2026 Target'!AC1215:AC1233)-$C$17),-2)<0,0,ROUNDUP((AVERAGE('Private Boats 2026 Target'!AC1215:AC1233)-$C$17),-2))} -> 23105900 | D69: {=ROUNDUP(C69,-4)} -> 23110000 | E69: {=D69*110%} -> 25421000 | F69: 21550000 | G69: {=_xlfn.IFERROR((D69-F69),"not listed")} -> 1560000 | H69: {=IF(A69="O",ROUND((F69+$F$17)/0.9-$F$17,-3),F69)} -> 21550000 | I69: {=$F$17+F69} -> 33845000 | K69: {=$F$17+F69-VLOOKUP(B69,'Private Boats 2026 Target'!$C$2:$AN$1501,38,0)} -> 5553052.8 | L69: {=K69/VLOOKUP(B69,'Private Boats 2026 Target'!$C$2:$AN$1501,38,0)} -> 0.1962768 | M69: No fee | N69: No fee | P69: {=($F$17+F69)/14500} -> 2334.1379
A70: O | B70: Boat MW40 | C70: {=IF(ROUNDUP((AVERAGE('Private Boats 2026 Target'!AC1239:AC1257)-$C$17),-2)<0,0,ROUNDUP((AVERAGE('Private Boats 2026 Target'!AC1239:AC1257)-$C$17),-2))} -> 3653400 | D70: {=ROUNDUP(C70,-4)} -> 3660000 | E70: {=D70*110%} -> 4026000 | F70: 5250000 | G70: {=_xlfn.IFERROR((D70-F70),"not listed")} -> -1590000 | H70: {=IF(A70="O",ROUND((F70+$F$17)/0.9-$F$17,-3),F70)} -> 7199000 | I70: {=$F$17+F70} -> 17545000 | K70: {=$F$17+F70-VLOOKUP(B70,'Private Boats 2026 Target'!$C$2:$AN$1501,38,0)} -> 4753052.8 | L70: {=K70/VLOOKUP(B70,'Private Boats 2026 Target'!$C$2:$AN$1501,38,0)} -> 0.37156602 | M70: No fee | N70: No fee | P70: {=($F$17+F70)/14500} -> 1210
A71: P | B71: Boat KR-13 | C71: {=IF(ROUNDUP((AVERAGE('Private Boats 2026 Target'!AC1192:AC1209)-$C$17),-2)<0,0,ROUNDUP((AVERAGE('Private Boats 2026 Target'!AC1192:AC1209)-$C$17),-2))} -> 9300900 | D71: {=ROUNDUP(C71,-4)} -> 9310000 | E71: {=D71*110%} -> 10241000 | F71: 8500000 | G71: {=_xlfn.IFERROR((D71-F71),"not listed")} -> 810000 | H71: {=IF(A71="O",ROUND((F71+$F$17)/0.9-$F$17,-3),F71)} -> 8500000 | I71: {=$F$17+F71} -> 20795000 | K71: {=$F$17+F71-VLOOKUP(B71,'Private Boats 2026 Target'!$C$2:$AN$1501,38,0)} -> 3503052.8 | L71: {=K71/VLOOKUP(B71,'Private Boats 2026 Target'!$C$2:$AN$1501,38,0)} -> 0.2025829 | M71: No fee | N71: No fee | P71: {=($F$17+F71)/14500} -> 1434.1379
B72: Blue Marlin Class: | P72: {=($F$17+F72)/14500} -> 847.93103
A73: P | B73: {='Boats Data Sheet 2025'!C39} -> Lux Yacht BM55 | C73: {=IF(ROUNDUP((AVERAGE('Private Boats 2026 Target'!AC536:AC553)-$C$17),-2)<0,0,ROUNDUP((AVERAGE('Private Boats 2026 Target'!AC536:AC553)-$C$17),-2))} -> 31577000 | D73: {=ROUNDUP(C73,-4)} -> 31580000 | E73: {=D73*110%} -> 34738000 | F73: 29940000 | G73: {=_xlfn.IFERROR((D73-F73),"not listed")} -> 1640000 | H73: {=IF(A73="O",ROUND((F73+$F$17)/0.9-$F$17,-3),F73)} -> 29940000 | I73: {=$F$17+F73} -> 42235000 | K73: {=$F$17+F73-VLOOKUP(B73,'Private Boats 2026 Target'!$C$2:$AN$1501,38,0)} -> 4213052.8 | L73: {=K73/VLOOKUP(B73,'Private Boats 2026 Target'!$C$2:$AN$1501,38,0)} -> 0.11080581 | M73: No fee | N73: No fee | P73: {=($F$17+F73)/14500} -> 2912.7586 | R73: {=IF((C73-VLOOKUP(B73,'Private Boats 2026 Target'!$C$2:$AJ$714,32,0))<0,0,(C73-VLOOKUP(B73,'Private Boats 2026 Target'!$C$2:$AJ$714,32,0)))} -> 29718938 | AA73: We accept that Blue Marlin Class is a lower margin product with only 7% gross and 4% nett margin
A74: P | B74: {='Boats Data Sheet 2025'!C40} -> Yacht BM49 | C74: {=IF(ROUNDUP((AVERAGE('Private Boats 2026 Target'!AC559:AC576)-$C$17),-2)<0,0,ROUNDUP((AVERAGE('Private Boats 2026 Target'!AC559:AC576)-$C$17),-2))} -> 15922900 | D74: {=ROUNDUP(C74,-4)} -> 15930000 | E74: {=D74*110%} -> 17523000 | F74: 14140000 | G74: {=_xlfn.IFERROR((D74-F74),"not listed")} -> 1790000 | H74: {=IF(A74="O",ROUND((F74+$F$17)/0.9-$F$17,-3),F74)} -> 14140000 | I74: {=$F$17+F74} -> 26435000 | K74: {=$F$17+F74-VLOOKUP(B74,'Private Boats 2026 Target'!$C$2:$AN$1501,38,0)} -> 2098052.8 | L74: {=K74/VLOOKUP(B74,'Private Boats 2026 Target'!$C$2:$AN$1501,38,0)} -> 0.086208547 | M74: No fee | N74: No fee | P74: {=($F$17+F74)/14500} -> 1823.1034 | R74: {=IF((C74-VLOOKUP(B74,'Private Boats 2026 Target'!$C$2:$AJ$714,32,0))<0,0,(C74-VLOOKUP(B74,'Private Boats 2026 Target'!$C$2:$AJ$714,32,0)))} -> 15922900 | AA74: We accept that Blue Marlin Class is a lower margin product with only 7% gross and 4% nett margin
A75: P | B75: {='Boats Data Sheet 2025'!C41} -> Yacht Lux M13 | C75: {=IF(ROUNDUP((AVERAGE('Private Boats 2026 Target'!AC582:AC599)-$C$17),-2)<0,0,ROUNDUP((AVERAGE('Private Boats 2026 Target'!AC582:AC599)-$C$17),-2))} -> 22242900 | D75: {=ROUNDUP(C75,-4)} -> 22250000 | E75: {=D75*110%} -> 24475000 | F75: 21340000 | G75: {=_xlfn.IFERROR((D75-F75),"not listed")} -> 910000 | H75: {=IF(A75="O",ROUND((F75+$F$17)/0.9-$F$17,-3),F75)} -> 21340000 | I75: {=$F$17+F75} -> 33635000 | K75: {=$F$17+F75-VLOOKUP(B75,'Private Boats 2026 Target'!$C$2:$AN$1501,38,0)} -> 3773052.8 | L75: {=K75/VLOOKUP(B75,'Private Boats 2026 Target'!$C$2:$AN$1501,38,0)} -> 0.12634986 | M75: No fee | N75: No fee | P75: {=($F$17+F75)/14500} -> 2319.6552 | R75: {=IF((C75-VLOOKUP(B75,'Private Boats 2026 Target'!$C$2:$AJ$714,32,0))<0,0,(C75-VLOOKUP(B75,'Private Boats 2026 Target'!$C$2:$AJ$714,32,0)))} -> 20577317 | AA75: We accept that Blue Marlin Class is a lower margin product with only 7% gross and 4% nett margin
A76: P | B76: {='Boats Data Sheet 2025'!C42} -> Premium Yacht BM42 | C76: {=IF(ROUNDUP((AVERAGE('Private Boats 2026 Target'!AC605:AC622)-$C$17),-2)<0,0,ROUNDUP((AVERAGE('Private Boats 2026 Target'!AC605:AC622)-$C$17),-2))} -> 20298300 | D76: {=ROUNDUP(C76,-4)} -> 20300000 | E76: {=D76*110%} -> 22330000 | F76: 18740000 | G76: {=_xlfn.IFERROR((D76-F76),"not listed")} -> 1560000 | H76: {=IF(A76="O",ROUND((F76+$F$17)/0.9-$F$17,-3),F76)} -> 18740000 | I76: {=$F$17+F76} -> 31035000 | K76: {=$F$17+F76-VLOOKUP(B76,'Private Boats 2026 Target'!$C$2:$AN$1501,38,0)} -> 2873052.8 | L76: {=K76/VLOOKUP(B76,'Private Boats 2026 Target'!$C$2:$AN$1501,38,0)} -> 0.10201897 | M76: No fee | N76: No fee | P76: {=($F$17+F76)/14500} -> 2140.3448 | R76: {=IF((C76-VLOOKUP(B76,'Private Boats 2026 Target'!$C$2:$AJ$714,32,0))<0,0,(C76-VLOOKUP(B76,'Private Boats 2026 Target'!$C$2:$AJ$714,32,0)))} -> 18533871 | AA76: We accept that Blue Marlin Class is a lower margin product with only 7% gross and 4% nett margin
B78: PRIVATE BOAT CASSES | C78: Net Prices Agents | E78: Extra Pax Charge | F78: In IDR
B79: Small Boats | C79: {=ROUND(F17+AVERAGE(F39,F41,F62)-400000,-4)} -> 11400000 | E79: No Guide | F79: {=ROUNDUP('Private Boats 2026 Target'!AA6,-3)+50000} -> 290000
B80: Standard Boats | C80: {=ROUND(F17+AVERAGE(F22,F20,F24,F23,F25,F44)-400000,-4)} -> 13080000 | E80: With Guide | F80: {=ROUNDUP('Private Boats 2026 Target'!AA12,-3)+50000} -> 1389000
B81: Premium Boats | C81: {=ROUND(F17+AVERAGE(F26:F29,F63)-400000,-4)} -> 15990000
D83: Global Target | E83: Bluuu.tours | F83: WhatsApp Web and other | G83: TripAdvisor | H83: Klook | I83: AirBnb
B84: TARGET NET PROFIT MARGIN | D84: 0.25 | E84: 0.25 | F84: 0.25 | G84: 0.15 | H84: 0.2 | I84: 0.2
B86: NO LAND TOUR - BASE SEASON | G86: Per person base price NO Land Tour | K86: Per tour base price NO Land Tour
B87: Recommended Base Prices: | C87: Recommended Extra Pax +10% | D87: Actual Extra Pax +10% | E87: Total Base for bluuu.tours | F87: Total Base for WhatAspp, Web | G87: Per Person Base for TripAdvisor (25%) | H87: Per Person Base for Klook (20%) | I87: Per Person Base for AirBnB (20%) | K87: TOTAL BASE for TripAdvisor (25%) | L87: TOTAL BASE for Klook (20%) | M87: TOTAL BASE for AirBnB (20%) | O87: NP.one Low Season | R87: NP.one High or Mid Season | Z87: TA Standard | AB87: TA Premium
A88: 1 | B88: 1 | C88: {=ROUNDUP('Private Boats 2026 Target'!AA120,-2)} -> 0 | D88: 0 | E88: {=ROUND($D$17*(100%+($E$84-$D$84))+D88,-3)} -> 12295000 | F88: {=ROUND(($D$17*(100%+($F$84-$D$84))+D88)/(100%),-4)} -> 12300000 | G88: {=ROUND(($D$17*(100%+($G$84-$D$84))+SUM($D$88:D88))/(100%-25%)/$A88,-3)} -> 14754000 | H88: {=($D$17*(100%+($H$84-$D$84))+SUM($D$88:D88))/(100%-20%)/$A88} -> 14600312 | I88: {=($D$17*(100%+($I$84-$D$84))+SUM($D$88:D88))/(100%-20%)/$A88} -> 14600312 | K88: {=($D$17*(100%+($G$84-$D$84))+SUM($D$88:D88))/(100%-25%)} -> 14754000 | L88: {=($D$17*(100%+($H$84-$D$84))+SUM($D$88:D88))/(100%-20%)} -> 14600312 | M88: {=($D$17*(100%+($I$84-$D$84))+SUM($D$88:D88))/(100%-20%)} -> 14600312 | O88: 1 | P88: {=E88} -> 12295000 | R88: 1 | S88: {=E111} -> 13025000 | Z88: {=ROUND((K88+$F$22/0.75)/A88,-3)} -> 15847000 | AB88: {=ROUND((K88+7205000/0.75)/A88,-3)} -> 24361000
A89: 2 | B89: 2 | C89: {=ROUNDUP('Private Boats 2026 Target'!AA121,-2)} -> 195800 | D89: {=$F$79} -> 290000 | E89: {=ROUND(E88+D89,-3)} -> 12585000 | F89: {=F88+D89} -> 12590000 | G89: {=ROUND(($D$17*(100%+($G$84-$D$84))+SUM($D$88:D89))/(100%-25%)/$A89,-3)} -> 7570000 | H89: {=($D$17*(100%+($H$84-$D$84))+SUM($D$88:D89))/(100%-20%)/$A89} -> 7481406.2 | I89: {=($D$17*(100%+($I$84-$D$84))+SUM($D$88:D89))/(100%-20%)/$A89} -> 7481406.2 | K89: {=($D$17*(100%+($G$84-$D$84))+SUM($D$88:D89))/(100%-25%)} -> 15140667 | L89: {=($D$17*(100%+($H$84-$D$84))+SUM($D$88:D89))/(100%-20%)} -> 14962812 | M89: {=($D$17*(100%+($I$84-$D$84))+SUM($D$88:D89))/(100%-20%)} -> 14962812 | O89: 2 | P89: {=E89} -> 12585000 | R89: 2 | S89: {=E112} -> 13344000 | Z89: {=ROUND((K89+$F$22/0.75)/A89,-3)} -> 8117000 | AB89: {=ROUND((K89+7205000/0.75)/A89,-3)} -> 12374000
A90: 3 | B90: 3 | C90: {=ROUNDUP('Private Boats 2026 Target'!AA122,-2)} -> 195800 | D90: {=$F$79} -> 290000 | E90: {=ROUND(E89+D90,-3)} -> 12875000 | F90: {=F89+D90} -> 12880000 | G90: {=ROUND(($D$17*(100%+($G$84-$D$84))+SUM($D$88:D90))/(100%-25%)/$A90,-3)} -> 5176000 | H90: {=($D$17*(100%+($H$84-$D$84))+SUM($D$88:D90))/(100%-20%)/$A90} -> 5108437.5 | I90: {=($D$17*(100%+($I$84-$D$84))+SUM($D$88:D90))/(100%-20%)/$A90} -> 5108437.5 | K90: {=($D$17*(100%+($G$84-$D$84))+SUM($D$88:D90))/(100%-25%)} -> 15527333 | L90: {=($D$17*(100%+($H$84-$D$84))+SUM($D$88:D90))/(100%-20%)} -> 15325312 | M90: {=($D$17*(100%+($I$84-$D$84))+SUM($D$88:D90))/(100%-20%)} -> 15325312 | O90: 3 | P90: {=E90} -> 12875000 | R90: 3 | S90: {=E113} -> 13663000 | Z90: {=ROUND((K90+$F$22/0.75)/A90,-3)} -> 5540000 | AB90: {=ROUND((K90+7205000/0.75)/A90,-3)} -> 8378000
A91: 4 | B91: 4 | C91: {=ROUNDUP('Private Boats 2026 Target'!AA123,-2)} -> 195800 | D91: {=$F$79} -> 290000 | E91: {=ROUND(E90+D91,-3)} -> 13165000 | F91: {=F90+D91} -> 13170000 | G91: {=ROUND(($D$17*(100%+($G$84-$D$84))+SUM($D$88:D91))/(100%-25%)/$A91,-3)} -> 3979000 | H91: {=($D$17*(100%+($H$84-$D$84))+SUM($D$88:D91))/(100%-20%)/$A91} -> 3921953.1 | I91: {=($D$17*(100%+($I$84-$D$84))+SUM($D$88:D91))/(100%-20%)/$A91} -> 3921953.1 | K91: {=($D$17*(100%+($G$84-$D$84))+SUM($D$88:D91))/(100%-25%)} -> 15914000 | L91: {=($D$17*(100%+($H$84-$D$84))+SUM($D$88:D91))/(100%-20%)} -> 15687812 | M91: {=($D$17*(100%+($I$84-$D$84))+SUM($D$88:D91))/(100%-20%)} -> 15687812 | O91: 4 | P91: {=E91} -> 13165000 | R91: 4 | S91: {=E114} -> 13982000 | Z91: {=ROUND((K91+$F$22/0.75)/A91,-3)} -> 4252000 | AB91: {=ROUND((K91+7205000/0.75)/A91,-3)} -> 6380000
A92: 5 | B92: 5 | C92: {=ROUNDUP('Private Boats 2026 Target'!AA124,-2)} -> 195800 | D92: {=$F$79} -> 290000 | E92: {=ROUND(E91+D92,-3)} -> 13455000 | F92: {=F91+D92} -> 13460000 | G92: {=ROUND(($D$17*(100%+($G$84-$D$84))+SUM($D$88:D92))/(100%-25%)/$A92,-3)} -> 3260000 | H92: {=($D$17*(100%+($H$84-$D$84))+SUM($D$88:D92))/(100%-20%)/$A92} -> 3210062.5 | I92: {=($D$17*(100%+($I$84-$D$84))+SUM($D$88:D92))/(100%-20%)/$A92} -> 3210062.5 | K92: {=($D$17*(100%+($G$84-$D$84))+SUM($D$88:D92))/(100%-25%)} -> 16300667 | L92: {=($D$17*(100%+($H$84-$D$84))+SUM($D$88:D92))/(100%-20%)} -> 16050312 | M92: {=($D$17*(100%+($I$84-$D$84))+SUM($D$88:D92))/(100%-20%)} -> 16050312 | O92: 5 | P92: {=E92} -> 13455000 | R92: 5 | S92: {=E115} -> 14301000 | Z92: {=ROUND((K92+$F$22/0.75)/A92,-3)} -> 3479000 | AB92: {=ROUND((K92+7205000/0.75)/A92,-3)} -> 5181000
A93: 6 | B93: 0-6 | C93: {=ROUNDUP('Private Boats 2026 Target'!AA125,-2)} -> 195800 | D93: {=$F$79} -> 290000 | E93: {=ROUND(E92+D93,-3)} -> 13745000 | F93: {=F92+D93} -> 13750000 | G93: {=ROUND(($D$17*(100%+($G$84-$D$84))+SUM($D$88:D93))/(100%-25%)/$A93,-3)} -> 2781000 | H93: {=($D$17*(100%+($H$84-$D$84))+SUM($D$88:D93))/(100%-20%)/$A93} -> 2735468.8 | I93: {=($D$17*(100%+($I$84-$D$84))+SUM($D$88:D93))/(100%-20%)/$A93} -> 2735468.8 | K93: {=($D$17*(100%+($G$84-$D$84))+SUM($D$88:D93))/(100%-25%)} -> 16687333 | L93: {=($D$17*(100%+($H$84-$D$84))+SUM($D$88:D93))/(100%-20%)} -> 16412812 | M93: {=($D$17*(100%+($I$84-$D$84))+SUM($D$88:D93))/(100%-20%)} -> 16412812 | O93: 6 | P93: {=E93} -> 13745000 | R93: 6 | S93: {=E116} -> 14620000 | Z93: {=ROUND((K93+$F$22/0.75)/A93,-3)} -> 2963000 | AB93: {=ROUND((K93+7205000/0.75)/A93,-3)} -> 4382000
A94: 7 | B94: 7 | C94: {=ROUNDUP('Private Boats 2026 Target'!AA126,-2)} -> 195800 | D94: {=$F$79} -> 290000 | E94: {=ROUND(E93+D94,-3)} -> 14035000 | F94: {=F93+D94} -> 14040000 | G94: {=ROUND(($D$17*(100%+($G$84-$D$84))+SUM($D$88:D94))/(100%-25%)/$A94,-3)} -> 2439000 | H94: {=($D$17*(100%+($H$84-$D$84))+SUM($D$88:D94))/(100%-20%)/$A94} -> 2396473.2 | I94: {=($D$17*(100%+($I$84-$D$84))+SUM($D$88:D94))/(100%-20%)/$A94} -> 2396473.2 | K94: {=($D$17*(100%+($G$84-$D$84))+SUM($D$88:D94))/(100%-25%)} -> 17074000 | L94: {=($D$17*(100%+($H$84-$D$84))+SUM($D$88:D94))/(100%-20%)} -> 16775312 | M94: {=($D$17*(100%+($I$84-$D$84))+SUM($D$88:D94))/(100%-20%)} -> 16775312 | O94: 7 | P94: {=E94} -> 14035000 | R94: 7 | S94: {=E117} -> 14939000 | Z94: {=ROUND((K94+$F$22/0.75)/A94,-3)} -> 2595000 | AB94: {=ROUND((K94+7205000/0.75)/A94,-3)} -> 3812000
A95: 8 | B95: 8 | C95: {=ROUNDUP('Private Boats 2026 Target'!AA127,-2)} -> 1294600 | D95: {=$F$80} -> 1389000 | E95: {=ROUND(E94+D95,-3)} -> 15424000 | F95: {=F94+D95} -> 15429000 | G95: {=ROUND(($D$17*(100%+($G$84-$D$84))+SUM($D$88:D95))/(100%-25%)/$A95,-3)} -> 2366000 | H95: {=($D$17*(100%+($H$84-$D$84))+SUM($D$88:D95))/(100%-20%)/$A95} -> 2313945.3 | I95: {=($D$17*(100%+($I$84-$D$84))+SUM($D$88:D95))/(100%-20%)/$A95} -> 2313945.3 | K95: {=($D$17*(100%+($G$84-$D$84))+SUM($D$88:D95))/(100%-25%)} -> 18926000 | L95: {=($D$17*(100%+($H$84-$D$84))+SUM($D$88:D95))/(100%-20%)} -> 18511562 | M95: {=($D$17*(100%+($I$84-$D$84))+SUM($D$88:D95))/(100%-20%)} -> 18511562 | O95: 8 | P95: {=E95} -> 15424000 | R95: 8 | S95: {=E118} -> 16466000 | Z95: {=ROUND((K95+$F$22/0.75)/A95,-3)} -> 2502000 | AB95: {=ROUND((K95+7205000/0.75)/A95,-3)} -> 3567000
A96: 9 | B96: 9 | C96: {=ROUNDUP('Private Boats 2026 Target'!AA128,-2)} -> 195800 | D96: {=$F$79} -> 290000 | E96: {=ROUND(E95+D96,-3)} -> 15714000 | F96: {=F95+D96} -> 15719000 | G96: {=ROUND(($D$17*(100%+($G$84-$D$84))+SUM($D$88:D96))/(100%-25%)/$A96,-3)} -> 2146000 | H96: {=($D$17*(100%+($H$84-$D$84))+SUM($D$88:D96))/(100%-20%)/$A96} -> 2097118.1 | I96: {=($D$17*(100%+($I$84-$D$84))+SUM($D$88:D96))/(100%-20%)/$A96} -> 2097118.1 | K96: {=($D$17*(100%+($G$84-$D$84))+SUM($D$88:D96))/(100%-25%)} -> 19312667 | L96: {=($D$17*(100%+($H$84-$D$84))+SUM($D$88:D96))/(100%-20%)} -> 18874062 | M96: {=($D$17*(100%+($I$84-$D$84))+SUM($D$88:D96))/(100%-20%)} -> 18874062 | O96: 9 | P96: {=E96} -> 15714000 | R96: 9 | S96: {=E119} -> 16785000 | Z96: {=ROUND((K96+$F$22/0.75)/A96,-3)} -> 2267000 | AB96: {=ROUND((K96+7205000/0.75)/A96,-3)} -> 3213000
A97: 10 | B97: 10 | C97: {=ROUNDUP('Private Boats 2026 Target'!AA129,-2)} -> 195800 | D97: {=$F$79} -> 290000 | E97: {=ROUND(E96+D97,-3)} -> 16004000 | F97: {=F96+D97} -> 16009000 | G97: {=ROUND(($D$17*(100%+($G$84-$D$84))+SUM($D$88:D97))/(100%-25%)/$A97,-3)} -> 1970000 | H97: {=($D$17*(100%+($H$84-$D$84))+SUM($D$88:D97))/(100%-20%)/$A97} -> 1923656.2 | I97: {=($D$17*(100%+($I$84-$D$84))+SUM($D$88:D97))/(100%-20%)/$A97} -> 1923656.2 | K97: {=($D$17*(100%+($G$84-$D$84))+SUM($D$88:D97))/(100%-25%)} -> 19699333 | L97: {=($D$17*(100%+($H$84-$D$84))+SUM($D$88:D97))/(100%-20%)} -> 19236562 | M97: {=($D$17*(100%+($I$84-$D$84))+SUM($D$88:D97))/(100%-20%)} -> 19236562 | O97: 10 | P97: {=E97} -> 16004000 | R97: 10 | S97: {=E120} -> 17104000 | Z97: {=ROUND((K97+$F$22/0.75)/A97,-3)} -> 2079000 | AB97: {=ROUND((K97+7205000/0.75)/A97,-3)} -> 2931000
A98: 11 | B98: 11 | C98: {=ROUNDUP('Private Boats 2026 Target'!AA130,-2)} -> 195800 | D98: {=$F$79} -> 290000 | E98: {=ROUND(E97+D98,-3)} -> 16294000 | F98: {=F97+D98} -> 16299000 | G98: {=ROUND(($D$17*(100%+($G$84-$D$84))+SUM($D$88:D98))/(100%-25%)/$A98,-3)} -> 1826000 | H98: {=($D$17*(100%+($H$84-$D$84))+SUM($D$88:D98))/(100%-20%)/$A98} -> 1781733 | I98: {=($D$17*(100%+($I$84-$D$84))+SUM($D$88:D98))/(100%-20%)/$A98} -> 1781733 | K98: {=($D$17*(100%+($G$84-$D$84))+SUM($D$88:D98))/(100%-25%)} -> 20086000 | L98: {=($D$17*(100%+($H$84-$D$84))+SUM($D$88:D98))/(100%-20%)} -> 19599062 | M98: {=($D$17*(100%+($I$84-$D$84))+SUM($D$88:D98))/(100%-20%)} -> 19599062 | O98: 11 | P98: {=E98} -> 16294000 | R98: 11 | S98: {=E121} -> 17423000 | Z98: {=ROUND((K98+$F$22/0.75)/A98,-3)} -> 1925000 | AB98: {=ROUND((K98+7205000/0.75)/A98,-3)} -> 2699000
A99: 12 | B99: 12 | C99: {=ROUNDUP('Private Boats 2026 Target'!AA131,-2)} -> 195800 | D99: {=$F$79} -> 290000 | E99: {=ROUND(E98+D99,-3)} -> 16584000 | F99: {=F98+D99} -> 16589000 | G99: {=ROUND(($D$17*(100%+($G$84-$D$84))+SUM($D$88:D99))/(100%-25%)/$A99,-3)} -> 1706000 | H99: {=($D$17*(100%+($H$84-$D$84))+SUM($D$88:D99))/(100%-20%)/$A99} -> 1663463.5 | I99: {=($D$17*(100%+($I$84-$D$84))+SUM($D$88:D99))/(100%-20%)/$A99} -> 1663463.5 | K99: {=($D$17*(100%+($G$84-$D$84))+SUM($D$88:D99))/(100%-25%)} -> 20472667 | L99: {=($D$17*(100%+($H$84-$D$84))+SUM($D$88:D99))/(100%-20%)} -> 19961562 | M99: {=($D$17*(100%+($I$84-$D$84))+SUM($D$88:D99))/(100%-20%)} -> 19961562 | O99: 12 | P99: {=E99} -> 16584000 | R99: 12 | S99: {=E122} -> 17742000 | Z99: {=ROUND((K99+$F$22/0.75)/A99,-3)} -> 1797000 | AB99: {=ROUND((K99+7205000/0.75)/A99,-3)} -> 2507000
A100: 13 | B100: 13 | C100: {=ROUNDUP('Private Boats 2026 Target'!AA132,-2)} -> 195800 | D100: {=$F$79} -> 290000 | E100: {=ROUND(E99+D100,-3)} -> 16874000 | F100: {=F99+D100} -> 16879000 | G100: {=ROUND(($D$17*(100%+($G$84-$D$84))+SUM($D$88:D100))/(100%-25%)/$A100,-3)} -> 1605000 | H100: {=($D$17*(100%+($H$84-$D$84))+SUM($D$88:D100))/(100%-20%)/$A100} -> 1563389.4 | I100: {=($D$17*(100%+($I$84-$D$84))+SUM($D$88:D100))/(100%-20%)/$A100} -> 1563389.4 | K100: {=($D$17*(100%+($G$84-$D$84))+SUM($D$88:D100))/(100%-25%)} -> 20859333 | L100: {=($D$17*(100%+($H$84-$D$84))+SUM($D$88:D100))/(100%-20%)} -> 20324062 | M100: {=($D$17*(100%+($I$84-$D$84))+SUM($D$88:D100))/(100%-20%)} -> 20324062 | O100: 13 | P100: {=E100} -> 16874000 | R100: 13 | S100: {=E123} -> 18061000 | Z100: {=ROUND((K100+$F$22/0.75)/A100,-3)} -> 1689000 | AB100: {=ROUND((K100+7205000/0.75)/A100,-3)} -> 2344000
A101: 14 | B101: 14 | C101: {=ROUNDUP('Private Boats 2026 Target'!AA133,-2)} -> 195800 | D101: {=$F$79} -> 290000 | E101: {=ROUND(E100+D101,-3)} -> 17164000 | F101: {=F100+D101} -> 17169000 | G101: {=ROUND(($D$17*(100%+($G$84-$D$84))+SUM($D$88:D101))/(100%-25%)/$A101,-3)} -> 1518000 | H101: {=($D$17*(100%+($H$84-$D$84))+SUM($D$88:D101))/(100%-20%)/$A101} -> 1477611.6 | I101: {=($D$17*(100%+($I$84-$D$84))+SUM($D$88:D101))/(100%-20%)/$A101} -> 1477611.6 | K101: {=($D$17*(100%+($G$84-$D$84))+SUM($D$88:D101))/(100%-25%)} -> 21246000 | L101: {=($D$17*(100%+($H$84-$D$84))+SUM($D$88:D101))/(100%-20%)} -> 20686562 | M101: {=($D$17*(100%+($I$84-$D$84))+SUM($D$88:D101))/(100%-20%)} -> 20686562 | O101: 14 | P101: {=E101} -> 17164000 | R101: 14 | S101: {=E124} -> 18380000 | Z101: {=ROUND((K101+$F$22/0.75)/A101,-3)} -> 1596000 | AB101: {=ROUND((K101+7205000/0.75)/A101,-3)} -> 2204000
A102: 15 | B102: 15 | C102: {=ROUNDUP('Private Boats 2026 Target'!AA134,-2)} -> 195800 | D102: {=$F$79} -> 290000 | E102: {=ROUND(E101+D102,-3)} -> 17454000 | F102: {=F101+D102} -> 17459000 | G102: {=ROUND(($D$17*(100%+($G$84-$D$84))+SUM($D$88:D102))/(100%-25%)/$A102,-3)} -> 1442000 | H102: {=($D$17*(100%+($H$84-$D$84))+SUM($D$88:D102))/(100%-20%)/$A102} -> 1403270.8 | I102: {=($D$17*(100%+($I$84-$D$84))+SUM($D$88:D102))/(100%-20%)/$A102} -> 1403270.8 | K102: {=($D$17*(100%+($G$84-$D$84))+SUM($D$88:D102))/(100%-25%)} -> 21632667 | L102: {=($D$17*(100%+($H$84-$D$84))+SUM($D$88:D102))/(100%-20%)} -> 21049062 | M102: {=($D$17*(100%+($I$84-$D$84))+SUM($D$88:D102))/(100%-20%)} -> 21049062 | O102: 15 | P102: {=E102} -> 17454000 | R102: 15 | S102: {=E125} -> 18699000 | Z102: {=ROUND((K102+$F$22/0.75)/A102,-3)} -> 1515000 | AB102: {=ROUND((K102+7205000/0.75)/A102,-3)} -> 2083000
A103: 16 | B103: 16 | C103: {=ROUNDUP('Private Boats 2026 Target'!AA135,-2)} -> 195800 | D103: {=$F$80} -> 1389000 | E103: {=ROUND(E102+D103,-3)} -> 18843000 | F103: {=F102+D103} -> 18848000 | G103: {=ROUND(($D$17*(100%+($G$84-$D$84))+SUM($D$88:D103))/(100%-25%)/$A103,-3)} -> 1468000 | H103: {=($D$17*(100%+($H$84-$D$84))+SUM($D$88:D103))/(100%-20%)/$A103} -> 1424082 | I103: {=($D$17*(100%+($I$84-$D$84))+SUM($D$88:D103))/(100%-20%)/$A103} -> 1424082 | K103: {=($D$17*(100%+($G$84-$D$84))+SUM($D$88:D103))/(100%-25%)} -> 23484667 | L103: {=($D$17*(100%+($H$84-$D$84))+SUM($D$88:D103))/(100%-20%)} -> 22785312 | M103: {=($D$17*(100%+($I$84-$D$84))+SUM($D$88:D103))/(100%-20%)} -> 22785312 | O103: 16 | P103: {=E103} -> 18843000 | R103: 16 | S103: {=E126} -> 20227000 | Z103: {=ROUND((K103+$F$22/0.75)/A103,-3)} -> 1536000 | AB103: {=ROUND((K103+7205000/0.75)/A103,-3)} -> 2068000
A104: 17 | B104: 17 | C104: {=ROUNDUP('Private Boats 2026 Target'!AA136,-2)} -> 195800 | D104: {=$F$79} -> 290000 | E104: {=ROUND(E103+D104,-3)} -> 19133000 | F104: {=F103+D104} -> 19138000 | G104: {=ROUND(($D$17*(100%+($G$84-$D$84))+SUM($D$88:D104))/(100%-25%)/$A104,-3)} -> 1404000 | H104: {=($D$17*(100%+($H$84-$D$84))+SUM($D$88:D104))/(100%-20%)/$A104} -> 1361636 | I104: {=($D$17*(100%+($I$84-$D$84))+SUM($D$88:D104))/(100%-20%)/$A104} -> 1361636 | K104: {=($D$17*(100%+($G$84-$D$84))+SUM($D$88:D104))/(100%-25%)} -> 23871333 | L104: {=($D$17*(100%+($H$84-$D$84))+SUM($D$88:D104))/(100%-20%)} -> 23147812 | M104: {=($D$17*(100%+($I$84-$D$84))+SUM($D$88:D104))/(100%-20%)} -> 23147812 | O104: 17 | P104: {=E104} -> 19133000 | R104: 17 | S104: {=E127} -> 20546000 | Z104: {=ROUND((K104+$F$22/0.75)/A104,-3)} -> 1469000 | AB104: {=ROUND((K104+7205000/0.75)/A104,-3)} -> 1969000
A105: 18 | B105: 18 | C105: {=ROUNDUP('Private Boats 2026 Target'!AA137,-2)} -> 195800 | D105: {=$F$79} -> 290000 | E105: {=ROUND(E104+D105,-3)} -> 19423000 | F105: {=F104+D105} -> 19428000 | G105: {=ROUND(($D$17*(100%+($G$84-$D$84))+SUM($D$88:D105))/(100%-25%)/$A105,-3)} -> 1348000 | H105: {=($D$17*(100%+($H$84-$D$84))+SUM($D$88:D105))/(100%-20%)/$A105} -> 1306128.5 | I105: {=($D$17*(100%+($I$84-$D$84))+SUM($D$88:D105))/(100%-20%)/$A105} -> 1306128.5 | K105: {=($D$17*(100%+($G$84-$D$84))+SUM($D$88:D105))/(100%-25%)} -> 24258000 | L105: {=($D$17*(100%+($H$84-$D$84))+SUM($D$88:D105))/(100%-20%)} -> 23510312 | M105: {=($D$17*(100%+($I$84-$D$84))+SUM($D$88:D105))/(100%-20%)} -> 23510312 | O105: 18 | P105: {=E105} -> 19423000 | R105: 18 | S105: {=E128} -> 20865000 | Z105: {=ROUND((K105+$F$22/0.75)/A105,-3)} -> 1408000 | AB105: {=ROUND((K105+7205000/0.75)/A105,-3)} -> 1881000
A106: 19 | B106: 19 | C106: {=ROUNDUP('Private Boats 2026 Target'!AA138,-2)} -> 195800 | D106: {=$F$79} -> 290000 | E106: {=ROUND(E105+D106,-3)} -> 19713000 | F106: {=F105+D106} -> 19718000 | G106: {=ROUND(($D$17*(100%+($G$84-$D$84))+SUM($D$88:D106))/(100%-25%)/$A106,-3)} -> 1297000 | H106: {=($D$17*(100%+($H$84-$D$84))+SUM($D$88:D106))/(100%-20%)/$A106} -> 1256463.8 | I106: {=($D$17*(100%+($I$84-$D$84))+SUM($D$88:D106))/(100%-20%)/$A106} -> 1256463.8 | K106: {=($D$17*(100%+($G$84-$D$84))+SUM($D$88:D106))/(100%-25%)} -> 24644667 | L106: {=($D$17*(100%+($H$84-$D$84))+SUM($D$88:D106))/(100%-20%)} -> 23872812 | M106: {=($D$17*(100%+($I$84-$D$84))+SUM($D$88:D106))/(100%-20%)} -> 23872812 | O106: 19 | P106: {=E106} -> 19713000 | R106: 19 | S106: {=E129} -> 21184000 | Z106: {=ROUND((K106+$F$22/0.75)/A106,-3)} -> 1355000 | AB106: {=ROUND((K106+7205000/0.75)/A106,-3)} -> 1803000
A107: 20 | B107: 20+ | C107: {=ROUNDUP('Private Boats 2026 Target'!AA139,-2)} -> 195800 | D107: {=$F$79} -> 290000 | E107: {=ROUND(E106+D107,-3)} -> 20003000 | F107: {=F106+D107} -> 20008000 | G107: {=ROUND(($D$17*(100%+($G$84-$D$84))+SUM($D$88:D107))/(100%-25%)/$A107,-3)} -> 1252000 | H107: {=($D$17*(100%+($H$84-$D$84))+SUM($D$88:D107))/(100%-20%)/$A107} -> 1211765.6 | I107: {=($D$17*(100%+($I$84-$D$84))+SUM($D$88:D107))/(100%-20%)/$A107} -> 1211765.6 | K107: {=($D$17*(100%+($G$84-$D$84))+SUM($D$88:D107))/(100%-25%)} -> 25031333 | L107: {=($D$17*(100%+($H$84-$D$84))+SUM($D$88:D107))/(100%-20%)} -> 24235312 | M107: {=($D$17*(100%+($I$84-$D$84))+SUM($D$88:D107))/(100%-20%)} -> 24235312 | O107: 20 | P107: {=E107} -> 20003000 | R107: 20 | S107: {=E130} -> 21503000 | Z107: {=ROUND((K107+$F$22/0.75)/A107,-3)} -> 1306000 | AB107: {=ROUND((K107+7205000/0.75)/A107,-3)} -> 1732000
...

Sheet PnL 2026 Plan-Forecast
B2: PROFIT AND LOSS STATEMENT | C2: 2026 FORECAST AND PLAN | D2: % | F2: Delivered Quantity
B4: SALES REVENUE | INCOME | C4: {=SUM(C24,C80,C93,C108,C117,C119,C121,C144)} -> 9.4173591e+10
B6: Private Tour - Base Price (AirBnb) | C6: {=F6*'RECOMMENDED PRICES'!$M$93} -> 25637953 | D6: {=F6/$F$24} -> 0.00066294724 | F6: {=$F$24*'Actual Sales 2025'!D7} -> 1.5620694
B7: Less: AirBnB servive comission (20%) | C7: {=-C6*20%} -> -5127590.5
B8: Private Tour - Base Price (WhatsApp) | C8: {=F8*'RECOMMENDED PRICES'!$E$93} -> 9640449.2 | D8: {=F8/$F$24} -> 0.00029766732 | F8: {=$F$24*'Actual Sales 2025'!D8} -> 0.70137862
B9: Private Tour - Base Price (Nusapenida.one) | C9: {=F9*'RECOMMENDED PRICES'!$E$93} -> 0 | D9: {=F9/$F$24} -> 0 | F9: {=$F$24*0} -> 0
B10: Private Tour - Base Price (GetMyBoat) | C10: {=F10*'RECOMMENDED PRICES'!$F$93} -> 80709442 | D10: {=F10/$F$24} -> 0.0024911523 | F10: {=$F$24*'Actual Sales 2025'!D9} -> 5.8697776
B11: Private Tour - Base Price (Bluuu.tours) | C11: {=F11*'RECOMMENDED PRICES'!$E$93} -> 2.6627741e+10 | D11: {=F11/$F$24} -> 0.82218247 | F11: {=$F$24*('Actual Sales 2025'!D19+'Actual Sales 2025'!D10+'Actual Sales 2025'!D16)} -> 1937.2674
B12: Less: discount (10%) | C12: {=-C11*10%} -> -2.6627741e+09
B13: Private Tour - Base Price (Klook) | C13: {=F13*'RECOMMENDED PRICES'!L93} -> 2.3571893e+08 | D13: {=F13/$F$24} -> 0.0060952297 | F13: {=$F$24*'Actual Sales 2025'!D11} -> 14.361885
B14: Less: Klook servive comission (20%) | C14: {=-C13*20%} -> -47143785
B15: Private Tour - Base Price (TripAdvisor (pv)) | C15: {=F15*'RECOMMENDED PRICES'!K93} -> 6.1582142e+09 | D15: {=F15/$F$24} -> 0.15661973 | F15: {=$F$24*'Actual Sales 2025'!D12} -> 369.03525
B16: Less: TripAdvisor servive comission (25%) | C16: {=-C15*25%} -> -1.5395535e+09
B17: Private Tour - Base Price (Instagram) | C17: {=F17*'RECOMMENDED PRICES'!$E$93} -> 48842468 | D17: {=F17/$F$24} -> 0.0015081047 | F17: {=$F$24*'Actual Sales 2025'!D15} -> 3.5534717
B18: Private Tour - Base Price (MyBaliTrips) | C18: 0 | D18: 0 | F18: {=$F$24*0} -> 0
B19: Private Tour - Base Price (ClickAndBoat) | C19: {=F19*'RECOMMENDED PRICES'!$E$93} -> 1.0379965e+08 | D19: 0 | F19: {=$F$24*'Actual Sales 2025'!D14} -> 7.5518118
B20: Private Tour - Base Price (LuxEscapes) | C20: {=F20*'RECOMMENDED PRICES'!$E$93} -> 52488952 | D20: {=F20/$F$24} -> 0.0016206969 | F20: {=$F$24*'Actual Sales 2025'!D17} -> 3.818767
B21: Private Tour - Base Price (Vio) | C21: {=F21*'RECOMMENDED PRICES'!$E$93} -> 13096722 | D21: {=F21/$F$24} -> 0.00040438635 | F21: {=$F$24*'Actual Sales 2025'!D18} -> 0.95283535
B22: Private Tour - Base Price (GetYourGuide) | C22: {=F22*'RECOMMENDED PRICES'!$K$93} -> 1.931611e+08 | D22: {=F22/$F$24} -> 0.0049125995 | F22: {=$F$24*'Actual Sales 2025'!D13} -> 11.575312
B23: Less: GYG servive comission (30%) | C23: {=-C22*25%} -> -48290274
B24: Private Tour Base Price Total | C24: {=SUM(C6:C22)} -> 2.9294452e+10 | D24: {=F24/$F$24} -> 1 | F24: {='Allocation OH and Target 2026'!K92} -> 2356.25
B26: Sweetheart 4 | C26: {=_xlfn.IFERROR((VLOOKUP(B26,'RECOMMENDED PRICES'!$B$20:$F$58,5,0)*F26),0)} -> 42000000 | D26: {=C26/$C$80} -> 0.0042887755 | F26: {=VLOOKUP(B26,'Allocation OH and Target 2026'!$C$35:$K$87,9,0)} -> 28
B27: Riki J | C27: {=_xlfn.IFERROR((VLOOKUP(B27,'RECOMMENDED PRICES'!$B$20:$F$58,5,0)*F27),0)} -> 153900000 | D27: {=C27/$C$80} -> 0.015715299 | F27: {=VLOOKUP(B27,'Allocation OH and Target 2026'!$C$35:$K$91,9,0)} -> 57
B28: Sanjaya | C28: {=_xlfn.IFERROR((VLOOKUP(B28,'RECOMMENDED PRICES'!$B$20:$F$58,5,0)*F28),0)} -> 55760000 | D28: {=C28/$C$80} -> 0.0056938601 | F28: {=VLOOKUP(B28,'Allocation OH and Target 2026'!$C$35:$K$91,9,0)} -> 68
B29: Jayanadi | C29: {=_xlfn.IFERROR((VLOOKUP(B29,'RECOMMENDED PRICES'!$B$20:$F$58,5,0)*F29),0)} -> 130285000 | D29: {=C29/$C$80} -> 0.013303884 | F29: {=VLOOKUP(B29,'Allocation OH and Target 2026'!$C$35:$K$91,9,0)} -> 71
B30: Sea Dragon | C30: {=_xlfn.IFERROR((VLOOKUP(B30,'RECOMMENDED PRICES'!$B$20:$F$76,5,0)*F30),0)} -> 55760000 | D30: {=C30/$C$80} -> 0.0056938601 | F30: {=VLOOKUP(B30,'Allocation OH and Target 2026'!$C$35:$K$91,9,0)} -> 68
B31: Sanjaya O4 | C31: {=_xlfn.IFERROR((VLOOKUP(B31,'RECOMMENDED PRICES'!$B$20:$F$76,5,0)*F31),0)} -> 379100000 | D31: {=C31/$C$80} -> 0.038711305 | F31: {=VLOOKUP(B31,'Allocation OH and Target 2026'!$C$35:$K$91,9,0)} -> 85
B32: Sanjaya O5 | C32: {=_xlfn.IFERROR((VLOOKUP(B32,'RECOMMENDED PRICES'!$B$20:$F$76,5,0)*F32),0)} -> 361260000 | D32: {=C32/$C$80} -> 0.036889596 | F32: {=VLOOKUP(B32,'Allocation OH and Target 2026'!$C$35:$K$91,9,0)} -> 81
B33: Almond Milk | C33: {=_xlfn.IFERROR((VLOOKUP(B33,'RECOMMENDED PRICES'!$B$20:$F$76,5,0)*F33),0)} -> 224640000 | D33: {=C33/$C$80} -> 0.022938822 | F33: {=VLOOKUP(B33,'Allocation OH and Target 2026'!$C$35:$K$91,9,0)} -> 54
B34: Honey Milk | C34: {=_xlfn.IFERROR((VLOOKUP(B34,'RECOMMENDED PRICES'!$B$20:$F$76,5,0)*F34),0)} -> 224640000 | D34: {=C34/$C$80} -> 0.022938822 | F34: {=VLOOKUP(B34,'Allocation OH and Target 2026'!$C$35:$K$91,9,0)} -> 54
B35: Eldorado 1 | C35: {=_xlfn.IFERROR((VLOOKUP(B35,'RECOMMENDED PRICES'!$B$20:$F$76,5,0)*F35),0)} -> 266240000 | D35: {=C35/$C$80} -> 0.027186752 | F35: {=VLOOKUP(B35,'Allocation OH and Target 2026'!$C$35:$K$91,9,0)} -> 64
B36: Eldorado 2 - Arya | C36: {=_xlfn.IFERROR((VLOOKUP(B36,'RECOMMENDED PRICES'!$B$20:$F$76,5,0)*F36),0)} -> 3.2794667e+08 | D36: {=C36/$C$80} -> 0.033487848 | F36: {=VLOOKUP(B36,'Allocation OH and Target 2026'!$C$35:$K$91,9,0)} -> 78.833333
B37: Eldorado 3 - Evgenii | C37: {=_xlfn.IFERROR((VLOOKUP(B37,'RECOMMENDED PRICES'!$B$20:$F$76,5,0)*F37),0)} -> 2.9813333e+08 | D37: {=C37/$C$80} -> 0.030443499 | F37: {=VLOOKUP(B37,'Allocation OH and Target 2026'!$C$35:$K$91,9,0)} -> 71.666667
B38: Eldorado 4 - Vadim | C38: {=_xlfn.IFERROR((VLOOKUP(B38,'RECOMMENDED PRICES'!$B$20:$F$76,5,0)*F38),0)} -> 252720000 | D38: {=C38/$C$80} -> 0.025806175 | F38: {=VLOOKUP(B38,'Allocation OH and Target 2026'!$C$35:$K$91,9,0)} -> 60.75
B39: Eldorado 5 - Robert | C39: {=_xlfn.IFERROR((VLOOKUP(B39,'RECOMMENDED PRICES'!$B$20:$F$76,5,0)*F39),0)} -> 299520000 | D39: {=C39/$C$80} -> 0.030585096 | F39: {=VLOOKUP(B39,'Allocation OH and Target 2026'!$C$35:$K$91,9,0)} -> 72
B40: Eldorado 6 - Vadim | C40: {=_xlfn.IFERROR((VLOOKUP(B40,'RECOMMENDED PRICES'!$B$20:$F$76,5,0)*F40),0)} -> 262080000 | D40: {=C40/$C$80} -> 0.026761959 | F40: {=VLOOKUP(B40,'Allocation OH and Target 2026'!$C$35:$K$91,9,0)} -> 63
B41: Boat Angels | C41: {=_xlfn.IFERROR((VLOOKUP(B41,'RECOMMENDED PRICES'!$B$20:$F$76,5,0)*F41),0)} -> 424320000 | D41: {=C41/$C$80} -> 0.043328886 | F41: {=VLOOKUP(B41,'Allocation OH and Target 2026'!$C$35:$K$91,9,0)} -> 102
... B79: Yacht T13 | C79: {=_xlfn.IFERROR((VLOOKUP(B79,'RECOMMENDED PRICES'!$B$20:$F$76,5,0)*F79),0)} -> 0 | D79: {=C79/$C$80} -> 0 | F79: {=VLOOKUP(B79,'Allocation OH and Target 2026'!$C$35:$K$91,9,0)} -> 3
B80: Private Boat Upgrade Total | C80: {=SUM(C26:C79)} -> 9793005000 | D80: {=C80/$C$80} -> 1
B82: Extra Pax (0-6) | C82: 0 | D82: {=C82/$C$93} | F82: 0
B83: Extra Pax (7) | C83: 0 | D83: {=C83/$C$93} | F83: 0
B84: Extra Pax (8) | C84: 0 | D84: {=C84/$C$93} | F84: 0
B85: Extra Pax (9) | C85: 0 | D85: {=C85/$C$93} | F85: 0
B86: Extra Pax (10) | C86: 0 | D86: {=C86/$C$93} | F86: 0
B87: Extra Pax (11) | C87: 0 | D87: {=C87/$C$93} | F87: 0
B88: Extra Pax (12) | C88: 0 | D88: {=C88/$C$93} | F88: 0
B89: Extra Pax (13) | C89: 0 | D89: {=C89/$C$93} | F89: 0
B90: Extra Pax (14) | C90: 0 | D90: {=C90/$C$93} | F90: 0
B91: Extra Pax (15) | C91: 0 | D91: {=C91/$C$93} | F91: 0
B92: Extra Pax (20+) | C92: 0 | D92: {=C92/$C$93} | F92: 0
B93: Extra Pax Charge Total | C93: {=SUM(C82:C92)} -> 0 | D93: {=C93/$C$93} | F93: {=SUM(F82:F92)} -> 0
B95: Shared Tour (AirBnb) | C95: {=D95*$C$108} -> 5.4972883e+09 | D95: {=F95/$F$108} -> 0.12090248 | F95: {=$F$108*'Actual Sales 2025'!D22} -> 3765.2659
B96: Shared Tour (GetMyBoat) | C96: {=D96*$C$108} -> 55063901 | D96: {=F96/$F$108} -> 0.0012110266 | F96: {=$F$108*'Actual Sales 2025'!D23} -> 37.715001
B97: Shared Tour (Nusapenida.one) | C97: {=D97*$C$108} -> 8.0941531e+09 | D97: {=F97/$F$108} -> 0.17801562 | F97: {=$F$108*'Actual Sales 2025'!D24} -> 5543.9405
B98: Shared Tour (balibooking.tours) | C98: {=D98*$C$108} -> 15091086 | D98: {=F98/$F$108} -> 0.00033189994 | F98: {=$F$108*'Actual Sales 2025'!D25} -> 10.33636
B99: Shared Tour (Klook) | C99: {=D99*$C$108} -> 5.7269883e+09 | D99: {=F99/$F$108} -> 0.1259543 | F99: {=$F$108*'Actual Sales 2025'!D26} -> 3922.5947
B100: Shared Tour (GetYourGuide) | C100: {=D100*$C$108} -> 4.6919466e+09 | D100: {=F100/$F$108} -> 0.10319051 | F100: {=$F$108*'Actual Sales 2025'!D27} -> 3213.6621
B101: Shared Tour (TripAdvisor (sh)) | C101: {=D101*$C$108} -> 1.8201841e+10 | D101: {=F101/$F$108} -> 0.40031514 | F101: {=$F$108*'Actual Sales 2025'!D28} -> 12467.014
B102: Shared Tour (Trip.com) | C102: {=D102*$C$108} -> 2.1109517e+08 | D102: {=F102/$F$108} -> 0.0046426399 | F102: {=$F$108*'Actual Sales 2025'!D29} -> 144.58573
B103: Shared Tour (Headout.com) | C103: {=D103*$C$108} -> 88674749 | D103: {=F103/$F$108} -> 0.0019502338 | F103: {=$F$108*'Actual Sales 2025'!D30} -> 60.73613
B104: Shared Tour (Triping) | C104: {=D104*$C$108} -> 2.4672156e+08 | D104: {=F104/$F$108} -> 0.005426175 | F104: {=$F$108*'Actual Sales 2025'!D31} -> 168.98737
B105: Shared Tour (Luxury Escapes) | C105: {=D105*$C$108} -> 4.5127995e+08 | D105: {=F105/$F$108} -> 0.0099250507 | F105: {=$F$108*'Actual Sales 2025'!D32} -> 309.09586
B106: Shared Tour (MyBaliTrips) | C106: {=D106*$C$108} -> 5.9197282e+08 | D106: {=F106/$F$108} -> 0.013019325 | F106: {=$F$108*'Actual Sales 2025'!D33} -> 405.46083
B107: Shared Tour (Bluuu.tours) | C107: {=D107*$C$108} -> 1.5966635e+09 | D107: {=F107/$F$108} -> 0.035115601 | F107: {=$F$108*'Actual Sales 2025'!D34} -> 1093.6052
B108: Shared Tour Total | C108: {='RECOMMENDED PRICES'!C8*F108} -> 45468780000 | D108: {=SUM(D95:D107)} -> 1 | F108: {='Allocation OH and Target 2026'!M24} -> 31143
B110: Transfer (Pick Up + Drop Off) | C110: {='Trasnfers, Extras, Alco 2026'!G4} -> 4600800000 | D110: {=C110/$C$117} -> 0.91694154 | F110: {='Trasnfers, Extras, Alco 2026'!E4} -> 7668
B111: Transfer (Pick Up) | C111: {='Trasnfers, Extras, Alco 2026'!G5} -> 60600000 | D111: {=C111/$C$117} -> 0.012077608 | F111: {='Trasnfers, Extras, Alco 2026'!E5} -> 202
B112: Transfer (No Transfer) | C112: {='Trasnfers, Extras, Alco 2026'!G6} -> 0 | D112: {=C112/$C$117} -> 0 | F112: {='Trasnfers, Extras, Alco 2026'!E6} -> 4477
B113: Transfer (Drop Off) | C113: {='Trasnfers, Extras, Alco 2026'!G7} -> 137400000 | D113: {=C113/$C$117} -> 0.027383883 | F113: {='Trasnfers, Extras, Alco 2026'!E7} -> 458
B114: Transfer (Transfer 600K Pick Up + Drop Off) | C114: {='Trasnfers, Extras, Alco 2026'!G8} -> 18900000 | D114: {=C114/$C$117} -> 0.0037667786 | F114: {='Trasnfers, Extras, Alco 2026'!E8} -> 27
B115: Transfer (Transfer 300K Pick Up) | C115: {='Trasnfers, Extras, Alco 2026'!G9} -> 9450000 | D115: {=C115/$C$117} -> 0.0018833893 | F115: {='Trasnfers, Extras, Alco 2026'!E9} -> 27
B116: Transfer (Transfer 300K Drop Off) | C116: {='Trasnfers, Extras, Alco 2026'!G10} -> 190400000 | D116: {=C116/$C$117} -> 0.037946807 | F116: {='Trasnfers, Extras, Alco 2026'!E10} -> 544
B117: Transfer Services Total | C117: {=SUM(C110:C116)} -> 5017550000 | D117: {=C117/$C$117} -> 1 | F117: {=SUM(F110:F116)} -> 13403
B119: [LTR] Land Tour | C119: {='Trasnfers, Extras, Alco 2026'!G118} -> 2353500000 | D119: 1 | F119: {='Trasnfers, Extras, Alco 2026'!E118} -> 2615
B121: POS Sales + Extras (Alco and Food) | C121: {='Trasnfers, Extras, Alco 2026'!G111} -> 1537440000 | D121: 1 | F121: -
B123: Extra Services (GoPro10) | C123: {='Trasnfers, Extras, Alco 2026'!G37} -> 6000000 | D123: {=C123/$C$144} -> 0.008464247 | F123: {='Trasnfers, Extras, Alco 2026'!E37} -> 12
B124: Extra Services (Full Face Snorkel Mask) | C124: {='Trasnfers, Extras, Alco 2026'!G38} -> 0 | D124: {=C124/$C$144} -> 0 | F124: {='Trasnfers, Extras, Alco 2026'!E38} -> 8.4
B125: Extra Services (Fishing Rods) | C125: {='Trasnfers, Extras, Alco 2026'!G39} -> 0 | D125: {=C125/$C$144} -> 0 | F125: {='Trasnfers, Extras, Alco 2026'!E39} -> 13.2
B126: Extra Services (Kids Full Face Snorkel Mask) | C126: {='Trasnfers, Extras, Alco 2026'!G40} -> 0 | D126: {=C126/$C$144} -> 0 | F126: {='Trasnfers, Extras, Alco 2026'!E40} -> 440.4
B127: Extra Services (Kids Life Jacket (15-20 kg)) | C127: {='Trasnfers, Extras, Alco 2026'!G41} -> 0 | D127: {=C127/$C$144} -> 0 | F127: {='Trasnfers, Extras, Alco 2026'!E41} -> 192
B128: Extra Services (Kid Life Jacket (20-40 kg)) | C128: {='Trasnfers, Extras, Alco 2026'!G42} -> 0 | D128: {=C128/$C$144} -> 0 | F128: {='Trasnfers, Extras, Alco 2026'!E42} -> 324
B129: Extra Services (Party Decoration) | C129: {='Trasnfers, Extras, Alco 2026'!G43} -> 12600000 | D129: {=C129/$C$144} -> 0.017774919 | F129: {='Trasnfers, Extras, Alco 2026'!E43} -> 8.4
B130: Extra Services (Pro Photographer + Drone Pilot) | C130: {='Trasnfers, Extras, Alco 2026'!G44} -> 96000000 | D130: {=C130/$C$144} -> 0.13542795 | F130: {='Trasnfers, Extras, Alco 2026'!E44} -> 24
B131: Extra Services (Pro Photographer) | C131: {='Trasnfers, Extras, Alco 2026'!G45} -> 76560000 | D131: {=C131/$C$144} -> 0.10800379 | F131: {='Trasnfers, Extras, Alco 2026'!E45} -> 34.8
B132: Extra Services (Drone Pilot) | C132: {='Trasnfers, Extras, Alco 2026'!G46} -> 60000000 | D132: {=C132/$C$144} -> 0.08464247 | F132: {='Trasnfers, Extras, Alco 2026'!E46} -> 24
B133: Extra Services (Wetsuit) | C133: {='Trasnfers, Extras, Alco 2026'!G47} -> 11520000 | D133: {=C133/$C$144} -> 0.016251354 | F133: {='Trasnfers, Extras, Alco 2026'!E47} -> 38.4
B134: Extra Services (Advanced Divers) | C134: {='Trasnfers, Extras, Alco 2026'!G48} -> 69000000 | D134: {=C134/$C$144} -> 0.097338841 | F134: {='Trasnfers, Extras, Alco 2026'!E48} -> 30
... B143: Extra Services (Massage Table) | C143: {='Trasnfers, Extras, Alco 2026'!G57} -> 720000 | D143: {=C143/$C$144} -> 0.0010157096 | F143: {='Trasnfers, Extras, Alco 2026'!E57} -> 2.4
B144: Extra Services Total | C144: {=SUM(C123:C143)} -> 708864000 | D144: {=C144/$C$144} -> 1 | F144: {=SUM(F123:F143)} -> 1621.2
B147: COST OF GOODS SOLD | DIRECT COSTS | C147: {=SUM(C203,C205,C207,C230,C240,C242,C244,C246,C248)} -> 5.9894507e+10
B149: Sweetheart 4 | C149: {=_xlfn.IFERROR((VLOOKUP(B149,'Private Boats 2026 Target'!$C$2:$AF$1501,30,0)*F149),0)} -> 1.9557253e+08 | D149: {=C149/$C$203} -> 0.0085450495 | F149: {=VLOOKUP(B149,'Allocation OH and Target 2026'!$C$35:$K$91,9,0)} -> 28
B150: Riki J | C150: {=_xlfn.IFERROR((VLOOKUP(B150,'Private Boats 2026 Target'!$C$2:$AF$1501,30,0)*F150),0)} -> 417082300 | D150: {=C150/$C$203} -> 0.018223361 | F150: {=VLOOKUP(B150,'Allocation OH and Target 2026'!$C$35:$K$91,9,0)} -> 57
B151: Sanjaya | C151: {=_xlfn.IFERROR((VLOOKUP(B151,'Private Boats 2026 Target'!$C$2:$AF$1501,30,0)*F151),0)} -> 520880000 | D151: {=C151/$C$203} -> 0.02275854 | F151: {=VLOOKUP(B151,'Allocation OH and Target 2026'!$C$35:$K$91,9,0)} -> 68
B152: Jayanadi | C152: {=_xlfn.IFERROR((VLOOKUP(B152,'Private Boats 2026 Target'!$C$2:$AF$1501,30,0)*F152),0)} -> 616280000 | D152: {=C152/$C$203} -> 0.026926803 | F152: {=VLOOKUP(B152,'Allocation OH and Target 2026'!$C$35:$K$91,9,0)} -> 71
B153: Sea Dragon | C153: {=_xlfn.IFERROR((VLOOKUP(B153,'Private Boats 2026 Target'!$C$2:$AF$1501,30,0)*F153),0)} -> 520880000 | D153: {=C153/$C$203} -> 0.02275854 | F153: {=VLOOKUP(B153,'Allocation OH and Target 2026'!$C$35:$K$91,9,0)} -> 68
B154: Sanjaya O4 | C154: {=_xlfn.IFERROR((VLOOKUP(B154,'Private Boats 2026 Target'!$C$2:$AF$1501,30,0)*F154),0)} -> 8.3702333e+08 | D154: {=C154/$C$203} -> 0.036571627 | F154: {=VLOOKUP(B154,'Allocation OH and Target 2026'!$C$35:$K$91,9,0)} -> 85
B155: Sanjaya O5 | C155: {=_xlfn.IFERROR((VLOOKUP(B155,'Private Boats 2026 Target'!$C$2:$AF$1501,30,0)*F155),0)} -> 7.97634e+08 | D155: {=C155/$C$203} -> 0.03485061 | F155: {=VLOOKUP(B155,'Allocation OH and Target 2026'!$C$35:$K$91,9,0)} -> 81
B156: Almond Milk | C156: {=_xlfn.IFERROR((VLOOKUP(B156,'Private Boats 2026 Target'!$C$2:$AF$1501,30,0)*F156),0)} -> 377175600 | D156: {=C156/$C$203} -> 0.016479738 | F156: {=VLOOKUP(B156,'Allocation OH and Target 2026'!$C$35:$K$91,9,0)} -> 54
B157: Honey Milk | C157: {=_xlfn.IFERROR((VLOOKUP(B157,'Private Boats 2026 Target'!$C$2:$AF$1501,30,0)*F157),0)} -> 377175600 | D157: {=C157/$C$203} -> 0.016479738 | F157: {=VLOOKUP(B157,'Allocation OH and Target 2026'!$C$35:$K$91,9,0)} -> 54
B158: Eldorado 1 | C158: {=_xlfn.IFERROR((VLOOKUP(B158,'Private Boats 2026 Target'!$C$2:$AF$1501,30,0)*F158),0)} -> 4.4702293e+08 | D158: {=C158/$C$203} -> 0.019531542 | F158: {=VLOOKUP(B158,'Allocation OH and Target 2026'!$C$35:$K$91,9,0)} -> 64
...

Sheet FCF 2025-2026 Forecast
F2: Actual | G2: Actual | H2: Actual | I2: Actual | J2: Forecast | K2: Forecast | L2: Forecast | M2: Forecast | N2: Forecast | O2: Forecast | P2: Forecast | Q2: Forecast | R2: Forecast | S2: Forecast | T2: Forecast | U2: Forecast | V2: Forecast | W2: Forecast | X2: Forecast | Y2: Forecast | Z2: Forecast | AA2: Forecast | AB2: Forecast | AC2: Forecast | AD2: Forecast | AE2: Forecast | AF2: Forecast | AG2: Forecast | AH2: Forecast | AI2: Forecast | AJ2: Forecast | AK2: Forecast
B3: in thousands IDR | F3: 45413 | G3: 45444 | H3: 45474 | I3: 45505 | J3: 45536 | K3: 45566 | L3: 45597 | M3: 45627 | N3: 45658 | O3: 45689 | P3: 45717 | Q3: 45748 | R3: 45778 | S3: 45809 | T3: 45839 | U3: 45870 | V3: 45901 | W3: 45931 | X3: 45962 | Y3: 45992 | Z3: 46023 | AA3: 46054 | AB3: 46082 | AC3: 46113 | AD3: 46143 | AE3: 46174 | AF3: 46204 | AG3: 46235 | AH3: 46266 | AI3: 46296 | AJ3: 46327 | AK3: 46357
B4: Cash flows from operating activities:
B5: Net Inflows:
D6: Forecasted Sales | E6: {=50896.35*16272} -> 8.2818541e+08 | F6: {='Monthly PnL 2024'!K9/1000} -> 5785086.4 | G6: {='Monthly PnL 2024'!J9/1000} -> 6950616.2 | H6: {='Monthly PnL 2024'!I9/1000} -> 9183590.2 | I6: {='Monthly PnL 2024'!H9/1000} -> 9559343.1 | J6: {='Monthly PnL 2024'!G9/1000} -> 8068004.5 | K6: {='Monthly PnL 2024'!F9/1000} -> 6866898.6 | L6: {='Monthly PnL 2024'!E9/1000} -> 5429922.4 | M6: {='Monthly PnL 2024'!D9/1000} -> 4324886.3 | N6: 4130380 | O6: 2791144.7 | P6: {=3366730.999} -> 3366731 | Q6: {=7865187} -> 7865187 | R6: {=6810201} -> 6810201 | S6: {=7770035} -> 7770035 | T6: {=8891109} -> 8891109 | U6: {=9354106-424609} -> 8929497 | V6: {=7368862-443025} -> 6925837 | W6: {=7520717} -> 7520717 | X6: {=4258506-364365-151086} -> 3743055 | Y6: {=4750134-324168-226403} -> 4199563 | Z6: {=3960365} -> 3960365 | AA6: {=Z6*(100%+'PnL 2025'!K4)} -> 2645311.1 | AB6: {=AA6*(100%+'PnL 2025'!J4)} -> 3476906.4 | AC6: {=AB6*(100%+'PnL 2025'!I4)} -> 8030663.9 | AD6: {=AC6*(100%+'PnL 2025'!H4)} -> 6767509.6 | AE6: {=AD6*(100%+'PnL 2025'!G4)} -> 7842118.7 | AF6: {=AE6*(100%+'PnL 2025'!F4)} -> 8998930.5 | AG6: {=AF6*(100%+'PnL 2025'!E4)} -> 9029046.3 | AH6: {=AG6*(100%+'PnL 2025'!D4)} -> 6832504.8 | AI6: {=AH6*(100%+'PnL 2025'!C4)} -> 7751033.9 | AJ6: {=AI6*(100%+'PnL 2025'!N4)} -> 5957428.3 | AK6: {=AJ6*(100%+'PnL 2025'!M4)} -> 5444709.1
D7: NPM | E7: {=50896.35*16272} -> 8.2818541e+08 | F7: {=F8/F6} -> 0.2489949 | G7: {=G8/G6} -> 0.20299923 | H7: {=H8/H6} -> 0.25131771 | I7: {=I8/I6} -> 0.25722042 | J7: {=J8/J6} -> 0.22273309 | K7: {=K8/K6} -> 0.16986774 | L7: {=L8/L6} -> 0.15270839 | M7: {=M8/M6} -> 0.030486992 | ... Z7: {=Z8/Z6} -> 0.18770416 | AA7: 0.1 | AB7: 0.1 | AC7: 0.2 | AD7: 0.2 | AE7: 0.2 | AF7: 0.2 | AG7: 0.2 | AH7: 0.2 | AI7: 0.15 | AJ7: 0.12 | AK7: 0.1
D8: Net Income | E8: {=50896.35*16272} -> 8.2818541e+08 | F8: {='Monthly PnL 2024'!K5/1000} -> 1440457 | G8: {='Monthly PnL 2024'!J5/1000} -> 1410969.7 | H8: {='Monthly PnL 2024'!I5/1000} -> 2307998.9 | I8: {='Monthly PnL 2024'!H5/1000} -> 2458858.3 | J8: {='Monthly PnL 2024'!G5/1000} -> 1797011.6 | K8: {='Monthly PnL 2024'!F5/1000} -> 1166464.5 | L8: {='Monthly PnL 2024'!E5/1000} -> 829194.7 | M8: {='Monthly PnL 2024'!D5/1000} -> 131852.77 | N8: 171158 | O8: -273381 | P8: {=-87674} -> -87674 | Q8: {=1887227} -> 1887227 | R8: {=1197493} -> 1197493 | S8: {=1389404} -> 1389404 | T8: {=1788491} -> 1788491 | U8: 1672235.6 | V8: {=880192} -> 880192 | W8: {=1723148} -> 1723148 | X8: -464482.74 | Y8: {=397438} -> 397438 | Z8: {=743377} -> 743377 | AA8: {=AA6*AA7} -> 264531.11 | AB8: {=AB6*AB7} -> 347690.64 | AC8: {=AC6*AC7} -> 1606132.8 | AD8: {=AD6*AD7} -> 1353501.9 | AE8: {=AE6*AE7} -> 1568423.7 | AF8: {=AF6*AF7} -> 1799786.1 | AG8: {=AG6*AG7} -> 1805809.3 | AH8: {=AH6*AH7} -> 1366501 | ... AK8: {=AK6*AK7} -> 544470.91
B9: Current month outflows: | E9: {=50896.35*16272} -> 8.2818541e+08
D10: Current Month Payroll | F10: 0 | G10: 0 | H10: 0 | I10: 0 | J10: 0 | K10: 0 | L10: 0 | M10: 0 | N10: 0 | O10: 0 | P10: 0 | Q10: 0 | R10: 0 | S10: 0 | T10: 0 | U10: 0 | V10: 0 | W10: 0 | X10: 0 | Y10: 0 | Z10: 0 | AA10: 0 | AB10: 0 | AC10: 0 | AD10: 0 | AE10: 0 | AF10: 0 | AG10: 0 | AH10: 0 | AI10: 0 | AJ10: 0 | AK10: 0
D11: LM Overhaul | E11: {=50896.35*16272} -> 8.2818541e+08 | F11: 0 | G11: 0 | H11: 0 | I11: 0 | J11: 0 | K11: 0 | L11: 0 | M11: 0 | N11: 0 | O11: 0 | P11: 0 | Q11: 0 | R11: 0 | S11: 0 | T11: 0 | U11: 0 | V11: 0 | W11: 0 | X11: 0 | Y11: 0 | Z11: 0 | AA11: 0 | AB11: 0 | AC11: 0 | AD11: 0 | AE11: 0 | AF11: 0 | AG11: 0 | AH11: 0 | AI11: 0 | AJ11: 0 | AK11: 0
D12: RJ Overhaul | F12: 0 | G12: 0 | H12: 0 | I12: 0 | J12: 0 | K12: 0 | L12: 0 | M12: 0 | N12: 0 | O12: 0 | P12: 0 | Q12: 0 | R12: 0 | S12: 0 | T12: 0 | U12: 0 | V12: 0 | W12: 0 | X12: 0 | Y12: 0 | Z12: 0 | AA12: 0 | AB12: -60000 | AC12: -120000 | AD12: 0 | AE12: 0 | AF12: 0 | AG12: 0 | AH12: 0 | AI12: 0 | AJ12: 0 | AK12: 0
D13: SH4 Overhaul | F13: 0 | G13: 0 | H13: 0 | I13: 0 | J13: 0 | K13: 0 | L13: 0 | M13: 0 | N13: 0 | O13: 0 | P13: 0 | Q13: 0 | R13: 0 | S13: 0 | T13: 0 | U13: 0 | V13: 0 | W13: 0 | X13: 0 | Y13: 0 | Z13: 0 | AA13: 0 | AB13: 0 | AC13: 0 | AD13: 0 | AE13: 0 | AF13: -124000 | AG13: 0 | AH13: 0 | AI13: 0 | AJ13: 0 | AK13: 0
D14: AM Overhaul | F14: 0 | G14: 0 | H14: 0 | I14: 0 | J14: 0 | K14: 0 | L14: 0 | M14: 0 | N14: 0 | O14: 0 | P14: 0 | Q14: 0 | R14: 0 | S14: 0 | T14: 0 | U14: 0 | V14: 0 | W14: 0 | X14: 0 | Y14: 0 | Z14: 0 | AA14: 0 | AB14: 0 | AC14: -84000 | AD14: 0 | AE14: 0 | AF14: 0 | AG14: 0 | AH14: 0 | AI14: 0 | AJ14: 0 | AK14: 0
D15: HM Overhaul | F15: 0 | G15: 0 | H15: 0 | I15: 0 | J15: 0 | K15: 0 | L15: 0 | M15: 0 | N15: 0 | O15: 0 | P15: 0 | Q15: 0 | R15: 0 | S15: 0 | T15: 0 | U15: 0 | V15: 0 | W15: 0 | X15: 0 | Y15: 0 | Z15: 0 | AA15: 0 | AB15: 0 | AC15: 0 | AD15: -84000 | AE15: 0 | AF15: 0 | AG15: 0 | AH15: 0 | AI15: 0 | AJ15: 0 | AK15: 0
D16: Unplanned expenses | E16: {=50896.35*16272} -> 8.2818541e+08 | F16: 0 | G16: 0 | H16: 0 | I16: 0 | J16: 0 | K16: 0 | L16: 0 | M16: 0 | N16: 0 | O16: 0 | P16: 0 | Q16: 0 | R16: 0 | S16: 0 | T16: 0 | U16: 0 | V16: 0 | W16: 0 | X16: 0 | Y16: 0 | Z16: 0 | AA16: 0 | AB16: 0 | AC16: 0 | AD16: 0 | AE16: 0 | AF16: 0 | AG16: 0 | AH16: 0 | AI16: 0 | AJ16: 0 | AK16: 0
E17: {=50896.35*16272} -> 8.2818541e+08
B18: Cash flows from investing activities: | E18: {=50896.35*16272} -> 8.2818541e+08
B19: Project Serangan: | E19: {=50896.35*16272} -> 8.2818541e+08
B20: Total project cost | D20: {=-SUM(F21:V25)+180000+959972+180000} -> 1319972
D21: Pergola payment #2 | E21: {=50896.35*16272} -> 8.2818541e+08 | F21: 0 | G21: 0 | H21: 0 | I21: 0 | J21: 0 | K21: 0 | L21: 0 | M21: 0 | N21: 0 | O21: 0 | P21: 0 | Q21: 0 | R21: 0 | S21: 0 | T21: 0 | U21: 0 | V21: 0 | W21: 0 | X21: 0 | Y21: 0 | Z21: 0 | AA21: 0 | AB21: 0 | AC21: 0 | AD21: 0 | AE21: 0 | AF21: 0 | AG21: 0 | AH21: 0 | AI21: 0 | AJ21: 0 | AK21: 0
D22: Plants and gardening | E22: {=50896.35*16272} -> 8.2818541e+08 | F22: 0 | G22: 0 | H22: 0 | I22: 0 | J22: 0 | K22: 0 | L22: 0 | M22: 0 | N22: 0 | O22: 0 | P22: 0 | Q22: 0 | R22: 0 | S22: 0 | T22: 0 | U22: 0 | V22: 0 | W22: 0 | X22: 0 | Y22: 0 | Z22: 0 | AA22: 0 | AB22: 0 | AC22: 0 | AD22: 0 | AE22: 0 | AF22: 0 | AG22: 0 | AH22: 0 | AI22: 0 | AJ22: 0 | AK22: 0
D23: Furniture and other equipment | E23: {=50896.35*16272} -> 8.2818541e+08 | F23: 0 | G23: 0 | H23: 0 | I23: 0 | J23: 0 | K23: 0 | L23: 0 | M23: 0 | N23: 0 | O23: 0 | P23: 0 | Q23: 0 | R23: 0 | S23: 0 | T23: 0 | U23: 0 | V23: 0 | W23: 0 | X23: 0 | Y23: 0 | Z23: 0 | AA23: 0 | AB23: 0 | AC23: 0 | AD23: 0 | AE23: 0 | AF23: 0 | AG23: 0 | AH23: 0 | AI23: 0 | AJ23: 0 | AK23: 0
D24: Construction and other Arif's payments | F24: 0 | G24: 0 | H24: 0 | I24: 0 | J24: 0 | K24: 0 | L24: 0 | M24: 0 | N24: 0 | O24: 0 | P24: 0 | Q24: 0 | R24: 0 | S24: 0 | T24: 0 | U24: 0 | V24: 0 | W24: 0 | X24: 0 | Y24: 0 | Z24: 0 | AA24: 0 | AB24: 0 | AC24: 0 | AD24: 0 | AE24: 0 | AF24: 0 | AG24: 0 | AH24: 0 | AI24: 0 | AJ24: 0 | AK24: 0
D25: Second rent payment | F25: 0 | G25: 0 | H25: 0 | I25: 0 | J25: 0 | K25: 0 | L25: 0 | M25: 0 | N25: 0 | O25: 0 | P25: 0 | Q25: 0 | R25: 0 | S25: 0 | T25: 0 | U25: 0 | V25: 0 | W25: 0 | X25: 0 | Y25: 0 | Z25: 0 | AA25: 0 | AB25: 0 | AC25: 0 | AD25: 0 | AE25: 0 | AF25: 0 | AG25: 0 | AH25: 0 | AI25: 0 | AJ25: 0 | AK25: 0
B27: Project Bali Boat Builders:
B28: Total project cost | D28: {=-SUM(F34:V54)} -> 0
D29: Advance from Arya | F29: 0 | G29: 0 | H29: 0 | I29: 0 | J29: 0 | K29: 0 | L29: 0 | M29: 0 | N29: 0 | O29: 0 | P29: 0 | Q29: 0 | R29: 0 | S29: 0 | T29: 0 | U29: 0 | V29: 0 | W29: 0 | X29: 0 | Y29: 0 | Z29: 0 | AA29: 0 | AB29: 110000 | AC29: 0 | AD29: 0 | AE29: 0 | AF29: 0 | AG29: 0 | AH29: 0 | AI29: 0 | AJ29: 0 | AK29: 0
D30: Advance from Eugene | F30: 0 | G30: 0 | H30: 0 | I30: 0 | J30: 0 | K30: 0 | L30: 0 | M30: 0 | N30: 0 | O30: 0 | P30: 0 | Q30: 0 | R30: 0 | S30: 0 | T30: 0 | U30: 0 | V30: 0 | W30: 0 | X30: 0 | Y30: 0 | Z30: 0 | AA30: 0 | AB30: 0 | AC30: 0 | AD30: 0 | AE30: 0 | AF30: 0 | AG30: 0 | AH30: 0 | AI30: 0 | AJ30: 0 | AK30: 0
D31: Advance from Vadim Boat 4 | F31: 0 | G31: 0 | H31: 0 | I31: 0 | J31: 0 | K31: 0 | L31: 0 | M31: 0 | N31: 0 | O31: 0 | P31: 0 | Q31: 0 | R31: 0 | S31: 0 | T31: 0 | U31: 0 | V31: 0 | W31: 0 | X31: 0 | Y31: 0 | Z31: 0 | AA31: {=2490000*30%} -> 747000 | AB31: 0 | AC31: {=2490000*40%} -> 996000 | AD31: 0 | AE31: 0 | AF31: 0 | AG31: 0 | AH31: 0 | AI31: 0 | AJ31: 0 | AK31: 0
D32: Advance from Robert Boat 5 | F32: 0 | G32: 0 | H32: 0 | I32: 0 | J32: 0 | K32: 0 | L32: 0 | M32: 0 | N32: 0 | O32: 0 | P32: 0 | Q32: 0 | R32: 0 | S32: 0 | T32: 0 | U32: 0 | V32: 0 | W32: 0 | X32: 0 | Y32: 0 | Z32: 0 | AA32: 0 | AB32: {=2770000*30%} -> 831000 | AC32: 0 | AD32: {=2770000*40%} -> 1108000 | AE32: 0 | AF32: 0 | AG32: 0 | AH32: 0 | AI32: 0 | AJ32: 0 | AK32: 0
D33: Advance from Osamah Boat 6 | F33: 0 | G33: 0 | H33: 0 | I33: 0 | J33: 0 | K33: 0 | L33: 0 | M33: 0 | N33: 0 | O33: 0 | P33: 0 | Q33: 0 | R33: 0 | S33: 0 | T33: 0 | U33: 0 | V33: 0 | W33: 0 | X33: 0 | Y33: 0 | Z33: 0 | AA33: 917000 | AB33: 0 | AC33: {=2936000*30%} -> 880800 | AD33: 0 | AE33: {=2936000*40%} -> 1174400 | AF33: 0 | AG33: 0 | AH33: 0 | AI33: 0 | AJ33: 0 | AK33: 0
D34: Loan to PT Fortune Yachts Bali | F34: 0 | G34: 0 | H34: 0 | I34: 0 | J34: 0 | K34: 0 | L34: 0 | M34: 0 | N34: 0 | O34: 0 | P34: 0 | Q34: 0 | R34: 0 | T34: 0 | U34: 0 | V34: 0 | W34: 0 | X34: 0 | Y34: 0 | Z34: 0 | AA34: -140000 | AB34: -140000 | AC34: -140000 | AD34: 0 | AE34: 0 | AF34: 0 | AG34: 0 | AH34: 0 | AI34: 0 | AJ34: 0 | AK34: 0
D35: Order Boat 1 | F35: 0 | G35: 0 | H35: 0 | I35: 0 | J35: 0 | K35: 0 | L35: 0 | M35: 0 | N35: 0 | O35: 0 | P35: 0 | Q35: 0 | R35: 0 | S35: 0 | T35: 0 | U35: 0 | V35: 0 | W35: 0 | X35: 0 | Y35: 0 | Z35: 0 | AA35: {=-453600+120000+70000+50000+50000+50000+50000+50000} -> -13600 | AB35: 0 | AC35: 0 | AD35: 0 | AE35: 0 | AF35: 0 | AG35: 0 | AH35: 0 | AI35: 0 | AJ35: 0 | AK35: 0
D36: Order Boat 2 | F36: 0 | G36: 0 | H36: 0 | I36: 0 | J36: 0 | K36: 0 | L36: 0 | M36: 0 | N36: 0 | O36: 0 | P36: 0 | Q36: 0 | R36: 0 | T36: 0 | U36: 0 | V36: 0 | W36: 0 | X36: 0 | Y36: 0 | Z36: 0 | AA36: {=-453600+50000+50000+50000+50000+50000+50000+50000+20000+20000+20000+10000+10000} -> -23600 | AB36: 0 | AC36: 0 | AD36: 0 | AE36: 0 | AF36: 0 | AG36: 0 | AH36: 0 | AI36: 0 | AJ36: 0 | AK36: 0
D37: Order Boat 3 | F37: 0 | G37: 0 | H37: 0 | I37: 0 | J37: 0 | K37: 0 | L37: 0 | M37: 0 | N37: 0 | O37: 0 | P37: 0 | Q37: 0 | R37: 0 | S37: 0 | T37: 0 | U37: 0 | V37: 0 | W37: 0 | X37: 0 | Y37: 0 | Z37: 0 | AA37: {=-453600+40000+50000+100000+50000+30000+30000+30000+20000+30000+20000+20000} -> -33600 | AB37: 0 | AC37: 0 | AD37: 0 | AE37: 0 | AF37: 0 | AG37: 0 | AH37: 0 | AI37: 0 | AJ37: 0 | AK37: 0
D38: Order Boat 4 | F38: 0 | G38: 0 | H38: 0 | I38: 0 | J38: 0 | K38: 0 | L38: 0 | M38: 0 | N38: 0 | O38: 0 | P38: 0 | Q38: 0 | R38: 0 | S38: 0 | T38: 0 | U38: 0 | V38: 0 | W38: 0 | X38: 0 | Y38: 0 | Z38: 0 | AA38: {=-453600+100000+50000+50000+50000+50000+20000} -> -133600 | AB38: 0 | AC38: 0 | AD38: 0 | AE38: 0 | AF38: 0 | AG38: 0 | AH38: 0 | AI38: 0 | AJ38: 0 | AK38: 0
D39: Order Boat 5 | F39: 0 | G39: 0 | H39: 0 | I39: 0 | J39: 0 | K39: 0 | L39: 0 | M39: 0 | N39: 0 | O39: 0 | P39: 0 | Q39: 0 | R39: 0 | S39: 0 | T39: 0 | U39: 0 | V39: 0 | W39: 0 | X39: 0 | Y39: 0 | Z39: 0 | AA39: {=-453600+200000+50000+20000} -> -183600 | AB39: 0 | AC39: 0 | AD39: 0 | AE39: 0 | AF39: 0 | AG39: 0 | AH39: 0 | AI39: 0 | AJ39: 0 | AK39: 0
D40: Order Boat 6 | F40: 0 | G40: 0 | H40: 0 | I40: 0 | J40: 0 | K40: 0 | L40: 0 | M40: 0 | N40: 0 | O40: 0 | P40: 0 | Q40: 0 | R40: 0 | S40: 0 | T40: 0 | U40: 0 | V40: 0 | W40: 0 | X40: 0 | Y40: 0 | Z40: 0 | AA40: -453600 | AB40: 0 | AC40: 0 | AD40: 0 | AE40: 0 | AF40: 0 | AG40: 0 | AH40: 0 | AI40: 0 | AJ40: 0 | AK40: 0
D41: Order Boat 7 | F41: 0 | G41: 0 | H41: 0 | I41: 0 | J41: 0 | K41: 0 | L41: 0 | M41: 0 | N41: 0 | O41: 0 | P41: 0 | Q41: 0 | R41: 0 | S41: 0 | T41: 0 | U41: 0 | V41: 0 | W41: 0 | X41: 0 | Y41: 0 | Z41: 0 | AA41: 0 | AB41: 0 | AC41: 0 | AD41: -453600 | AE41: 0 | AF41: 0 | AG41: 0 | AH41: 0 | AI41: 0 | AJ41: 0 | AK41: 0
D42: Order Boat 8 | F42: 0 | G42: 0 | H42: 0 | I42: 0 | J42: 0 | K42: 0 | L42: 0 | M42: 0 | N42: 0 | O42: 0 | P42: 0 | Q42: 0 | R42: 0 | S42: 0 | T42: 0 | U42: 0 | V42: 0 | W42: 0 | X42: 0 | Y42: 0 | Z42: 0 | AA42: 0 | AB42: 0 | AC42: 0 | AD42: 0 | AE42: -453600 | AF42: 0 | AG42: 0 | AH42: 0 | AI42: 0 | AJ42: 0 | AK42: 0
D43: Engines x2 Yamaha 250hp (Boat 1) | F43: 0 | G43: 0 | H43: 0 | I43: 0 | J43: 0 | K43: 0 | L43: 0 | M43: 0 | N43: 0 | O43: 0 | P43: 0 | Q43: 0 | R43: 0 | S43: 0 | T43: 0 | U43: 0 | V43: 0 | W43: 0 | X43: 0 | Y43: 0 | Z43: 0 | AA43: 0 | AB43: 0 | AC43: 0 | AD43: 0 | AE43: 0 | AF43: 0 | AG43: 0 | AH43: 0 | AI43: 0 | AJ43: 0 | AK43: 0
D44: Documentation and other (Boat 1) | F44: 0 | G44: 0 | H44: 0 | I44: 0 | J44: 0 | K44: 0 | L44: 0 | M44: 0 | N44: 0 | O44: 0 | P44: 0 | Q44: 0 | R44: 0 | S44: 0 | T44: 0 | U44: 0 | V44: 0 | W44: 0 | X44: 0 | Y44: 0 | Z44: 0 | AA44: {=-130000+62000+30000+30000} -> -8000 | AB44: -50000 | AC44: 0 | AD44: 0 | AE44: 0 | AF44: 0 | AG44: 0 | AH44: 0 | AI44: 0 | AJ44: 0 | AK44: 0
D45: Engines x2 Yamaha 250hp (Boat 2) | F45: 0 | G45: 0 | H45: 0 | I45: 0 | J45: 0 | K45: 0 | L45: 0 | M45: 0 | N45: 0 | O45: 0 | P45: 0 | Q45: 0 | R45: 0 | S45: 0 | T45: 0 | U45: 0 | V45: 0 | W45: 0 | X45: 0 | Y45: 0 | Z45: 0 | AA45: 0 | AB45: 0 | AC45: 0 | AD45: 0 | AE45: 0 | AF45: 0 | AG45: 0 | AH45: 0 | AI45: 0 | AJ45: 0 | AK45: 0
D46: Documentation and other (Boat 2) | F46: 0 | G46: 0 | H46: 0 | I46: 0 | J46: 0 | K46: 0 | L46: 0 | M46: 0 | N46: 0 | O46: 0 | P46: 0 | Q46: 0 | R46: 0 | S46: 0 | T46: 0 | U46: 0 | V46: 0 | W46: 0 | X46: 0 | Y46: 0 | Z46: 0 | AA46: {=-130000+50000} -> -80000 | AB46: -50000 | AC46: 0 | AD46: 0 | AE46: 0 | AF46: 0 | AG46: 0 | AH46: 0 | AI46: 0 | AJ46: 0 | AK46: 0
D47: Engines x2 Yamaha 250hp (Boat 3) | F47: 0 | G47: 0 | H47: 0 | I47: 0 | J47: 0 | K47: 0 | L47: 0 | M47: 0 | N47: 0 | O47: 0 | P47: 0 | Q47: 0 | R47: 0 | S47: 0 | T47: 0 | U47: 0 | V47: 0 | W47: 0 | X47: 0 | Y47: 0 | Z47: 0 | AA47: {=-510000+50000} -> -460000 | AB47: 0 | AC47: 0 | AD47: 0 | AE47: 0 | AF47: 0 | AG47: 0 | AH47: 0 | AI47: 0 | AJ47: 0 | AK47: 0
D48: Documentation and other (Boat 3) | F48: 0 | G48: 0 | H48: 0 | I48: 0 | J48: 0 | K48: 0 | L48: 0 | M48: 0 | N48: 0 | O48: 0 | P48: 0 | Q48: 0 | R48: 0 | S48: 0 | T48: 0 | U48: 0 | V48: 0 | W48: 0 | X48: 0 | Y48: 0 | Z48: 0 | AA48: -130000 | AB48: -50000 | AC48: 0 | AD48: 0 | AE48: 0 | AF48: 0 | AG48: 0 | AH48: 0 | AI48: 0 | AJ48: 0 | AK48: 0
D49: Engines x2 Yamaha 250hp (Boat 4) | F49: 0 | G49: 0 | H49: 0 | I49: 0 | J49: 0 | K49: 0 | L49: 0 | M49: 0 | N49: 0 | O49: 0 | P49: 0 | Q49: 0 | R49: 0 | S49: 0 | T49: 0 | U49: 0 | V49: 0 | W49: 0 | X49: 0 | Y49: 0 | Z49: 0 | AA49: 0 | AB49: -510000 | AC49: 0 | AD49: 0 | AE49: 0 | AF49: 0 | AG49: 0 | AH49: 0 | AI49: 0 | AJ49: 0 | AK49: 0
D50: Documentation and other (Boat 4) | F50: 0 | G50: 0 | H50: 0 | I50: 0 | J50: 0 | K50: 0 | L50: 0 | M50: 0 | N50: 0 | O50: 0 | P50: 0 | Q50: 0 | R50: 0 | S50: 0 | T50: 0 | U50: 0 | V50: 0 | W50: 0 | X50: 0 | Y50: 0 | Z50: 0 | AA50: 0 | AB50: -130000 | AC50: -50000 | AD50: 0 | AE50: 0 | AF50: 0 | AG50: 0 | AH50: 0 | AI50: 0 | AJ50: 0 | AK50: 0
D51: Engines x2 Yamaha 250hp (Boat 5) | F51: 0 | G51: 0 | H51: 0 | I51: 0 | J51: 0 | K51: 0 | L51: 0 | M51: 0 | N51: 0 | O51: 0 | P51: 0 | Q51: 0 | R51: 0 | S51: 0 | T51: 0 | U51: 0 | V51: 0 | W51: 0 | X51: 0 | Y51: 0 | Z51: 0 | AA51: 0 | AB51: 0 | AC51: -510000 | AD51: 0 | AE51: 0 | AF51: 0 | AG51: 0 | AH51: 0 | AI51: 0 | AJ51: 0 | AK51: 0
D52: Documentation and other (Boat 5) | F52: 0 | G52: 0 | H52: 0 | I52: 0 | J52: 0 | K52: 0 | L52: 0 | M52: 0 | N52: 0 | O52: 0 | P52: 0 | Q52: 0 | R52: 0 | S52: 0 | T52: 0 | U52: 0 | V52: 0 | W52: 0 | X52: 0 | Y52: 0 | Z52: 0 | AA52: 0 | AB52: 0 | AC52: -130000 | AD52: -50000 | AE52: 0 | AF52: 0 | AG52: 0 | AH52: 0 | AI52: 0 | AJ52: 0 | AK52: 0
D53: Engines x2 Yamaha 250hp (Boat 6) | F53: 0 | G53: 0 | H53: 0 | I53: 0 | J53: 0 | K53: 0 | L53: 0 | M53: 0 | N53: 0 | O53: 0 | P53: 0 | Q53: 0 | R53: 0 | S53: 0 | T53: 0 | U53: 0 | V53: 0 | W53: 0 | X53: 0 | Y53: 0 | Z53: 0 | AA53: 0 | AB53: 0 | AC53: 0 | AD53: 0 | AE53: -510000 | AF53: 0 | AG53: 0 | AH53: 0 | AI53: 0 | AJ53: 0 | AK53: 0
D54: Documentation and other (Boat 6) | F54: 0 | G54: 0 | H54: 0 | I54: 0 | J54: 0 | K54: 0 | L54: 0 | M54: 0 | N54: 0 | O54: 0 | P54: 0 | Q54: 0 | R54: 0 | S54: 0 | T54: 0 | U54: 0 | V54: 0 | W54: 0 | X54: 0 | Y54: 0 | Z54: 0 | AA54: 0 | AB54: 0 | AC54: 0 | AD54: 0 | AE54: -130000 | AF54: -50000 | AG54: 0 | AH54: 0 | AI54: 0 | AJ54: 0 | AK54: 0
D55: Engines x2 Yamaha 250hp (Boat 7) | F55: 0 | G55: 0 | H55: 0 | I55: 0 | J55: 0 | K55: 0 | L55: 0 | M55: 0 | N55: 0 | O55: 0 | P55: 0 | Q55: 0 | R55: 0 | S55: 0 | T55: 0 | U55: 0 | V55: 0 | W55: 0 | X55: 0 | Y55: 0 | Z55: 0 | AA55: 0 | AB55: 0 | AC55: 0 | AD55: 0 | AE55: 0 | AF55: 0 | AG55: -510000 | AH55: 0 | AI55: 0 | AJ55: 0 | AK55: 0
D56: Documentation and other (Boat 7) | F56: 0 | G56: 0 | H56: 0 | I56: 0 | J56: 0 | K56: 0 | L56: 0 | M56: 0 | N56: 0 | O56: 0 | P56: 0 | Q56: 0 | R56: 0 | S56: 0 | T56: 0 | U56: 0 | V56: 0 | W56: 0 | X56: 0 | Y56: 0 | Z56: 0 | AA56: 0 | AB56: 0 | AC56: 0 | AD56: 0 | AE56: 0 | AF56: 0 | AG56: -130000 | AH56: -50000 | AI56: 0 | AJ56: 0 | AK56: 0
D57: Engines x2 Yamaha 250hp (Boat 8) | F57: 0 | G57: 0 | H57: 0 | I57: 0 | J57: 0 | K57: 0 | L57: 0 | M57: 0 | N57: 0 | O57: 0 | P57: 0 | Q57: 0 | R57: 0 | S57: 0 | T57: 0 | U57: 0 | V57: 0 | W57: 0 | X57: 0 | Y57: 0 | Z57: 0 | AA57: 0 | AB57: 0 | AC57: 0 | AD57: 0 | AE57: 0 | AF57: 0 | AG57: 0 | AH57: -510000 | AI57: 0 | AJ57: 0 | AK57: 0
D58: Documentation and other (Boat 8) | F58: 0 | G58: 0 | H58: 0 | I58: 0 | J58: 0 | K58: 0 | L58: 0 | M58: 0 | N58: 0 | O58: 0 | P58: 0 | Q58: 0 | R58: 0 | S58: 0 | T58: 0 | U58: 0 | V58: 0 | W58: 0 | X58: 0 | Y58: 0 | Z58: 0 | AA58: 0 | AB58: 0 | AC58: 0 | AD58: 0 | AE58: 0 | AF58: 0 | AG58: 0 | AH58: -130000 | AI58: -50000 | AJ58: 0 | AK58: 0
B60: Project AM & HM - COMPLETED:
B61: Total project cost | D61: {=195000+195000+195000+195000+195000+100000+195000-SUM(F61:V67)} -> 1270000
D62: Boat 1 Construction (Almond Milk) | F62: 0 | G62: 0 | H62: 0 | I62: 0 | J62: 0 | K62: 0 | L62: 0 | M62: 0 | N62: 0 | O62: 0 | P62: 0 | Q62: 0 | R62: 0 | S62: 0 | T62: 0 | U62: 0 | V62: 0 | W62: 0 | X62: 0 | Y62: 0 | Z62: 0 | AA62: 0 | AB62: 0 | AC62: 0 | AD62: 0 | AE62: 0 | AF62: 0 | AG62: 0 | AH62: 0 | AI62: 0 | AJ62: 0 | AK62: 0
D63: Boat 2 Construction (Oat Milk) | F63: 0 | G63: 0 | H63: 0 | I63: 0 | J63: 0 | K63: 0 | L63: 0 | M63: 0 | N63: 0 | O63: 0 | P63: 0 | Q63: 0 | R63: 0 | S63: 0 | T63: 0 | U63: 0 | V63: 0 | W63: 0 | X63: 0 | Y63: 0 | Z63: 0 | AA63: 0 | AB63: 0 | AC63: 0 | AD63: 0 | AE63: 0 | AF63: 0 | AG63: 0 | AH63: 0 | AI63: 0 | AJ63: 0 | AK63: 0
D64: Engines x2 Yamaha 250hp (Boat 1) | E64: {=50896.35*16272} -> 8.2818541e+08 | F64: 0 | G64: 0 | H64: 0 | I64: 0 | J64: 0 | K64: 0 | L64: 0 | M64: 0 | N64: 0 | O64: 0 | P64: 0 | Q64: 0 | R64: 0 | S64: 0 | T64: 0 | U64: 0 | V64: 0 | W64: 0 | X64: 0 | Y64: 0 | Z64: 0 | AA64: 0 | AB64: 0 | AC64: 0 | AD64: 0 | AE64: 0 | AF64: 0 | AG64: 0 | AH64: 0 | AI64: 0 | AJ64: 0 | AK64: 0
D65: Engines x2 Yamaha 250hp (Boat 2) | F65: 0 | G65: 0 | H65: 0 | I65: 0 | J65: 0 | K65: 0 | L65: 0 | M65: 0 | N65: 0 | O65: 0 | P65: 0 | Q65: 0 | R65: 0 | S65: 0 | T65: 0 | U65: 0 | V65: 0 | W65: 0 | X65: 0 | Y65: 0 | Z65: 0 | AA65: 0 | AB65: 0 | AC65: 0 | AD65: 0 | AE65: 0 | AF65: 0 | AG65: 0 | AH65: 0 | AI65: 0 | AJ65: 0 | AK65: 0
D66: Documentation and other (Boat 1) | F66: 0 | G66: 0 | H66: 0 | I66: 0 | J66: 0 | K66: 0 | L66: 0 | M66: 0 | N66: 0 | O66: 0 | P66: 0 | Q66: 0 | R66: 0 | S66: 0 | T66: 0 | U66: 0 | V66: 0 | W66: 0 | X66: 0 | Y66: 0 | Z66: 0 | AA66: 0 | AB66: 0 | AC66: 0 | AD66: 0 | AE66: 0 | AF66: 0 | AG66: 0 | AH66: 0 | AI66: 0 | AJ66: 0 | AK66: 0
D67: Documentation and other (Boat 2) | F67: 0 | G67: 0 | H67: 0 | I67: 0 | J67: 0 | K67: 0 | L67: 0 | M67: 0 | N67: 0 | O67: 0 | P67: 0 | Q67: 0 | R67: 0 | S67: 0 | T67: 0 | U67: 0 | V67: 0 | W67: 0 | X67: 0 | Y67: 0 | Z67: 0 | AA67: 0 | AB67: 0 | AC67: 0 | AD67: 0 | AE67: 0 | AF67: 0 | AG67: 0 | AH67: 0 | AI67: 0 | AJ67: 0 | AK67: 0
B69: Equiipment replenishment :
D70: Diving Sets | F70: 0 | G70: 0 | H70: 0 | I70: 0 | J70: 0 | K70: 0 | L70: 0 | M70: 0 | N70: 0 | O70: 0 | P70: 0 | Q70: 0 | R70: 0 | S70: 0 | T70: 0 | U70: 0 | V70: 0 | W70: 0 | X70: 0 | Y70: 0 | Z70: 0 | AA70: 0 | AB70: 0 | AC70: 0 | AD70: 0 | AE70: 0 | AF70: 0 | AG70: 0 | AH70: 0 | AI70: 0 | AJ70: 0 | AK70: 0
D71: Serangan Office - Part 2 Rent | F71: 0 | G71: 0 | H71: 0 | I71: 0 | J71: 0 | K71: 0 | L71: 0 | M71: 0 | N71: 0 | O71: 0 | P71: 0 | Q71: 0 | R71: 0 | S71: 0 | T71: 0 | U71: 0 | V71: 0 | W71: 0 | X71: 0 | Y71: 0 | Z71: 0 | AA71: 0 | AB71: 0 | AC71: 0 | AD71: -160000 | AE71: 0 | AF71: 0 | AG71: 0 | AH71: 0 | AI71: 0 | AJ71: 0 | AK71: 0
D72: Serangan Office - Leasehold Improvements | F72: 0 | G72: 0 | H72: 0 | I72: 0 | J72: 0 | K72: 0 | L72: 0 | M72: 0 | N72: 0 | O72: 0 | P72: 0 | Q72: 0 | R72: 0 | S72: 0 | T72: 0 | U72: 0 | V72: 0 | W72: 0 | X72: 0 | Y72: 0 | Z72: 0 | AA72: 0 | AB72: 0 | AC72: 0 | AD72: 0 | AE72: 0 | AF72: 0 | AG72: 0 | AH72: 0 | AI72: 0 | AJ72: 0 | AK72: 0
D73: Fixed assets and equipment replenishment | F73: 0 | G73: 0 | H73: 0 | I73: 0 | J73: 0 | K73: 0 | L73: 0 | M73: 0 | N73: 0 | O73: 0 | P73: 0 | Q73: 0 | R73: 0 | S73: 0 | T73: 0 | U73: 0 | V73: 0 | W73: 0 | X73: 0 | Y73: 0 | Z73: 0 | AA73: -30000 | AB73: -100000 | AC73: -100000 | AD73: -100000 | AE73: -100000 | AF73: -100000 | AG73: -100000 | AH73: -100000 | AI73: -100000 | AJ73: -100000 | AK73: -100000
E74: {=50896.35*16272} -> 8.2818541e+08
B75: Cash flows from financing activities:
D76: Advance from Klook | F76: 0 | G76: 0 | H76: 0 | I76: 0 | J76: 0 | K76: 0 | L76: 0 | M76: 0 | N76: 0 | O76: 0 | P76: 0 | Q76: 0 | R76: 0 | S76: 0 | T76: 0 | U76: 0 | V76: 0 | W76: 0 | X76: 0 | Y76: 0 | Z76: 0 | AA76: -250000 | AB76: -400000 | AC76: -400000 | AD76: 1200000 | AE76: -400000 | AF76: -400000 | AG76: -400000 | AH76: 1200000 | AI76: -400000 | AJ76: -400000 | AK76: -400000
D77: Divindends/Loan to Alex (villa rent) | F77: 0 | G77: 0 | H77: 0 | I77: 0 | J77: 0 | K77: 0 | L77: 0 | M77: 0 | N77: 0 | O77: 0 | P77: 0 | Q77: 0 | R77: 0 | S77: 0 | T77: 0 | U77: 0 | V77: 0 | W77: 0 | X77: 0 | Y77: 0 | Z77: 0 | AA77: 0 | AB77: 0 | AC77: 0 | AD77: 0 | AE77: 0 | AF77: 0 | AG77: 0 | AH77: 0 | AI77: 0 | AJ77: 0 | AK77: 0
D78: Dima's KITAS | F78: 0 | G78: 0 | H78: 0 | I78: 0 | J78: 0 | K78: 0 | L78: 0 | M78: 0 | N78: 0 | O78: 0 | P78: 0 | Q78: 0 | R78: 0 | S78: 0 | T78: 0 | U78: 0 | V78: 0 | W78: 0 | X78: 0 | Y78: 0 | Z78: 0 | AA78: 0 | AB78: 0 | AC78: 0 | AD78: 0 | AE78: 0 | AF78: 0 | AG78: 0 | AH78: 0 | AI78: -31000 | AJ78: 0 | AK78: 0
D79: Karim's KITAS | F79: 0 | G79: 0 | H79: 0 | I79: 0 | J79: 0 | K79: 0 | L79: 0 | M79: 0 | N79: 0 | O79: 0 | P79: 0 | Q79: 0 | R79: 0 | S79: 0 | T79: 0 | U79: 0 | V79: 0 | W79: 0 | X79: 0 | Y79: 0 | Z79: 0 | AA79: 0 | AB79: 0 | AC79: 0 | AD79: 0 | AE79: 0 | AF79: 0 | AG79: 0 | AH79: 0 | AI79: -31000 | AJ79: 0 | AK79: 0
D80: Divindends/Loan to Alex (salary) | F80: 0 | G80: 0 | H80: 0 | I80: 0 | J80: 0 | K80: 0 | L80: 0 | M80: 0 | N80: 0 | O80: 0 | P80: 0 | Q80: 0 | R80: 0 | S80: 0 | T80: 0 | U80: 0 | V80: 0 | W80: 0 | X80: 0 | Y80: 0 | Z80: 0 | AA80: {=-3*16272} -> -48816 | AB80: {=-5*16272} -> -81360 | AC80: {=-5*16272} -> -81360 | AD80: {=-5*16272} -> -81360 | AE80: {=-5*16272} -> -81360 | AF80: {=-5*16272} -> -81360 | AG80: {=-5*16272} -> -81360 | AH80: {=-5*16272} -> -81360 | AI80: {=-5*16272} -> -81360 | ... AK80: {=-5*16272} -> -81360
D81: Annual dividends and payroll bonus reserve | F81: 0 | G81: 0 | H81: 0 | I81: 0 | J81: 0 | K81: 0 | L81: 0 | M81: 0 | N81: 0 | O81: 0 | P81: 0 | Q81: 0 | R81: 0 | S81: 0 | T81: 0 | U81: 0 | V81: 0 | W81: 0 | X81: 0 | Y81: 0 | Z81: 0 | AA81: 0 | AB81: 0 | AC81: 0 | AD81: 0 | AE81: 0 | AF81: 0 | AG81: 0 | AH81: 0 | AI81: 0 | AJ81: 0 | AK81: 0
E82: {=50896.35*16272} -> 8.2818541e+08
B83: Net cash inflows/ourflows:
D84: Openning cash and cash equivalents | I84: {=(D117-D116-D112-D113)/1000} -> 3600738.6 | J84: {=I86} -> 3600738.6 | K84: {=J86} -> 3600738.6 | L84: {=K86} -> 3600738.6 | M84: {=L86} -> 3600738.6 | N84: {=M86} -> 3600738.6 | O84: {=N86} -> 3600738.6 | P84: {=O86} -> 3600738.6 | Q84: {=P86} -> 3600738.6 | ... AK84: {=AJ86} -> 12682950
D85: Net cash inflows/outflows | I85: {=SUM(I11:I16,I21:I73,I76:I81)} -> 0 | J85: {=SUM(J11:J16,J21:J73,J76:J81)} -> 0 | K85: {=SUM(K11:K16,K21:K73,K76:K81)} -> 0 | L85: 0 | M85: 0 | N85: 0 | O85: 0 | P85: 0 | Q85: 0 | R85: 0 | S85: 0 | T85: 0 | U85: 0 | V85: 0 | W85: {=W8*0/31+SUM(W11:W16,W21:W73,W76:W81)} -> 0 | X85: 0 | Y85: 0 | Z85: 0 | AA85: {=SUM(AA10:AA16,AA21:AA73,AA76:AA81)+AA8*10/28} -> -229940.6 | AB85: {=SUM(AB8:AB16,AB21:AB73,AB76:AB81)} -> -282669.36 | AC85: {=SUM(AC8:AC16,AC21:AC73,AC76:AC81)} -> 1867572.8 | AD85: {=SUM(AD8:AD16,AD21:AD73,AD76:AD81)} -> 2732541.9 | AE85: {=SUM(AE8:AE16,AE21:AE73,AE76:AE81)} -> 1067863.7 | AF85: {=SUM(AF8:AF16,AF21:AF73,AF76:AF81)} -> 1044426.1 | AG85: {=SUM(AG8:AG16,AG21:AG73,AG76:AG81)} -> 584449.27 | AH85: {=SUM(AH8:AH16,AH21:AH73,AH76:AH81)} -> 1695141 | AI85: {=SUM(AI8:AI16,AI21:AI73,AI76:AI81)} -> 469295.08 | ... AK85: {=SUM(AK8:AK16,AK21:AK73,AK76:AK81)} -> -36889.095
D86: Ending cash and cash equivalents | I86: {=SUM(I84:I85)} -> 3600738.6 | J86: {=SUM(J84:J85)} -> 3600738.6 | K86: {=SUM(K84:K85)} -> 3600738.6 | L86: {=SUM(L84:L85)} -> 3600738.6 | M86: {=SUM(M84:M85)} -> 3600738.6 | N86: {=SUM(N84:N85)} -> 3600738.6 | O86: {=SUM(O84:O85)} -> 3600738.6 | P86: {=SUM(P84:P85)} -> 3600738.6 | ... AK86: {=SUM(AK84:AK85)} -> 12646061
E87: {=50896.35*16272} -> 8.2818541e+08
B88: Free cash flows:
D89: Reserve held for working capital | I89: -2000000 | J89: -2000000 | K89: -2000000 | L89: -2000000 | M89: -2000000 | N89: -2000000 | O89: -2000000 | P89: -2000000 | Q89: -2000000 | R89: -2000000 | S89: -2000000 | T89: -2000000 | U89: -2000000 | V89: -2000000 | W89: -2000000 | X89: -2000000 | Y89: -2000000 | Z89: -2000000 | AA89: -2000000 | AB89: -2000000 | AC89: -3000000 | AD89: -3000000 | AE89: -3000000 | AF89: -3000000 | AG89: -3000000 | AH89: -3000000 | AI89: -3000000 | AJ89: -3000000 | AK89: -3000000
D90: CASH PROFICIT/DEFICIT (FCF) | I90: {=SUM(I86:I89)} -> 1600738.6 | J90: {=SUM(J86:J89)} -> 1600738.6 | K90: {=SUM(K86:K89)} -> 1600738.6 | L90: {=SUM(L86:L89)} -> 1600738.6 | M90: {=SUM(M86:M89)} -> 1600738.6 | N90: {=SUM(N86:N89)} -> 1600738.6 | O90: {=SUM(O86:O89)} -> 1600738.6 | P90: {=SUM(P86:P89)} -> 1600738.6 | ... AK90: {=SUM(AK86:AK89)} -> 9646060.8
E91: {=50896.35*16272} -> 8.2818541e+08
B93: Current Date Cash | D93: 46072
B95: Cash at Banks - DTB | D95: 2.3227576e+08
B96: Cash at Banks - EBC | D96: {=10355208} -> 10355208
B97: Cash at Banks - E01 | D97: 8311797
B98: Cash at Banks - E02 | D98: 9900263
B99: Cash at Banks - E03 | D99: 9899604
B100: Cash at Banks - FYB | D100: {=23048571} -> 23048571
B101: Cash at Reserve | D101: 2582014286
B102: Cash at PayPal | D102: {=7281.79*16895} -> 1.2302584e+08
B103: Cash at Viator | D103: 277347750
B104: Cash at Klook | D104: 0
B105: Cash at GYG | D105: 303551500
B106: Cash at Headout.com | D106: 2780000
...

Sheet Private Boats 2026 Target
A2: 1 | B2: Boat: | C2: SWEETHEART 4 | AE2: Average direct cost | AF2: {=AVERAGE(Q5:Q10)} -> 6984733.3 | AG2: Extra pax cost | AH2: {=AVERAGE(Q11:Q18)-AF2} -> 2103062.5 | AI2: Average profit margin | AJ2: {=AVERAGE(Y5:Y12)} -> 2879936.5 | AK2: Average total cost | AL2: {=AVERAGE(W5:W10)} -> 11219309 | AM2: 1-Pax cost | AN2: {=W5} -> 10741809
C3: DIRECT COSTS | S3: INDIRECT COST | W3: TARGER PRICING | AC3: Წ
B4: Guests u | C4: Boat Rent u | D4: Guides | E4: Guides Salary & Tax | F4: Towels | G4: Ice & Water | H4: NP + Bali Clearance + Parking | I4: Seran Retribution | J4: Seran Parking and Mooring | K4: Offering | L4: Fruits | M4: Lunch | N4: Fuel Pertamax | O4: Crew Salary & Tax u | P4: Boat Tax | Q4: TOTAL DIRECT | S4: Indirect and Admin Cost per tour | T4: 3D (Depretiation, Docking, Doc) fees per tour u | U4: TOTAL INDIRECT | W4: TOTAL COST | X4: Tax Markup 0.5% | Y4: Targer Net Profit Margin 25% | Z4: TARGET PRICE PER TOUR | AA4: Extra Pax Charge | AC4: RECOMMENED BASE PRICE PER TOUR
B5: 1 | C5: {=IF(B5>0,IF(VLOOKUP(C2,'Boats Data Sheet 2026'!$C$3:$J$57,8,0)="N/A",0,VLOOKUP(C2,'Boats Data Sheet 2026'!$C$3:$J$57,8,0)),"N/A")} -> 0 | D5: {=IF(B5>7,2,IF(B5=0,"N/A",1))} -> 1 | E5: {=_xlfn.IFERROR(SUM('Direct Costs 2026'!$C$4:$C$5)*D5,"N/A")} -> 875500 | F5: {=_xlfn.IFERROR('Direct Costs 2026'!$C$43*B5,"N/A")} -> 6000 | G5: {=IF(B5>0,'Direct Costs 2026'!$C$25,"N/A")} -> 90000 | H5: {=IF(B5>0,('Direct Costs 2026'!$C$15+'Direct Costs 2026'!$C$17+'Direct Costs 2026'!$C$14),"N/A")} -> 580000 | I5: {=IF(B5>0,'Direct Costs 2026'!$C$19+'Direct Costs 2026'!$C$18*B5,"N/A")} -> 110000 | J5: {=IF(B5>0,SUM('Direct Costs 2026'!$C$20:$C$21),"N/A")} -> 98333.333 | K5: {=IF(B5>0,'Direct Costs 2026'!$C$26,"N/A")} -> 20000 | L5: {=IF(B5>0,'Direct Costs 2026'!$C$23,"N/A")} -> 140000 | M5: {=IF(B5>0,'Direct Costs 2026'!$C$45*B5,"N/A")} -> 150000 | N5: {=IF(B5>0,_xlfn.IFERROR(VLOOKUP(C2,'Boats Data Sheet 2026'!$C$3:$I$57,7,0)*'Direct Costs 2026'!$C$36,"N/A"),"N/A")} -> 3325000 | O5: {=IF(B5>0,IF(OR(VLOOKUP(C2,'Boats Data Sheet 2026'!$C$3:$F$57,4,0)="Own",VLOOKUP(C2,'Boats Data Sheet 2026'!$C$3:$F$57,4,0)="Management"),('Direct Costs 2026'!$C$37+'Direct Costs 2026'!$C$39),"N/A"),"N/A")} -> 1112400 | P5: {=_xlfn.IFERROR('Direct Costs 2026'!$C$27*C5,"N/A")} -> 0 | Q5: {=_xlfn.IFERROR(C5+SUM(E5:P5),"N/A")} -> 6507233.3 | S5: {=IF(B5>0,'Allocation OH and Target 2026'!$E$31,"N/A")} -> 3100447.2 | T5: {=IF(B5>0,VLOOKUP(C2,'Allocation OH and Target 2026'!$C$35:$S$87,17,0),"N/A")} -> 1134128.1 | U5: {=_xlfn.IFERROR((S5+T5),"N/A")} -> 4234575.3 | W5: {=_xlfn.IFERROR(U5+Q5,"N/A")} -> 10741809 | X5: {=_xlfn.IFERROR(W5*0.5%,"N/A")} -> 53709.043 | Y5: {=_xlfn.IFERROR(W5*25%,"N/A")} -> 2685452.2 | Z5: {=IF(B5>0,SUM(W5:Y5),"N/A")} -> 13480970 | AA5: 0 | AC5: {=IF(B5=6,Z5,"N/A")} -> N/A
B6: {=IF(B5=0,0,IF(B5<VLOOKUP(C2,'Boats Data Sheet 2026'!$C$3:$H$57,6,0),B5+1,0))} -> 2 | C6: {=IF(B6>0,IF(VLOOKUP(C2,'Boats Data Sheet 2026'!$C$3:$J$57,8,0)="N/A",0,VLOOKUP(C2,'Boats Data Sheet 2026'!$C$3:$J$57,8,0)),"N/A")} -> 0 | D6: {=IF(B6>7,2,IF(B6=0,"N/A",1))} -> 1 | E6: {=_xlfn.IFERROR(SUM('Direct Costs 2026'!$C$4:$C$5)*D6,"N/A")} -> 875500 | F6: {=_xlfn.IFERROR('Direct Costs 2026'!$C$43*B6,"N/A")} -> 12000 | G6: {=IF(B6>0,'Direct Costs 2026'!$C$25,"N/A")} -> 90000 | H6: {=IF(B6>0,('Direct Costs 2026'!$C$15+'Direct Costs 2026'!$C$17+'Direct Costs 2026'!$C$14),"N/A")} -> 580000 | I6: {=IF(B6>0,'Direct Costs 2026'!$C$19+'Direct Costs 2026'!$C$18*B6,"N/A")} -> 145000 | J6: {=IF(B6>0,SUM('Direct Costs 2026'!$C$20:$C$21),"N/A")} -> 98333.333 | K6: {=IF(B6>0,'Direct Costs 2026'!$C$26,"N/A")} -> 20000 | L6: {=IF(B6>0,'Direct Costs 2026'!$C$23,"N/A")} -> 140000 | M6: {=IF(B6>0,'Direct Costs 2026'!$C$45*B6,"N/A")} -> 300000 | N6: {=IF(B6>0,_xlfn.IFERROR(VLOOKUP(C2,'Boats Data Sheet 2026'!$C$3:$I$57,7,0)*'Direct Costs 2026'!$C$36,"N/A"),"N/A")} -> 3325000 | O6: {=IF(B6>0,IF(OR(VLOOKUP(C2,'Boats Data Sheet 2026'!$C$3:$F$57,4,0)="Own",VLOOKUP(C2,'Boats Data Sheet 2026'!$C$3:$F$57,4,0)="Management"),('Direct Costs 2026'!$C$37+'Direct Costs 2026'!$C$39),"N/A"),"N/A")} -> 1112400 | P6: {=_xlfn.IFERROR('Direct Costs 2026'!$C$27*C6,"N/A")} -> 0 | Q6: {=_xlfn.IFERROR(C6+SUM(E6:P6),"N/A")} -> 6698233.3 | S6: {=IF(B6>0,'Allocation OH and Target 2026'!$E$31,"N/A")} -> 3100447.2 | T6: {=IF(B6>0,VLOOKUP(C2,'Allocation OH and Target 2026'!$C$35:$S$87,17,0),"N/A")} -> 1134128.1 | U6: {=_xlfn.IFERROR((S6+T6),"N/A")} -> 4234575.3 | W6: {=_xlfn.IFERROR(U6+Q6,"N/A")} -> 10932809 | X6: {=_xlfn.IFERROR(W6*0.5%,"N/A")} -> 54664.043 | Y6: {=_xlfn.IFERROR(W6*25%,"N/A")} -> 2733202.2 | Z6: {=IF(B6>0,SUM(W6:Y6),"N/A")} -> 13720675 | AA6: {=_xlfn.IFERROR((Z6-Z5),"N/A")} -> 239705 | AC6: {=IF(B6=6,AVERAGE(Z6),"N/A")} -> N/A
B7: {=IF(B6=0,0,IF(B6<VLOOKUP(C2,'Boats Data Sheet 2026'!$C$3:$H$57,6,0),B6+1,0))} -> 3 | C7: {=IF(B7>0,IF(VLOOKUP(C2,'Boats Data Sheet 2026'!$C$3:$J$57,8,0)="N/A",0,VLOOKUP(C2,'Boats Data Sheet 2026'!$C$3:$J$57,8,0)),"N/A")} -> 0 | D7: {=IF(B7>7,2,IF(B7=0,"N/A",1))} -> 1 | E7: {=_xlfn.IFERROR(SUM('Direct Costs 2026'!$C$4:$C$5)*D7,"N/A")} -> 875500 | F7: {=_xlfn.IFERROR('Direct Costs 2026'!$C$43*B7,"N/A")} -> 18000 | G7: {=IF(B7>0,'Direct Costs 2026'!$C$25,"N/A")} -> 90000 | H7: {=IF(B7>0,('Direct Costs 2026'!$C$15+'Direct Costs 2026'!$C$17+'Direct Costs 2026'!$C$14),"N/A")} -> 580000 | I7: {=IF(B7>0,'Direct Costs 2026'!$C$19+'Direct Costs 2026'!$C$18*B7,"N/A")} -> 180000 | J7: {=IF(B7>0,SUM('Direct Costs 2026'!$C$20:$C$21),"N/A")} -> 98333.333 | K7: {=IF(B7>0,'Direct Costs 2026'!$C$26,"N/A")} -> 20000 | L7: {=IF(B7>0,'Direct Costs 2026'!$C$23,"N/A")} -> 140000 | M7: {=IF(B7>0,'Direct Costs 2026'!$C$45*B7,"N/A")} -> 450000 | N7: {=IF(B7>0,_xlfn.IFERROR(VLOOKUP(C2,'Boats Data Sheet 2026'!$C$3:$I$57,7,0)*'Direct Costs 2026'!$C$36,"N/A"),"N/A")} -> 3325000 | O7: {=IF(B7>0,IF(OR(VLOOKUP(C2,'Boats Data Sheet 2026'!$C$3:$F$57,4,0)="Own",VLOOKUP(C2,'Boats Data Sheet 2026'!$C$3:$F$57,4,0)="Management"),('Direct Costs 2026'!$C$37+'Direct Costs 2026'!$C$39),"N/A"),"N/A")} -> 1112400 | P7: {=_xlfn.IFERROR('Direct Costs 2026'!$C$27*C7,"N/A")} -> 0 | Q7: {=_xlfn.IFERROR(C7+SUM(E7:P7),"N/A")} -> 6889233.3 | S7: {=IF(B7>0,'Allocation OH and Target 2026'!$E$31,"N/A")} -> 3100447.2 | T7: {=IF(B7>0,VLOOKUP(C2,'Allocation OH and Target 2026'!$C$35:$S$87,17,0),"N/A")} -> 1134128.1 | U7: {=_xlfn.IFERROR((S7+T7),"N/A")} -> 4234575.3 | W7: {=_xlfn.IFERROR(U7+Q7,"N/A")} -> 11123809 | X7: {=_xlfn.IFERROR(W7*0.5%,"N/A")} -> 55619.043 | Y7: {=_xlfn.IFERROR(W7*25%,"N/A")} -> 2780952.2 | Z7: {=IF(B7>0,SUM(W7:Y7),"N/A")} -> 13960380 | AA7: {=_xlfn.IFERROR((Z7-Z6),"N/A")} -> 239705 | AC7: {=IF(B7=6,AVERAGE(Z7),"N/A")} -> N/A
B8: {=IF(B7=0,0,IF(B7<VLOOKUP(C2,'Boats Data Sheet 2026'!$C$3:$H$57,6,0),B7+1,0))} -> 4 | C8: {=IF(B8>0,IF(VLOOKUP(C2,'Boats Data Sheet 2026'!$C$3:$J$57,8,0)="N/A",0,VLOOKUP(C2,'Boats Data Sheet 2026'!$C$3:$J$57,8,0)),"N/A")} -> 0 | D8: {=IF(B8>7,2,IF(B8=0,"N/A",1))} -> 1 | E8: {=_xlfn.IFERROR(SUM('Direct Costs 2026'!$C$4:$C$5)*D8,"N/A")} -> 875500 | F8: {=_xlfn.IFERROR('Direct Costs 2026'!$C$43*B8,"N/A")} -> 24000 | G8: {=IF(B8>0,'Direct Costs 2026'!$C$25,"N/A")} -> 90000 | H8: {=IF(B8>0,('Direct Costs 2026'!$C$15+'Direct Costs 2026'!$C$17+'Direct Costs 2026'!$C$14),"N/A")} -> 580000 | I8: {=IF(B8>0,'Direct Costs 2026'!$C$19+'Direct Costs 2026'!$C$18*B8,"N/A")} -> 215000 | J8: {=IF(B8>0,SUM('Direct Costs 2026'!$C$20:$C$21),"N/A")} -> 98333.333 | K8: {=IF(B8>0,'Direct Costs 2026'!$C$26,"N/A")} -> 20000 | L8: {=IF(B8>0,'Direct Costs 2026'!$C$23,"N/A")} -> 140000 | M8: {=IF(B8>0,'Direct Costs 2026'!$C$45*B8,"N/A")} -> 600000 | N8: {=IF(B8>0,_xlfn.IFERROR(VLOOKUP(C2,'Boats Data Sheet 2026'!$C$3:$I$57,7,0)*'Direct Costs 2026'!$C$36,"N/A"),"N/A")} -> 3325000 | O8: {=IF(B8>0,IF(OR(VLOOKUP(C2,'Boats Data Sheet 2026'!$C$3:$F$57,4,0)="Own",VLOOKUP(C2,'Boats Data Sheet 2026'!$C$3:$F$57,4,0)="Management"),('Direct Costs 2026'!$C$37+'Direct Costs 2026'!$C$39),"N/A"),"N/A")} -> 1112400 | P8: {=_xlfn.IFERROR('Direct Costs 2026'!$C$27*C8,"N/A")} -> 0 | Q8: {=_xlfn.IFERROR(C8+SUM(E8:P8),"N/A")} -> 7080233.3 | S8: {=IF(B8>0,'Allocation OH and Target 2026'!$E$31,"N/A")} -> 3100447.2 | T8: {=IF(B8>0,VLOOKUP(C2,'Allocation OH and Target 2026'!$C$35:$S$87,17,0),"N/A")} -> 1134128.1 | U8: {=_xlfn.IFERROR((S8+T8),"N/A")} -> 4234575.3 | W8: {=_xlfn.IFERROR(U8+Q8,"N/A")} -> 11314809 | X8: {=_xlfn.IFERROR(W8*0.5%,"N/A")} -> 56574.043 | Y8: {=_xlfn.IFERROR(W8*25%,"N/A")} -> 2828702.2 | Z8: {=IF(B8>0,SUM(W8:Y8),"N/A")} -> 14200085 | AA8: {=_xlfn.IFERROR((Z8-Z7),"N/A")} -> 239705 | AC8: {=IF(B8=6,AVERAGE(Z8),"N/A")} -> N/A
B9: {=IF(B8=0,0,IF(B8<VLOOKUP(C2,'Boats Data Sheet 2026'!$C$3:$H$57,6,0),B8+1,0))} -> 5 | C9: {=IF(B9>0,IF(VLOOKUP(C2,'Boats Data Sheet 2026'!$C$3:$J$57,8,0)="N/A",0,VLOOKUP(C2,'Boats Data Sheet 2026'!$C$3:$J$57,8,0)),"N/A")} -> 0 | D9: {=IF(B9>7,2,IF(B9=0,"N/A",1))} -> 1 | E9: {=_xlfn.IFERROR(SUM('Direct Costs 2026'!$C$4:$C$5)*D9,"N/A")} -> 875500 | F9: {=_xlfn.IFERROR('Direct Costs 2026'!$C$43*B9,"N/A")} -> 30000 | G9: {=IF(B9>0,'Direct Costs 2026'!$C$25,"N/A")} -> 90000 | H9: {=IF(B9>0,('Direct Costs 2026'!$C$15+'Direct Costs 2026'!$C$17+'Direct Costs 2026'!$C$14),"N/A")} -> 580000 | I9: {=IF(B9>0,'Direct Costs 2026'!$C$19+'Direct Costs 2026'!$C$18*B9,"N/A")} -> 250000 | J9: {=IF(B9>0,SUM('Direct Costs 2026'!$C$20:$C$21),"N/A")} -> 98333.333 | K9: {=IF(B9>0,'Direct Costs 2026'!$C$26,"N/A")} -> 20000 | L9: {=IF(B9>0,'Direct Costs 2026'!$C$23,"N/A")} -> 140000 | M9: {=IF(B9>0,'Direct Costs 2026'!$C$45*B9,"N/A")} -> 750000 | N9: {=IF(B9>0,_xlfn.IFERROR(VLOOKUP(C2,'Boats Data Sheet 2026'!$C$3:$I$57,7,0)*'Direct Costs 2026'!$C$36,"N/A"),"N/A")} -> 3325000 | O9: {=IF(B9>0,IF(OR(VLOOKUP(C2,'Boats Data Sheet 2026'!$C$3:$F$57,4,0)="Own",VLOOKUP(C2,'Boats Data Sheet 2026'!$C$3:$F$57,4,0)="Management"),('Direct Costs 2026'!$C$37+'Direct Costs 2026'!$C$39),"N/A"),"N/A")} -> 1112400 | P9: {=_xlfn.IFERROR('Direct Costs 2026'!$C$27*C9,"N/A")} -> 0 | Q9: {=_xlfn.IFERROR(C9+SUM(E9:P9),"N/A")} -> 7271233.3 | S9: {=IF(B9>0,'Allocation OH and Target 2026'!$E$31,"N/A")} -> 3100447.2 | T9: {=IF(B9>0,VLOOKUP(C2,'Allocation OH and Target 2026'!$C$35:$S$87,17,0),"N/A")} -> 1134128.1 | U9: {=_xlfn.IFERROR((S9+T9),"N/A")} -> 4234575.3 | W9: {=_xlfn.IFERROR(U9+Q9,"N/A")} -> 11505809 | X9: {=_xlfn.IFERROR(W9*0.5%,"N/A")} -> 57529.043 | Y9: {=_xlfn.IFERROR(W9*25%,"N/A")} -> 2876452.2 | Z9: {=IF(B9>0,SUM(W9:Y9),"N/A")} -> 14439790 | AA9: {=_xlfn.IFERROR((Z9-Z8),"N/A")} -> 239705 | AC9: {=IF(B9=6,AVERAGE(Z9),"N/A")} -> N/A
B10: {=IF(B9=0,0,IF(B9<VLOOKUP(C2,'Boats Data Sheet 2026'!$C$3:$H$57,6,0),B9+1,0))} -> 6 | C10: {=IF(B10>0,IF(VLOOKUP(C2,'Boats Data Sheet 2026'!$C$3:$J$57,8,0)="N/A",0,VLOOKUP(C2,'Boats Data Sheet 2026'!$C$3:$J$57,8,0)),"N/A")} -> 0 | D10: {=IF(B10>7,2,IF(B10=0,"N/A",1))} -> 1 | E10: {=_xlfn.IFERROR(SUM('Direct Costs 2026'!$C$4:$C$5)*D10,"N/A")} -> 875500 | F10: {=_xlfn.IFERROR('Direct Costs 2026'!$C$43*B10,"N/A")} -> 36000 | G10: {=IF(B10>0,'Direct Costs 2026'!$C$25,"N/A")} -> 90000 | H10: {=IF(B10>0,('Direct Costs 2026'!$C$15+'Direct Costs 2026'!$C$17+'Direct Costs 2026'!$C$14),"N/A")} -> 580000 | I10: {=IF(B10>0,'Direct Costs 2026'!$C$19+'Direct Costs 2026'!$C$18*B10,"N/A")} -> 285000 | J10: {=IF(B10>0,SUM('Direct Costs 2026'!$C$20:$C$21),"N/A")} -> 98333.333 | K10: {=IF(B10>0,'Direct Costs 2026'!$C$26,"N/A")} -> 20000 | L10: {=IF(B10>0,'Direct Costs 2026'!$C$23,"N/A")} -> 140000 | M10: {=IF(B10>0,'Direct Costs 2026'!$C$45*B10,"N/A")} -> 900000 | N10: {=IF(B10>0,_xlfn.IFERROR(VLOOKUP(C2,'Boats Data Sheet 2026'!$C$3:$I$57,7,0)*'Direct Costs 2026'!$C$36,"N/A"),"N/A")} -> 3325000 | O10: {=IF(B10>0,IF(OR(VLOOKUP(C2,'Boats Data Sheet 2026'!$C$3:$F$57,4,0)="Own",VLOOKUP(C2,'Boats Data Sheet 2026'!$C$3:$F$57,4,0)="Management"),('Direct Costs 2026'!$C$37+'Direct Costs 2026'!$C$39),"N/A"),"N/A")} -> 1112400 | P10: {=_xlfn.IFERROR('Direct Costs 2026'!$C$27*C10,"N/A")} -> 0 | Q10: {=_xlfn.IFERROR(C10+SUM(E10:P10),"N/A")} -> 7462233.3 | S10: {=IF(B10>0,'Allocation OH and Target 2026'!$E$31,"N/A")} -> 3100447.2 | T10: {=IF(B10>0,VLOOKUP(C2,'Allocation OH and Target 2026'!$C$35:$S$87,17,0),"N/A")} -> 1134128.1 | U10: {=_xlfn.IFERROR((S10+T10),"N/A")} -> 4234575.3 | W10: {=_xlfn.IFERROR(U10+Q10,"N/A")} -> 11696809 | X10: {=_xlfn.IFERROR(W10*0.5%,"N/A")} -> 58484.043 | Y10: {=_xlfn.IFERROR(W10*25%,"N/A")} -> 2924202.2 | Z10: {=IF(B10>0,SUM(W10:Y10),"N/A")} -> 14679495 | AA10: {=_xlfn.IFERROR((Z10-Z9),"N/A")} -> 239705 | AC10: {=IF(B10=6,AVERAGE(Z5:Z10),"N/A")} -> 14080232
B11: {=IF(B10=0,0,IF(B10<VLOOKUP(C2,'Boats Data Sheet 2026'!$C$3:$H$57,6,0),B10+1,0))} -> 7 | C11: {=IF(B11>0,IF(VLOOKUP(C2,'Boats Data Sheet 2026'!$C$3:$J$57,8,0)="N/A",0,VLOOKUP(C2,'Boats Data Sheet 2026'!$C$3:$J$57,8,0)),"N/A")} -> 0 | D11: {=IF(B11>7,2,IF(B11=0,"N/A",1))} -> 1 | E11: {=_xlfn.IFERROR(SUM('Direct Costs 2026'!$C$4:$C$5)*D11,"N/A")} -> 875500 | F11: {=_xlfn.IFERROR('Direct Costs 2026'!$C$43*B11,"N/A")} -> 42000 | G11: {=IF(B11>0,'Direct Costs 2026'!$C$25,"N/A")} -> 90000 | H11: {=IF(B11>0,('Direct Costs 2026'!$C$15+'Direct Costs 2026'!$C$17+'Direct Costs 2026'!$C$14),"N/A")} -> 580000 | I11: {=IF(B11>0,'Direct Costs 2026'!$C$19+'Direct Costs 2026'!$C$18*B11,"N/A")} -> 320000 | J11: {=IF(B11>0,SUM('Direct Costs 2026'!$C$20:$C$21),"N/A")} -> 98333.333 | K11: {=IF(B11>0,'Direct Costs 2026'!$C$26,"N/A")} -> 20000 | L11: {=IF(B11>0,'Direct Costs 2026'!$C$23,"N/A")} -> 140000 | M11: {=IF(B11>0,'Direct Costs 2026'!$C$45*B11,"N/A")} -> 1050000 | N11: {=IF(B11>0,_xlfn.IFERROR(VLOOKUP(C2,'Boats Data Sheet 2026'!$C$3:$I$57,7,0)*'Direct Costs 2026'!$C$36,"N/A"),"N/A")} -> 3325000 | O11: {=IF(B11>0,IF(OR(VLOOKUP(C2,'Boats Data Sheet 2026'!$C$3:$F$57,4,0)="Own",VLOOKUP(C2,'Boats Data Sheet 2026'!$C$3:$F$57,4,0)="Management"),('Direct Costs 2026'!$C$37+'Direct Costs 2026'!$C$39),"N/A"),"N/A")} -> 1112400 | P11: {=_xlfn.IFERROR('Direct Costs 2026'!$C$27*C11,"N/A")} -> 0 | Q11: {=_xlfn.IFERROR(C11+SUM(E11:P11),"N/A")} -> 7653233.3 | S11: {=IF(B11>0,'Allocation OH and Target 2026'!$E$31,"N/A")} -> 3100447.2 | T11: {=IF(B11>0,VLOOKUP(C2,'Allocation OH and Target 2026'!$C$35:$S$87,17,0),"N/A")} -> 1134128.1 | U11: {=_xlfn.IFERROR((S11+T11),"N/A")} -> 4234575.3 | W11: {=_xlfn.IFERROR(U11+Q11,"N/A")} -> 11887809 | X11: {=_xlfn.IFERROR(W11*0.5%,"N/A")} -> 59439.043 | Y11: {=_xlfn.IFERROR(W11*25%,"N/A")} -> 2971952.2 | Z11: {=IF(B11>0,SUM(W11:Y11),"N/A")} -> 14919200 | AA11: {=_xlfn.IFERROR((Z11-Z10),"N/A")} -> 239705 | AC11: {=IF(B11=6,AVERAGE(Z11),"N/A")} -> N/A
B12: {=IF(B11=0,0,IF(B11<VLOOKUP(C2,'Boats Data Sheet 2026'!$C$3:$H$57,6,0),B11+1,0))} -> 8 | C12: {=IF(B12>0,IF(VLOOKUP(C2,'Boats Data Sheet 2026'!$C$3:$J$57,8,0)="N/A",0,VLOOKUP(C2,'Boats Data Sheet 2026'!$C$3:$J$57,8,0)),"N/A")} -> 0 | D12: {=IF(B12>7,2,IF(B12=0,"N/A",1))} -> 2 | E12: {=_xlfn.IFERROR(SUM('Direct Costs 2026'!$C$4:$C$5)*D12,"N/A")} -> 1751000 | F12: {=_xlfn.IFERROR('Direct Costs 2026'!$C$43*B12,"N/A")} -> 48000 | G12: {=IF(B12>0,'Direct Costs 2026'!$C$25,"N/A")} -> 90000 | H12: {=IF(B12>0,('Direct Costs 2026'!$C$15+'Direct Costs 2026'!$C$17+'Direct Costs 2026'!$C$14),"N/A")} -> 580000 | I12: {=IF(B12>0,'Direct Costs 2026'!$C$19+'Direct Costs 2026'!$C$18*B12,"N/A")} -> 355000 | J12: {=IF(B12>0,SUM('Direct Costs 2026'!$C$20:$C$21),"N/A")} -> 98333.333 | K12: {=IF(B12>0,'Direct Costs 2026'!$C$26,"N/A")} -> 20000 | L12: {=IF(B12>0,'Direct Costs 2026'!$C$23,"N/A")} -> 140000 | M12: {=IF(B12>0,'Direct Costs 2026'!$C$45*B12,"N/A")} -> 1200000 | N12: {=IF(B12>0,_xlfn.IFERROR(VLOOKUP(C2,'Boats Data Sheet 2026'!$C$3:$I$57,7,0)*'Direct Costs 2026'!$C$36,"N/A"),"N/A")} -> 3325000 | O12: {=IF(B12>0,IF(OR(VLOOKUP(C2,'Boats Data Sheet 2026'!$C$3:$F$57,4,0)="Own",VLOOKUP(C2,'Boats Data Sheet 2026'!$C$3:$F$57,4,0)="Management"),('Direct Costs 2026'!$C$37+'Direct Costs 2026'!$C$39),"N/A"),"N/A")} -> 1112400 | P12: {=_xlfn.IFERROR('Direct Costs 2026'!$C$27*C12,"N/A")} -> 0 | Q12: {=_xlfn.IFERROR(C12+SUM(E12:P12),"N/A")} -> 8719733.3 | S12: {=IF(B12>0,'Allocation OH and Target 2026'!$E$31,"N/A")} -> 3100447.2 | T12: {=IF(B12>0,VLOOKUP(C2,'Allocation OH and Target 2026'!$C$35:$S$87,17,0),"N/A")} -> 1134128.1 | U12: {=_xlfn.IFERROR((S12+T12),"N/A")} -> 4234575.3 | W12: {=_xlfn.IFERROR(U12+Q12,"N/A")} -> 12954309 | X12: {=_xlfn.IFERROR(W12*0.5%,"N/A")} -> 64771.543 | Y12: {=_xlfn.IFERROR(W12*25%,"N/A")} -> 3238577.2 | Z12: {=IF(B12>0,SUM(W12:Y12),"N/A")} -> 16257657 | AA12: {=_xlfn.IFERROR((Z12-Z11),"N/A")} -> 1338457.5 | AC12: {=IF(B12=6,AVERAGE(Z12),"N/A")} -> N/A
B13: {=IF(B12=0,0,IF(B12<VLOOKUP(C2,'Boats Data Sheet 2026'!$C$3:$H$57,6,0),B12+1,0))} -> 9 | C13: {=IF(B13>0,IF(VLOOKUP(C2,'Boats Data Sheet 2026'!$C$3:$J$57,8,0)="N/A",0,VLOOKUP(C2,'Boats Data Sheet 2026'!$C$3:$J$57,8,0)),"N/A")} -> 0 | D13: {=IF(B13>7,2,IF(B13=0,"N/A",1))} -> 2 | E13: {=_xlfn.IFERROR(SUM('Direct Costs 2026'!$C$4:$C$5)*D13,"N/A")} -> 1751000 | F13: {=_xlfn.IFERROR('Direct Costs 2026'!$C$43*B13,"N/A")} -> 54000 | G13: {=IF(B13>0,'Direct Costs 2026'!$C$25,"N/A")} -> 90000 | H13: {=IF(B13>0,('Direct Costs 2026'!$C$15+'Direct Costs 2026'!$C$17+'Direct Costs 2026'!$C$14),"N/A")} -> 580000 | I13: {=IF(B13>0,'Direct Costs 2026'!$C$19+'Direct Costs 2026'!$C$18*B13,"N/A")} -> 390000 | J13: {=IF(B13>0,SUM('Direct Costs 2026'!$C$20:$C$21),"N/A")} -> 98333.333 | K13: {=IF(B13>0,'Direct Costs 2026'!$C$26,"N/A")} -> 20000 | L13: {=IF(B13>0,'Direct Costs 2026'!$C$23,"N/A")} -> 140000 | M13: {=IF(B13>0,'Direct Costs 2026'!$C$45*B13,"N/A")} -> 1350000 | N13: {=IF(B13>0,_xlfn.IFERROR(VLOOKUP(C2,'Boats Data Sheet 2026'!$C$3:$I$57,7,0)*'Direct Costs 2026'!$C$36,"N/A"),"N/A")} -> 3325000 | O13: {=IF(B13>0,IF(OR(VLOOKUP(C2,'Boats Data Sheet 2026'!$C$3:$F$57,4,0)="Own",VLOOKUP(C2,'Boats Data Sheet 2026'!$C$3:$F$57,4,0)="Management"),('Direct Costs 2026'!$C$37+'Direct Costs 2026'!$C$39),"N/A"),"N/A")} -> 1112400 | P13: {=_xlfn.IFERROR('Direct Costs 2026'!$C$27*C13,"N/A")} -> 0 | Q13: {=_xlfn.IFERROR(C13+SUM(E13:P13),"N/A")} -> 8910733.3 | S13: {=IF(B13>0,'Allocation OH and Target 2026'!$E$31,"N/A")} -> 3100447.2 | T13: {=IF(B13>0,VLOOKUP(C2,'Allocation OH and Target 2026'!$C$35:$S$87,17,0),"N/A")} -> 1134128.1 | U13: {=_xlfn.IFERROR((S13+T13),"N/A")} -> 4234575.3 | W13: {=_xlfn.IFERROR(U13+Q13,"N/A")} -> 13145309 | X13: {=_xlfn.IFERROR(W13*0.5%,"N/A")} -> 65726.543 | Y13: {=_xlfn.IFERROR(W13*25%,"N/A")} -> 3286327.2 | Z13: {=IF(B13>0,SUM(W13:Y13),"N/A")} -> 16497362 | AA13: {=_xlfn.IFERROR((Z13-Z12),"N/A")} -> 239705 | AC13: {=IF(B13=6,AVERAGE(Z13),"N/A")} -> N/A
B14: {=IF(B13=0,0,IF(B13<VLOOKUP(C2,'Boats Data Sheet 2026'!$C$3:$H$57,6,0),B13+1,0))} -> 10 | C14: {=IF(B14>0,IF(VLOOKUP(C2,'Boats Data Sheet 2026'!$C$3:$J$57,8,0)="N/A",0,VLOOKUP(C2,'Boats Data Sheet 2026'!$C$3:$J$57,8,0)),"N/A")} -> 0 | D14: {=IF(B14>7,2,IF(B14=0,"N/A",1))} -> 2 | E14: {=_xlfn.IFERROR(SUM('Direct Costs 2026'!$C$4:$C$5)*D14,"N/A")} -> 1751000 | F14: {=_xlfn.IFERROR('Direct Costs 2026'!$C$43*B14,"N/A")} -> 60000 | G14: {=IF(B14>0,'Direct Costs 2026'!$C$25,"N/A")} -> 90000 | H14: {=IF(B14>0,('Direct Costs 2026'!$C$15+'Direct Costs 2026'!$C$17+'Direct Costs 2026'!$C$14),"N/A")} -> 580000 | I14: {=IF(B14>0,'Direct Costs 2026'!$C$19+'Direct Costs 2026'!$C$18*B14,"N/A")} -> 425000 | J14: {=IF(B14>0,SUM('Direct Costs 2026'!$C$20:$C$21),"N/A")} -> 98333.333 | K14: {=IF(B14>0,'Direct Costs 2026'!$C$26,"N/A")} -> 20000 | L14: {=IF(B14>0,'Direct Costs 2026'!$C$23,"N/A")} -> 140000 | M14: {=IF(B14>0,'Direct Costs 2026'!$C$45*B14,"N/A")} -> 1500000 | N14: {=IF(B14>0,_xlfn.IFERROR(VLOOKUP(C2,'Boats Data Sheet 2026'!$C$3:$I$57,7,0)*'Direct Costs 2026'!$C$36,"N/A"),"N/A")} -> 3325000 | O14: {=IF(B14>0,IF(OR(VLOOKUP(C2,'Boats Data Sheet 2026'!$C$3:$F$57,4,0)="Own",VLOOKUP(C2,'Boats Data Sheet 2026'!$C$3:$F$57,4,0)="Management"),('Direct Costs 2026'!$C$37+'Direct Costs 2026'!$C$39),"N/A"),"N/A")} -> 1112400 | P14: {=_xlfn.IFERROR('Direct Costs 2026'!$C$27*C14,"N/A")} -> 0 | Q14: {=_xlfn.IFERROR(C14+SUM(E14:P14),"N/A")} -> 9101733.3 | S14: {=IF(B14>0,'Allocation OH and Target 2026'!$E$31,"N/A")} -> 3100447.2 | T14: {=IF(B14>0,VLOOKUP(C2,'Allocation OH and Target 2026'!$C$35:$S$87,17,0),"N/A")} -> 1134128.1 | U14: {=_xlfn.IFERROR((S14+T14),"N/A")} -> 4234575.3 | W14: {=_xlfn.IFERROR(U14+Q14,"N/A")} -> 13336309 | X14: {=_xlfn.IFERROR(W14*0.5%,"N/A")} -> 66681.543 | Y14: {=_xlfn.IFERROR(W14*25%,"N/A")} -> 3334077.2 | Z14: {=IF(B14>0,SUM(W14:Y14),"N/A")} -> 16737067 | AA14: {=_xlfn.IFERROR((Z14-Z13),"N/A")} -> 239705 | AC14: {=IF(B14=6,AVERAGE(Z14),"N/A")} -> N/A
B15: {=IF(B14=0,0,IF(B14<VLOOKUP(C2,'Boats Data Sheet 2026'!$C$3:$H$57,6,0),B14+1,0))} -> 11 | C15: {=IF(B15>0,IF(VLOOKUP(C2,'Boats Data Sheet 2026'!$C$3:$J$57,8,0)="N/A",0,VLOOKUP(C2,'Boats Data Sheet 2026'!$C$3:$J$57,8,0)),"N/A")} -> 0 | D15: {=IF(B15>7,2,IF(B15=0,"N/A",1))} -> 2 | E15: {=_xlfn.IFERROR(SUM('Direct Costs 2026'!$C$4:$C$5)*D15,"N/A")} -> 1751000 | F15: {=_xlfn.IFERROR('Direct Costs 2026'!$C$43*B15,"N/A")} -> 66000 | G15: {=IF(B15>0,'Direct Costs 2026'!$C$25,"N/A")} -> 90000 | H15: {=IF(B15>0,('Direct Costs 2026'!$C$15+'Direct Costs 2026'!$C$17+'Direct Costs 2026'!$C$14),"N/A")} -> 580000 | I15: {=IF(B15>0,'Direct Costs 2026'!$C$19+'Direct Costs 2026'!$C$18*B15,"N/A")} -> 460000 | J15: {=IF(B15>0,SUM('Direct Costs 2026'!$C$20:$C$21),"N/A")} -> 98333.333 | K15: {=IF(B15>0,'Direct Costs 2026'!$C$26,"N/A")} -> 20000 | L15: {=IF(B15>0,'Direct Costs 2026'!$C$23,"N/A")} -> 140000 | M15: {=IF(B15>0,'Direct Costs 2026'!$C$45*B15,"N/A")} -> 1650000 | N15: {=IF(B15>0,_xlfn.IFERROR(VLOOKUP(C2,'Boats Data Sheet 2026'!$C$3:$I$57,7,0)*'Direct Costs 2026'!$C$36,"N/A"),"N/A")} -> 3325000 | O15: {=IF(B15>0,IF(OR(VLOOKUP(C2,'Boats Data Sheet 2026'!$C$3:$F$57,4,0)="Own",VLOOKUP(C2,'Boats Data Sheet 2026'!$C$3:$F$57,4,0)="Management"),('Direct Costs 2026'!$C$37+'Direct Costs 2026'!$C$39),"N/A"),"N/A")} -> 1112400 | P15: {=_xlfn.IFERROR('Direct Costs 2026'!$C$27*C15,"N/A")} -> 0 | Q15: {=_xlfn.IFERROR(C15+SUM(E15:P15),"N/A")} -> 9292733.3 | S15: {=IF(B15>0,'Allocation OH and Target 2026'!$E$31,"N/A")} -> 3100447.2 | T15: {=IF(B15>0,VLOOKUP(C2,'Allocation OH and Target 2026'!$C$35:$S$87,17,0),"N/A")} -> 1134128.1 | U15: {=_xlfn.IFERROR((S15+T15),"N/A")} -> 4234575.3 | W15: {=_xlfn.IFERROR(U15+Q15,"N/A")} -> 13527309 | X15: {=_xlfn.IFERROR(W15*0.5%,"N/A")} -> 67636.543 | Y15: {=_xlfn.IFERROR(W15*25%,"N/A")} -> 3381827.2 | Z15: {=IF(B15>0,SUM(W15:Y15),"N/A")} -> 16976772 | AA15: {=_xlfn.IFERROR((Z15-Z14),"N/A")} -> 239705 | AC15: {=IF(B15=6,AVERAGE(Z15),"N/A")} -> N/A
B16: {=IF(B15=0,0,IF(B15<VLOOKUP(C2,'Boats Data Sheet 2026'!$C$3:$H$57,6,0),B15+1,0))} -> 12 | C16: {=IF(B16>0,IF(VLOOKUP(C2,'Boats Data Sheet 2026'!$C$3:$J$57,8,0)="N/A",0,VLOOKUP(C2,'Boats Data Sheet 2026'!$C$3:$J$57,8,0)),"N/A")} -> 0 | D16: {=IF(B16>7,2,IF(B16=0,"N/A",1))} -> 2 | E16: {=_xlfn.IFERROR(SUM('Direct Costs 2026'!$C$4:$C$5)*D16,"N/A")} -> 1751000 | F16: {=_xlfn.IFERROR('Direct Costs 2026'!$C$43*B16,"N/A")} -> 72000 | G16: {=IF(B16>0,'Direct Costs 2026'!$C$25,"N/A")} -> 90000 | H16: {=IF(B16>0,('Direct Costs 2026'!$C$15+'Direct Costs 2026'!$C$17+'Direct Costs 2026'!$C$14),"N/A")} -> 580000 | I16: {=IF(B16>0,'Direct Costs 2026'!$C$19+'Direct Costs 2026'!$C$18*B16,"N/A")} -> 495000 | J16: {=IF(B16>0,SUM('Direct Costs 2026'!$C$20:$C$21),"N/A")} -> 98333.333 | K16: {=IF(B16>0,'Direct Costs 2026'!$C$26,"N/A")} -> 20000 | L16: {=IF(B16>0,'Direct Costs 2026'!$C$23,"N/A")} -> 140000 | M16: {=IF(B16>0,'Direct Costs 2026'!$C$45*B16,"N/A")} -> 1800000 | N16: {=IF(B16>0,_xlfn.IFERROR(VLOOKUP(C2,'Boats Data Sheet 2026'!$C$3:$I$57,7,0)*'Direct Costs 2026'!$C$36,"N/A"),"N/A")} -> 3325000 | O16: {=IF(B16>0,IF(OR(VLOOKUP(C2,'Boats Data Sheet 2026'!$C$3:$F$57,4,0)="Own",VLOOKUP(C2,'Boats Data Sheet 2026'!$C$3:$F$57,4,0)="Management"),('Direct Costs 2026'!$C$37+'Direct Costs 2026'!$C$39),"N/A"),"N/A")} -> 1112400 | P16: {=_xlfn.IFERROR('Direct Costs 2026'!$C$27*C16,"N/A")} -> 0 | Q16: {=_xlfn.IFERROR(C16+SUM(E16:P16),"N/A")} -> 9483733.3 | S16: {=IF(B16>0,'Allocation OH and Target 2026'!$E$31,"N/A")} -> 3100447.2 | T16: {=IF(B17>0,VLOOKUP(C2,'Allocation OH and Target 2026'!$C$35:$S$87,17,0),"N/A")} -> 1134128.1 | U16: {=_xlfn.IFERROR((S16+T16),"N/A")} -> 4234575.3 | W16: {=_xlfn.IFERROR(U16+Q16,"N/A")} -> 13718309 | X16: {=_xlfn.IFERROR(W16*0.5%,"N/A")} -> 68591.543 | Y16: {=_xlfn.IFERROR(W16*25%,"N/A")} -> 3429577.2 | Z16: {=IF(B16>0,SUM(W16:Y16),"N/A")} -> 17216477 | AA16: {=_xlfn.IFERROR((Z16-Z15),"N/A")} -> 239705 | AC16: {=IF(B16=6,AVERAGE(Z16),"N/A")} -> N/A
B17: {=IF(B16=0,0,IF(B16<VLOOKUP(C2,'Boats Data Sheet 2026'!$C$3:$H$57,6,0),B16+1,0))} -> 13 | C17: {=IF(B17>0,IF(VLOOKUP(C2,'Boats Data Sheet 2026'!$C$3:$J$57,8,0)="N/A",0,VLOOKUP(C2,'Boats Data Sheet 2026'!$C$3:$J$57,8,0)),"N/A")} -> 0 | D17: {=IF(B17>7,2,IF(B17=0,"N/A",1))} -> 2 | E17: {=_xlfn.IFERROR(SUM('Direct Costs 2026'!$C$4:$C$5)*D17,"N/A")} -> 1751000 | F17: {=_xlfn.IFERROR('Direct Costs 2026'!$C$43*B17,"N/A")} -> 78000 | G17: {=IF(B17>0,'Direct Costs 2026'!$C$25,"N/A")} -> 90000 | H17: {=IF(B17>0,('Direct Costs 2026'!$C$15+'Direct Costs 2026'!$C$17+'Direct Costs 2026'!$C$14),"N/A")} -> 580000 | I17: {=IF(B17>0,'Direct Costs 2026'!$C$19+'Direct Costs 2026'!$C$18*B17,"N/A")} -> 530000 | J17: {=IF(B17>0,SUM('Direct Costs 2026'!$C$20:$C$21),"N/A")} -> 98333.333 | K17: {=IF(B17>0,'Direct Costs 2026'!$C$26,"N/A")} -> 20000 | L17: {=IF(B17>0,'Direct Costs 2026'!$C$23,"N/A")} -> 140000 | M17: {=IF(B17>0,'Direct Costs 2026'!$C$45*B17,"N/A")} -> 1950000 | N17: {=IF(B17>0,_xlfn.IFERROR(VLOOKUP(C2,'Boats Data Sheet 2026'!$C$3:$I$57,7,0)*'Direct Costs 2026'!$C$36,"N/A"),"N/A")} -> 3325000 | O17: {=IF(B17>0,IF(OR(VLOOKUP(C2,'Boats Data Sheet 2026'!$C$3:$F$57,4,0)="Own",VLOOKUP(C2,'Boats Data Sheet 2026'!$C$3:$F$57,4,0)="Management"),('Direct Costs 2026'!$C$37+'Direct Costs 2026'!$C$39),"N/A"),"N/A")} -> 1112400 | P17: {=_xlfn.IFERROR('Direct Costs 2026'!$C$27*C17,"N/A")} -> 0 | Q17: {=_xlfn.IFERROR(C17+SUM(E17:P17),"N/A")} -> 9674733.3 | S17: {=IF(B17>0,'Allocation OH and Target 2026'!$E$31,"N/A")} -> 3100447.2 | T17: {=IF(B17>0,VLOOKUP(C2,'Allocation OH and Target 2026'!$C$35:$S$87,17,0),"N/A")} -> 1134128.1 | U17: {=_xlfn.IFERROR((S17+T17),"N/A")} -> 4234575.3 | W17: {=_xlfn.IFERROR(U17+Q17,"N/A")} -> 13909309 | X17: {=_xlfn.IFERROR(W17*0.5%,"N/A")} -> 69546.543 | Y17: {=_xlfn.IFERROR(W17*25%,"N/A")} -> 3477327.2 | Z17: {=IF(B17>0,SUM(W17:Y17),"N/A")} -> 17456182 | AA17: {=_xlfn.IFERROR((Z17-Z16),"N/A")} -> 239705 | AC17: {=IF(B17=6,AVERAGE(Z17),"N/A")} -> N/A
B18: {=IF(B17=0,0,IF(B17<VLOOKUP(C2,'Boats Data Sheet 2026'!$C$3:$H$57,6,0),B17+1,0))} -> 14 | C18: {=IF(B18>0,IF(VLOOKUP(C2,'Boats Data Sheet 2026'!$C$3:$J$57,8,0)="N/A",0,VLOOKUP(C2,'Boats Data Sheet 2026'!$C$3:$J$57,8,0)),"N/A")} -> 0 | D18: {=IF(B18>7,2,IF(B18=0,"N/A",1))} -> 2 | E18: {=_xlfn.IFERROR(SUM('Direct Costs 2026'!$C$4:$C$5)*D18,"N/A")} -> 1751000 | F18: {=_xlfn.IFERROR('Direct Costs 2026'!$C$43*B18,"N/A")} -> 84000 | G18: {=IF(B18>0,'Direct Costs 2026'!$C$25,"N/A")} -> 90000 | H18: {=IF(B18>0,('Direct Costs 2026'!$C$15+'Direct Costs 2026'!$C$17+'Direct Costs 2026'!$C$14),"N/A")} -> 580000 | I18: {=IF(B18>0,'Direct Costs 2026'!$C$19+'Direct Costs 2026'!$C$18*B18,"N/A")} -> 565000 | J18: {=IF(B18>0,SUM('Direct Costs 2026'!$C$20:$C$21),"N/A")} -> 98333.333 | K18: {=IF(B18>0,'Direct Costs 2026'!$C$26,"N/A")} -> 20000 | L18: {=IF(B18>0,'Direct Costs 2026'!$C$23,"N/A")} -> 140000 | M18: {=IF(B18>0,'Direct Costs 2026'!$C$45*B18,"N/A")} -> 2100000 | N18: {=IF(B18>0,_xlfn.IFERROR(VLOOKUP(C2,'Boats Data Sheet 2026'!$C$3:$I$57,7,0)*'Direct Costs 2026'!$C$36,"N/A"),"N/A")} -> 3325000 | O18: {=IF(B18>0,IF(OR(VLOOKUP(C2,'Boats Data Sheet 2026'!$C$3:$F$57,4,0)="Own",VLOOKUP(C2,'Boats Data Sheet 2026'!$C$3:$F$57,4,0)="Management"),('Direct Costs 2026'!$C$37+'Direct Costs 2026'!$C$39),"N/A"),"N/A")} -> 1112400 | P18: {=_xlfn.IFERROR('Direct Costs 2026'!$C$27*C18,"N/A")} -> 0 | Q18: {=_xlfn.IFERROR(C18+SUM(E18:P18),"N/A")} -> 9865733.3 | S18: {=IF(B18>0,'Allocation OH and Target 2026'!$E$31,"N/A")} -> 3100447.2 | T18: {=IF(B18>0,VLOOKUP(C2,'Allocation OH and Target 2026'!$C$35:$S$87,17,0),"N/A")} -> 1134128.1 | U18: {=_xlfn.IFERROR((S18+T18),"N/A")} -> 4234575.3 | W18: {=_xlfn.IFERROR(U18+Q18,"N/A")} -> 14100309 | X18: {=_xlfn.IFERROR(W18*0.5%,"N/A")} -> 70501.543 | Y18: {=_xlfn.IFERROR(W18*25%,"N/A")} -> 3525077.2 | Z18: {=IF(B18>0,SUM(W18:Y18),"N/A")} -> 17695887 | AA18: {=_xlfn.IFERROR((Z18-Z17),"N/A")} -> 239705 | AC18: {=IF(B18=6,AVERAGE(Z18),"N/A")} -> N/A
B19: {=IF(B18=0,0,IF(B18<VLOOKUP(C2,'Boats Data Sheet 2026'!$C$3:$H$57,6,0),B18+1,0))} -> 0 | C19: {=IF(B19>0,IF(VLOOKUP(C2,'Boats Data Sheet 2026'!$C$3:$J$57,8,0)="N/A",0,VLOOKUP(C2,'Boats Data Sheet 2026'!$C$3:$J$57,8,0)),"N/A")} -> N/A | D19: {=IF(B19>7,2,IF(B19=0,"N/A",1))} -> N/A | E19: {=_xlfn.IFERROR(SUM('Direct Costs 2026'!$C$4:$C$5)*D19,"N/A")} -> N/A | F19: {=_xlfn.IFERROR('Direct Costs 2026'!$C$43*B19,"N/A")} -> 0 | G19: {=IF(B19>0,'Direct Costs 2026'!$C$25,"N/A")} -> N/A | H19: {=IF(B19>0,('Direct Costs 2026'!$C$15+'Direct Costs 2026'!$C$17+'Direct Costs 2026'!$C$14),"N/A")} -> N/A | I19: {=IF(B19>0,'Direct Costs 2026'!$C$19+'Direct Costs 2026'!$C$18*B19,"N/A")} -> N/A | J19: {=IF(B19>0,SUM('Direct Costs 2026'!$C$20:$C$21),"N/A")} -> N/A | K19: {=IF(B19>0,'Direct Costs 2026'!$C$26,"N/A")} -> N/A | L19: {=IF(B19>0,'Direct Costs 2026'!$C$23,"N/A")} -> N/A | M19: {=IF(B19>0,'Direct Costs 2026'!$C$45*B19,"N/A")} -> N/A | N19: {=IF(B19>0,_xlfn.IFERROR(VLOOKUP(C2,'Boats Data Sheet 2026'!$C$3:$I$57,7,0)*'Direct Costs 2026'!$C$36,"N/A"),"N/A")} -> N/A | O19: {=IF(B19>0,IF(OR(VLOOKUP(C2,'Boats Data Sheet 2026'!$C$3:$F$57,4,0)="Own",VLOOKUP(C2,'Boats Data Sheet 2026'!$C$3:$F$57,4,0)="Management"),('Direct Costs 2026'!$C$37+'Direct Costs 2026'!$C$39),"N/A"),"N/A")} -> N/A | P19: {=_xlfn.IFERROR('Direct Costs 2026'!$C$27*C19,"N/A")} -> N/A | Q19: {=_xlfn.IFERROR(C19+SUM(E19:P19),"N/A")} -> N/A | S19: {=IF(B19>0,'Allocation OH and Target 2026'!$E$31,"N/A")} -> N/A | T19: {=IF(B19>0,VLOOKUP(C2,'Allocation OH and Target 2026'!$C$35:$S$87,16,0),"N/A")} -> N/A | U19: {=_xlfn.IFERROR((S19+T19),"N/A")} -> N/A | W19: {=_xlfn.IFERROR(U19+Q19,"N/A")} -> N/A | X19: {=_xlfn.IFERROR(W19*0.5%,"N/A")} -> N/A | Y19: {=_xlfn.IFERROR(W19*25%,"N/A")} -> N/A | Z19: {=IF(B19>0,SUM(W19:Y19),"N/A")} -> N/A | AA19: {=_xlfn.IFERROR((Z19-Z18),"N/A")} -> N/A | AC19: {=IF(B19=6,AVERAGE(Z19),"N/A")} -> N/A
B20: {=IF(B19=0,0,IF(B19<VLOOKUP(C2,'Boats Data Sheet 2026'!$C$3:$H$57,6,0),B19+1,0))} -> 0 | C20: {=IF(B20>0,IF(VLOOKUP(C2,'Boats Data Sheet 2026'!$C$3:$J$57,8,0)="N/A",0,VLOOKUP(C2,'Boats Data Sheet 2026'!$C$3:$J$57,8,0)),"N/A")} -> N/A | D20: {=IF(B20>7,2,IF(B20=0,"N/A",1))} -> N/A | E20: {=_xlfn.IFERROR(SUM('Direct Costs 2026'!$C$4:$C$5)*D20,"N/A")} -> N/A | F20: {=_xlfn.IFERROR('Direct Costs 2026'!$C$43*B20,"N/A")} -> 0 | G20: {=IF(B20>0,'Direct Costs 2026'!$C$25,"N/A")} -> N/A | H20: {=IF(B20>0,('Direct Costs 2026'!$C$15+'Direct Costs 2026'!$C$17+'Direct Costs 2026'!$C$14),"N/A")} -> N/A | I20: {=IF(B20>0,'Direct Costs 2026'!$C$19+'Direct Costs 2026'!$C$18*B20,"N/A")} -> N/A | J20: {=IF(B20>0,SUM('Direct Costs 2026'!$C$20:$C$21),"N/A")} -> N/A | K20: {=IF(B20>0,'Direct Costs 2026'!$C$26,"N/A")} -> N/A | L20: {=IF(B20>0,'Direct Costs 2026'!$C$23,"N/A")} -> N/A | M20: {=IF(B20>0,'Direct Costs 2026'!$C$45*B20,"N/A")} -> N/A | N20: {=IF(B20>0,_xlfn.IFERROR(VLOOKUP(C2,'Boats Data Sheet 2026'!$C$3:$I$57,7,0)*'Direct Costs 2026'!$C$36,"N/A"),"N/A")} -> N/A | O20: {=IF(B20>0,IF(OR(VLOOKUP(C2,'Boats Data Sheet 2026'!$C$3:$F$57,4,0)="Own",VLOOKUP(C2,'Boats Data Sheet 2026'!$C$3:$F$57,4,0)="Management"),('Direct Costs 2026'!$C$37+'Direct Costs 2026'!$C$39),"N/A"),"N/A")} -> N/A | P20: {=_xlfn.IFERROR('Direct Costs 2026'!$C$27*C20,"N/A")} -> N/A | Q20: {=_xlfn.IFERROR(C20+SUM(E20:P20),"N/A")} -> N/A | S20: {=IF(B20>0,'Allocation OH and Target 2026'!$E$31,"N/A")} -> N/A | T20: {=IF(B20>0,VLOOKUP(C2,'Allocation OH and Target 2026'!$C$35:$S$87,16,0),"N/A")} -> N/A | U20: {=_xlfn.IFERROR((S20+T20),"N/A")} -> N/A | W20: {=_xlfn.IFERROR(U20+Q20,"N/A")} -> N/A | X20: {=_xlfn.IFERROR(W20*0.5%,"N/A")} -> N/A | Y20: {=_xlfn.IFERROR(W20*25%,"N/A")} -> N/A | Z20: {=IF(B20>0,SUM(W20:Y20),"N/A")} -> N/A | AA20: {=_xlfn.IFERROR((Z20-Z19),"N/A")} -> N/A | AC20: {=IF(B20=6,AVERAGE(Z20),"N/A")} -> N/A
B21: {=IF(B20=0,0,IF(B20<VLOOKUP(C2,'Boats Data Sheet 2026'!$C$3:$H$57,6,0),B20+1,0))} -> 0 | C21: {=IF(B21>0,IF(VLOOKUP(C2,'Boats Data Sheet 2026'!$C$3:$J$57,8,0)="N/A",0,VLOOKUP(C2,'Boats Data Sheet 2026'!$C$3:$J$57,8,0)),"N/A")} -> N/A | D21: {=IF(B21>7,2,IF(B21=0,"N/A",1))} -> N/A | E21: {=_xlfn.IFERROR(SUM('Direct Costs 2026'!$C$4:$C$5)*D21,"N/A")} -> N/A | F21: {=_xlfn.IFERROR('Direct Costs 2026'!$C$43*B21,"N/A")} -> 0 | G21: {=IF(B21>0,'Direct Costs 2026'!$C$25,"N/A")} -> N/A | H21: {=IF(B21>0,('Direct Costs 2026'!$C$15+'Direct Costs 2026'!$C$17+'Direct Costs 2026'!$C$14),"N/A")} -> N/A | I21: {=IF(B21>0,'Direct Costs 2026'!$C$19+'Direct Costs 2026'!$C$18*B21,"N/A")} -> N/A | J21: {=IF(B21>0,SUM('Direct Costs 2026'!$C$20:$C$21),"N/A")} -> N/A | K21: {=IF(B21>0,'Direct Costs 2026'!$C$26,"N/A")} -> N/A | L21: {=IF(B21>0,'Direct Costs 2026'!$C$23,"N/A")} -> N/A | M21: {=IF(B21>0,'Direct Costs 2026'!$C$45*B21,"N/A")} -> N/A | N21: {=IF(B21>0,_xlfn.IFERROR(VLOOKUP(C2,'Boats Data Sheet 2026'!$C$3:$I$57,7,0)*'Direct Costs 2026'!$C$36,"N/A"),"N/A")} -> N/A | O21: {=IF(B21>0,IF(OR(VLOOKUP(C2,'Boats Data Sheet 2026'!$C$3:$F$57,4,0)="Own",VLOOKUP(C2,'Boats Data Sheet 2026'!$C$3:$F$57,4,0)="Management"),('Direct Costs 2026'!$C$37+'Direct Costs 2026'!$C$39),"N/A"),"N/A")} -> N/A | P21: {=_xlfn.IFERROR('Direct Costs 2026'!$C$27*C21,"N/A")} -> N/A | Q21: {=_xlfn.IFERROR(C21+SUM(E21:P21),"N/A")} -> N/A | S21: {=IF(B21>0,'Allocation OH and Target 2026'!$E$31,"N/A")} -> N/A | T21: {=IF(B21>0,VLOOKUP(C2,'Allocation OH and Target 2026'!$C$35:$S$87,16,0),"N/A")} -> N/A | U21: {=_xlfn.IFERROR((S21+T21),"N/A")} -> N/A | W21: {=_xlfn.IFERROR(U21+Q21,"N/A")} -> N/A | X21: {=_xlfn.IFERROR(W21*0.5%,"N/A")} -> N/A | Y21: {=_xlfn.IFERROR(W21*25%,"N/A")} -> N/A | Z21: {=IF(B21>0,SUM(W21:Y21),"N/A")} -> N/A | AA21: {=_xlfn.IFERROR((Z21-Z20),"N/A")} -> N/A | AC21: {=IF(B21=6,AVERAGE(Z21),"N/A")} -> N/A
B22: {=IF(B21=0,0,IF(B21<VLOOKUP(C2,'Boats Data Sheet 2026'!$C$3:$H$57,6,0),B21+1,0))} -> 0 | C22: {=IF(B22>0,IF(VLOOKUP(C2,'Boats Data Sheet 2026'!$C$3:$J$57,8,0)="N/A",0,VLOOKUP(C2,'Boats Data Sheet 2026'!$C$3:$J$57,8,0)),"N/A")} -> N/A | D22: {=IF(B22>7,2,IF(B22=0,"N/A",1))} -> N/A | E22: {=_xlfn.IFERROR(SUM('Direct Costs 2026'!$C$4:$C$5)*D22,"N/A")} -> N/A | F22: {=_xlfn.IFERROR('Direct Costs 2026'!$C$43*B22,"N/A")} -> 0 | G22: {=IF(B22>0,'Direct Costs 2026'!$C$25,"N/A")} -> N/A | H22: {=IF(B22>0,('Direct Costs 2026'!$C$15+'Direct Costs 2026'!$C$17+'Direct Costs 2026'!$C$14),"N/A")} -> N/A | I22: {=IF(B22>0,'Direct Costs 2026'!$C$19+'Direct Costs 2026'!$C$18*B22,"N/A")} -> N/A | J22: {=IF(B22>0,SUM('Direct Costs 2026'!$C$20:$C$21),"N/A")} -> N/A | K22: {=IF(B22>0,'Direct Costs 2026'!$C$26,"N/A")} -> N/A | L22: {=IF(B22>0,'Direct Costs 2026'!$C$23,"N/A")} -> N/A | M22: {=IF(B22>0,'Direct Costs 2026'!$C$45*B22,"N/A")} -> N/A | N22: {=IF(B22>0,_xlfn.IFERROR(VLOOKUP(C2,'Boats Data Sheet 2026'!$C$3:$I$57,7,0)*'Direct Costs 2026'!$C$36,"N/A"),"N/A")} -> N/A | O22: {=IF(B22>0,IF(OR(VLOOKUP(C2,'Boats Data Sheet 2026'!$C$3:$F$57,4,0)="Own",VLOOKUP(C2,'Boats Data Sheet 2026'!$C$3:$F$57,4,0)="Management"),('Direct Costs 2026'!$C$37+'Direct Costs 2026'!$C$39),"N/A"),"N/A")} -> N/A | P22: {=_xlfn.IFERROR('Direct Costs 2026'!$C$27*C22,"N/A")} -> N/A | Q22: {=_xlfn.IFERROR(C22+SUM(E22:P22),"N/A")} -> N/A | S22: {=IF(B22>0,'Allocation OH and Target 2026'!$E$31,"N/A")} -> N/A | T22: {=IF(B22>0,VLOOKUP(C2,'Allocation OH and Target 2026'!$C$35:$S$87,16,0),"N/A")} -> N/A | U22: {=_xlfn.IFERROR((S22+T22),"N/A")} -> N/A | W22: {=_xlfn.IFERROR(U22+Q22,"N/A")} -> N/A | X22: {=_xlfn.IFERROR(W22*0.5%,"N/A")} -> N/A | Y22: {=_xlfn.IFERROR(W22*25%,"N/A")} -> N/A | Z22: {=IF(B22>0,SUM(W22:Y22),"N/A")} -> N/A | AA22: {=_xlfn.IFERROR((Z22-Z21),"N/A")} -> N/A | AC22: {=IF(B22=6,AVERAGE(Z22),"N/A")} -> N/A
A25: 2 | B25: Boat: | C25: Riki J | AE25: Average direct cost | AF25: {=AVERAGE(Q28:Q33)} -> 7317233.3 | AG25: Extra pax cost | AH25: {=AVERAGE(Q34:Q41)-AF25} -> 2103062.5 | AI25: Average profit margin | AJ25: {=AVERAGE(Y28:Y35)} -> 3018530.7 | AK25: Average total cost | AL25: {=AVERAGE(W28:W33)} -> 11773685 | AM25: 1-Pax cost | AN25: {=W28} -> 11296185
C26: DIRECT COSTS | S26: INDIRECT COST | W26: TARGER PRICING | AC26: Წ
B27: Guests u | C27: Boat Rent u | D27: Guides | E27: Guides Salary & Tax | F27: Towels | G27: Ice & Water | H27: NP + Bali Clearance | I27: Seran Retribution | J27: Seran Parking and Mooring | K27: Offering | L27: Fruits | M27: Lunch | N27: Fuel Pertamax | O27: Crew Salary & Tax u | P27: Boat Tax | Q27: TOTAL DIRECT | S27: Indirect and Admin Cost per tour | T27: 3D (Depretiation, Docking, Doc) fees per tour u | U27: TOTAL INDIRECT | W27: TOTAL COST | X27: Tax Markup 0.5% | Y27: Targer Net Profit Margin 25% | Z27: TARGET PRICE PER TOUR | AA27: Extra Pax Charge | AC27: RECOMMENED BASE PRICE PER TOUR
B28: 1 | C28: {=IF(B28>0,IF(VLOOKUP(C25,'Boats Data Sheet 2026'!$C$3:$J$57,8,0)="N/A",0,VLOOKUP(C25,'Boats Data Sheet 2026'!$C$3:$J$57,8,0)),"N/A")} -> 0 | D28: {=IF(B28>7,2,IF(B28=0,"N/A",1))} -> 1 | E28: {=_xlfn.IFERROR(SUM('Direct Costs 2026'!$C$4:$C$5)*D28,"N/A")} -> 875500 | F28: {=_xlfn.IFERROR('Direct Costs 2026'!$C$43*B28,"N/A")} -> 6000 | G28: {=IF(B28>0,'Direct Costs 2026'!$C$25,"N/A")} -> 90000 | H28: {=IF(B28>0,('Direct Costs 2026'!$C$15+'Direct Costs 2026'!$C$14+'Direct Costs 2026'!$C$17),"N/A")} -> 580000 | I28: {=IF(B28>0,'Direct Costs 2026'!$C$19+'Direct Costs 2026'!$C$18*B28,"N/A")} -> 110000 | J28: {=IF(B28>0,SUM('Direct Costs 2026'!$C$20:$C$21),"N/A")} -> 98333.333 | K28: {=IF(B28>0,'Direct Costs 2026'!$C$26,"N/A")} -> 20000 | L28: {=IF(B28>0,'Direct Costs 2026'!$C$23,"N/A")} -> 140000 | M28: {=IF(B28>0,'Direct Costs 2026'!$C$45*B28,"N/A")} -> 150000 | N28: {=IF(B28>0,_xlfn.IFERROR(VLOOKUP(C25,'Boats Data Sheet 2026'!$C$3:$I$57,7,0)*'Direct Costs 2026'!$C$36,"N/A"),"N/A")} -> 3657500 | O28: {=IF(B28>0,IF(OR(VLOOKUP(C25,'Boats Data Sheet 2026'!$C$3:$F$57,4,0)="Own",VLOOKUP(C25,'Boats Data Sheet 2026'!$C$3:$F$57,4,0)="Management"),('Direct Costs 2026'!$C$37+'Direct Costs 2026'!$C$39),"N/A"),"N/A")} -> 1112400 | P28: {=_xlfn.IFERROR('Direct Costs 2026'!$C$27*C28,"N/A")} -> 0 | Q28: {=_xlfn.IFERROR(C28+SUM(E28:P28),"N/A")} -> 6839733.3 | S28: {=IF(B28>0,'Allocation OH and Target 2026'!$E$31,"N/A")} -> 3100447.2 | T28: {=IF(B28>0,VLOOKUP(C25,'Allocation OH and Target 2026'!$C$35:$S$87,17,0),"N/A")} -> 1356004.9 | U28: {=_xlfn.IFERROR((S28+T28),"N/A")} -> 4456452 | W28: {=_xlfn.IFERROR(U28+Q28,"N/A")} -> 11296185 | X28: {=_xlfn.IFERROR(W28*0.5%,"N/A")} -> 56480.927 | Y28: {=_xlfn.IFERROR(W28*25%,"N/A")} -> 2824046.3 | Z28: {=IF(B28>0,SUM(W28:Y28),"N/A")} -> 14176713 | AA28: 0 | AC28: {=IF(B28=6,AVERAGE(Z28:Z33),"N/A")} -> N/A
B29: {=IF(B28=0,0,IF(B28<VLOOKUP(C25,'Boats Data Sheet 2026'!$C$3:$H$57,6,0),B28+1,0))} -> 2 | C29: {=IF(B29>0,IF(VLOOKUP(C25,'Boats Data Sheet 2026'!$C$3:$J$57,8,0)="N/A",0,VLOOKUP(C25,'Boats Data Sheet 2026'!$C$3:$J$57,8,0)),"N/A")} -> 0 | D29: {=IF(B29>7,2,IF(B29=0,"N/A",1))} -> 1 | E29: {=_xlfn.IFERROR(SUM('Direct Costs 2026'!$C$4:$C$5)*D29,"N/A")} -> 875500 | F29: {=_xlfn.IFERROR('Direct Costs 2026'!$C$43*B29,"N/A")} -> 12000 | G29: {=IF(B29>0,'Direct Costs 2026'!$C$25,"N/A")} -> 90000 | H29: {=IF(B29>0,('Direct Costs 2026'!$C$15+'Direct Costs 2026'!$C$14+'Direct Costs 2026'!$C$17),"N/A")} -> 580000 | I29: {=IF(B29>0,'Direct Costs 2026'!$C$19+'Direct Costs 2026'!$C$18*B29,"N/A")} -> 145000 | J29: {=IF(B29>0,SUM('Direct Costs 2026'!$C$20:$C$21),"N/A")} -> 98333.333 | K29: {=IF(B29>0,'Direct Costs 2026'!$C$26,"N/A")} -> 20000 | L29: {=IF(B29>0,'Direct Costs 2026'!$C$23,"N/A")} -> 140000 | M29: {=IF(B29>0,'Direct Costs 2026'!$C$45*B29,"N/A")} -> 300000 | N29: {=IF(B29>0,_xlfn.IFERROR(VLOOKUP(C25,'Boats Data Sheet 2026'!$C$3:$I$57,7,0)*'Direct Costs 2026'!$C$36,"N/A"),"N/A")} -> 3657500 | O29: {=IF(B29>0,IF(OR(VLOOKUP(C25,'Boats Data Sheet 2026'!$C$3:$F$57,4,0)="Own",VLOOKUP(C25,'Boats Data Sheet 2026'!$C$3:$F$57,4,0)="Management"),('Direct Costs 2026'!$C$37+'Direct Costs 2026'!$C$39),"N/A"),"N/A")} -> 1112400 | P29: {=_xlfn.IFERROR('Direct Costs 2026'!$C$27*C29,"N/A")} -> 0 | Q29: {=_xlfn.IFERROR(C29+SUM(E29:P29),"N/A")} -> 7030733.3 | S29: {=IF(B29>0,'Allocation OH and Target 2026'!$E$31,"N/A")} -> 3100447.2 | T29: {=IF(B29>0,VLOOKUP(C25,'Allocation OH and Target 2026'!$C$35:$S$87,17,0),"N/A")} -> 1356004.9 | U29: {=_xlfn.IFERROR((S29+T29),"N/A")} -> 4456452 | W29: {=_xlfn.IFERROR(U29+Q29,"N/A")} -> 11487185 | X29: {=_xlfn.IFERROR(W29*0.5%,"N/A")} -> 57435.927 | Y29: {=_xlfn.IFERROR(W29*25%,"N/A")} -> 2871796.3 | Z29: {=IF(B29>0,SUM(W29:Y29),"N/A")} -> 14416418 | AA29: {=_xlfn.IFERROR((Z29-Z28),"N/A")} -> 239705 | AC29: {=IF(B29=6,AVERAGE(Z28:Z33),"N/A")} -> N/A
B30: {=IF(B29=0,0,IF(B29<VLOOKUP(C25,'Boats Data Sheet 2026'!$C$3:$H$57,6,0),B29+1,0))} -> 3 | C30: {=IF(B30>0,IF(VLOOKUP(C25,'Boats Data Sheet 2026'!$C$3:$J$57,8,0)="N/A",0,VLOOKUP(C25,'Boats Data Sheet 2026'!$C$3:$J$57,8,0)),"N/A")} -> 0 | D30: {=IF(B30>7,2,IF(B30=0,"N/A",1))} -> 1 | E30: {=_xlfn.IFERROR(SUM('Direct Costs 2026'!$C$4:$C$5)*D30,"N/A")} -> 875500 | F30: {=_xlfn.IFERROR('Direct Costs 2026'!$C$43*B30,"N/A")} -> 18000 | G30: {=IF(B30>0,'Direct Costs 2026'!$C$25,"N/A")} -> 90000 | H30: {=IF(B30>0,('Direct Costs 2026'!$C$15+'Direct Costs 2026'!$C$14+'Direct Costs 2026'!$C$17),"N/A")} -> 580000 | I30: {=IF(B30>0,'Direct Costs 2026'!$C$19+'Direct Costs 2026'!$C$18*B30,"N/A")} -> 180000 | J30: {=IF(B30>0,SUM('Direct Costs 2026'!$C$20:$C$21),"N/A")} -> 98333.333 | K30: {=IF(B30>0,'Direct Costs 2026'!$C$26,"N/A")} -> 20000 | L30: {=IF(B30>0,'Direct Costs 2026'!$C$23,"N/A")} -> 140000 | M30: {=IF(B30>0,'Direct Costs 2026'!$C$45*B30,"N/A")} -> 450000 | N30: {=IF(B30>0,_xlfn.IFERROR(VLOOKUP(C25,'Boats Data Sheet 2026'!$C$3:$I$57,7,0)*'Direct Costs 2026'!$C$36,"N/A"),"N/A")} -> 3657500 | O30: {=IF(B30>0,IF(OR(VLOOKUP(C25,'Boats Data Sheet 2026'!$C$3:$F$57,4,0)="Own",VLOOKUP(C25,'Boats Data Sheet 2026'!$C$3:$F$57,4,0)="Management"),('Direct Costs 2026'!$C$37+'Direct Costs 2026'!$C$39),"N/A"),"N/A")} -> 1112400 | P30: {=_xlfn.IFERROR('Direct Costs 2026'!$C$27*C30,"N/A")} -> 0 | Q30: {=_xlfn.IFERROR(C30+SUM(E30:P30),"N/A")} -> 7221733.3 | S30: {=IF(B30>0,'Allocation OH and Target 2026'!$E$31,"N/A")} -> 3100447.2 | T30: {=IF(B30>0,VLOOKUP(C25,'Allocation OH and Target 2026'!$C$35:$S$87,17,0),"N/A")} -> 1356004.9 | U30: {=_xlfn.IFERROR((S30+T30),"N/A")} -> 4456452 | W30: {=_xlfn.IFERROR(U30+Q30,"N/A")} -> 11678185 | X30: {=_xlfn.IFERROR(W30*0.5%,"N/A")} -> 58390.927 | Y30: {=_xlfn.IFERROR(W30*25%,"N/A")} -> 2919546.3 | Z30: {=IF(B30>0,SUM(W30:Y30),"N/A")} -> 14656123 | AA30: {=_xlfn.IFERROR((Z30-Z29),"N/A")} -> 239705 | AC30: {=IF(B30=6,AVERAGE(Z28:Z33),"N/A")} -> N/A
B31: {=IF(B30=0,0,IF(B30<VLOOKUP(C25,'Boats Data Sheet 2026'!$C$3:$H$57,6,0),B30+1,0))} -> 4 | C31: {=IF(B31>0,IF(VLOOKUP(C25,'Boats Data Sheet 2026'!$C$3:$J$57,8,0)="N/A",0,VLOOKUP(C25,'Boats Data Sheet 2026'!$C$3:$J$57,8,0)),"N/A")} -> 0 | D31: {=IF(B31>7,2,IF(B31=0,"N/A",1))} -> 1 | E31: {=_xlfn.IFERROR(SUM('Direct Costs 2026'!$C$4:$C$5)*D31,"N/A")} -> 875500 | F31: {=_xlfn.IFERROR('Direct Costs 2026'!$C$43*B31,"N/A")} -> 24000 | G31: {=IF(B31>0,'Direct Costs 2026'!$C$25,"N/A")} -> 90000 | H31: {=IF(B31>0,('Direct Costs 2026'!$C$15+'Direct Costs 2026'!$C$14+'Direct Costs 2026'!$C$17),"N/A")} -> 580000 | I31: {=IF(B31>0,'Direct Costs 2026'!$C$19+'Direct Costs 2026'!$C$18*B31,"N/A")} -> 215000 | J31: {=IF(B31>0,SUM('Direct Costs 2026'!$C$20:$C$21),"N/A")} -> 98333.333 | K31: {=IF(B31>0,'Direct Costs 2026'!$C$26,"N/A")} -> 20000 | L31: {=IF(B31>0,'Direct Costs 2026'!$C$23,"N/A")} -> 140000 | M31: {=IF(B31>0,'Direct Costs 2026'!$C$45*B31,"N/A")} -> 600000 | N31: {=IF(B31>0,_xlfn.IFERROR(VLOOKUP(C25,'Boats Data Sheet 2026'!$C$3:$I$57,7,0)*'Direct Costs 2026'!$C$36,"N/A"),"N/A")} -> 3657500 | O31: {=IF(B31>0,IF(OR(VLOOKUP(C25,'Boats Data Sheet 2026'!$C$3:$F$57,4,0)="Own",VLOOKUP(C25,'Boats Data Sheet 2026'!$C$3:$F$57,4,0)="Management"),('Direct Costs 2026'!$C$37+'Direct Costs 2026'!$C$39),"N/A"),"N/A")} -> 1112400 | P31: {=_xlfn.IFERROR('Direct Costs 2026'!$C$27*C31,"N/A")} -> 0 | Q31: {=_xlfn.IFERROR(C31+SUM(E31:P31),"N/A")} -> 7412733.3 | S31: {=IF(B31>0,'Allocation OH and Target 2026'!$E$31,"N/A")} -> 3100447.2 | T31: {=IF(B31>0,VLOOKUP(C25,'Allocation OH and Target 2026'!$C$35:$S$87,17,0),"N/A")} -> 1356004.9 | U31: {=_xlfn.IFERROR((S31+T31),"N/A")} -> 4456452 | W31: {=_xlfn.IFERROR(U31+Q31,"N/A")} -> 11869185 | X31: {=_xlfn.IFERROR(W31*0.5%,"N/A")} -> 59345.927 | Y31: {=_xlfn.IFERROR(W31*25%,"N/A")} -> 2967296.3 | Z31: {=IF(B31>0,SUM(W31:Y31),"N/A")} -> 14895828 | AA31: {=_xlfn.IFERROR((Z31-Z30),"N/A")} -> 239705 | AC31: {=IF(B31=6,AVERAGE(Z28:Z33),"N/A")} -> N/A
B32: {=IF(B31=0,0,IF(B31<VLOOKUP(C25,'Boats Data Sheet 2026'!$C$3:$H$57,6,0),B31+1,0))} -> 5 | C32: {=IF(B32>0,IF(VLOOKUP(C25,'Boats Data Sheet 2026'!$C$3:$J$57,8,0)="N/A",0,VLOOKUP(C25,'Boats Data Sheet 2026'!$C$3:$J$57,8,0)),"N/A")} -> 0 | D32: {=IF(B32>7,2,IF(B32=0,"N/A",1))} -> 1 | E32: {=_xlfn.IFERROR(SUM('Direct Costs 2026'!$C$4:$C$5)*D32,"N/A")} -> 875500 | F32: {=_xlfn.IFERROR('Direct Costs 2026'!$C$43*B32,"N/A")} -> 30000 | G32: {=IF(B32>0,'Direct Costs 2026'!$C$25,"N/A")} -> 90000 | H32: {=IF(B32>0,('Direct Costs 2026'!$C$15+'Direct Costs 2026'!$C$14+'Direct Costs 2026'!$C$17),"N/A")} -> 580000 | I32: {=IF(B32>0,'Direct Costs 2026'!$C$19+'Direct Costs 2026'!$C$18*B32,"N/A")} -> 250000 | J32: {=IF(B32>0,SUM('Direct Costs 2026'!$C$20:$C$21),"N/A")} -> 98333.333 | K32: {=IF(B32>0,'Direct Costs 2026'!$C$26,"N/A")} -> 20000 | L32: {=IF(B32>0,'Direct Costs 2026'!$C$23,"N/A")} -> 140000 | M32: {=IF(B32>0,'Direct Costs 2026'!$C$45*B32,"N/A")} -> 750000 | N32: {=IF(B32>0,_xlfn.IFERROR(VLOOKUP(C25,'Boats Data Sheet 2026'!$C$3:$I$57,7,0)*'Direct Costs 2026'!$C$36,"N/A"),"N/A")} -> 3657500 | O32: {=IF(B32>0,IF(OR(VLOOKUP(C25,'Boats Data Sheet 2026'!$C$3:$F$57,4,0)="Own",VLOOKUP(C25,'Boats Data Sheet 2026'!$C$3:$F$57,4,0)="Management"),('Direct Costs 2026'!$C$37+'Direct Costs 2026'!$C$39),"N/A"),"N/A")} -> 1112400 | P32: {=_xlfn.IFERROR('Direct Costs 2026'!$C$27*C32,"N/A")} -> 0 | Q32: {=_xlfn.IFERROR(C32+SUM(E32:P32),"N/A")} -> 7603733.3 | S32: {=IF(B32>0,'Allocation OH and Target 2026'!$E$31,"N/A")} -> 3100447.2 | T32: {=IF(B32>0,VLOOKUP(C25,'Allocation OH and Target 2026'!$C$35:$S$87,17,0),"N/A")} -> 1356004.9 | U32: {=_xlfn.IFERROR((S32+T32),"N/A")} -> 4456452 | W32: {=_xlfn.IFERROR(U32+Q32,"N/A")} -> 12060185 | X32: {=_xlfn.IFERROR(W32*0.5%,"N/A")} -> 60300.927 | Y32: {=_xlfn.IFERROR(W32*25%,"N/A")} -> 3015046.3 | Z32: {=IF(B32>0,SUM(W32:Y32),"N/A")} -> 15135533 | AA32: {=_xlfn.IFERROR((Z32-Z31),"N/A")} -> 239705 | AC32: {=IF(B32=6,AVERAGE(Z28:Z33),"N/A")} -> N/A
B33: {=IF(B32=0,0,IF(B32<VLOOKUP(C25,'Boats Data Sheet 2026'!$C$3:$H$57,6,0),B32+1,0))} -> 6 | C33: {=IF(B33>0,IF(VLOOKUP(C25,'Boats Data Sheet 2026'!$C$3:$J$57,8,0)="N/A",0,VLOOKUP(C25,'Boats Data Sheet 2026'!$C$3:$J$57,8,0)),"N/A")} -> 0 | D33: {=IF(B33>7,2,IF(B33=0,"N/A",1))} -> 1 | E33: {=_xlfn.IFERROR(SUM('Direct Costs 2026'!$C$4:$C$5)*D33,"N/A")} -> 875500 | F33: {=_xlfn.IFERROR('Direct Costs 2026'!$C$43*B33,"N/A")} -> 36000 | G33: {=IF(B33>0,'Direct Costs 2026'!$C$25,"N/A")} -> 90000 | H33: {=IF(B33>0,('Direct Costs 2026'!$C$15+'Direct Costs 2026'!$C$14+'Direct Costs 2026'!$C$17),"N/A")} -> 580000 | I33: {=IF(B33>0,'Direct Costs 2026'!$C$19+'Direct Costs 2026'!$C$18*B33,"N/A")} -> 285000 | J33: {=IF(B33>0,SUM('Direct Costs 2026'!$C$20:$C$21),"N/A")} -> 98333.333 | K33: {=IF(B33>0,'Direct Costs 2026'!$C$26,"N/A")} -> 20000 | L33: {=IF(B33>0,'Direct Costs 2026'!$C$23,"N/A")} -> 140000 | M33: {=IF(B33>0,'Direct Costs 2026'!$C$45*B33,"N/A")} -> 900000 | N33: {=IF(B33>0,_xlfn.IFERROR(VLOOKUP(C25,'Boats Data Sheet 2026'!$C$3:$I$57,7,0)*'Direct Costs 2026'!$C$36,"N/A"),"N/A")} -> 3657500 | O33: {=IF(B33>0,IF(OR(VLOOKUP(C25,'Boats Data Sheet 2026'!$C$3:$F$57,4,0)="Own",VLOOKUP(C25,'Boats Data Sheet 2026'!$C$3:$F$57,4,0)="Management"),('Direct Costs 2026'!$C$37+'Direct Costs 2026'!$C$39),"N/A"),"N/A")} -> 1112400 | P33: {=_xlfn.IFERROR('Direct Costs 2026'!$C$27*C33,"N/A")} -> 0 | Q33: {=_xlfn.IFERROR(C33+SUM(E33:P33),"N/A")} -> 7794733.3 | S33: {=IF(B33>0,'Allocation OH and Target 2026'!$E$31,"N/A")} -> 3100447.2 | T33: {=IF(B33>0,VLOOKUP(C25,'Allocation OH and Target 2026'!$C$35:$S$87,17,0),"N/A")} -> 1356004.9 | U33: {=_xlfn.IFERROR((S33+T33),"N/A")} -> 4456452 | W33: {=_xlfn.IFERROR(U33+Q33,"N/A")} -> 12251185 | X33: {=_xlfn.IFERROR(W33*0.5%,"N/A")} -> 61255.927 | Y33: {=_xlfn.IFERROR(W33*25%,"N/A")} -> 3062796.3 | Z33: {=IF(B33>0,SUM(W33:Y33),"N/A")} -> 15375238 | AA33: {=_xlfn.IFERROR((Z33-Z32),"N/A")} -> 239705 | AC33: {=IF(B33=6,AVERAGE(Z28:Z33),"N/A")} -> 14775975
B34: {=IF(B33=0,0,IF(B33<VLOOKUP(C25,'Boats Data Sheet 2026'!$C$3:$H$57,6,0),B33+1,0))} -> 7 | C34: {=IF(B34>0,IF(VLOOKUP(C25,'Boats Data Sheet 2026'!$C$3:$J$57,8,0)="N/A",0,VLOOKUP(C25,'Boats Data Sheet 2026'!$C$3:$J$57,8,0)),"N/A")} -> 0 | D34: {=IF(B34>7,2,IF(B34=0,"N/A",1))} -> 1 | E34: {=_xlfn.IFERROR(SUM('Direct Costs 2026'!$C$4:$C$5)*D34,"N/A")} -> 875500 | F34: {=_xlfn.IFERROR('Direct Costs 2026'!$C$43*B34,"N/A")} -> 42000 | G34: {=IF(B34>0,'Direct Costs 2026'!$C$25,"N/A")} -> 90000 | H34: {=IF(B34>0,('Direct Costs 2026'!$C$15+'Direct Costs 2026'!$C$14+'Direct Costs 2026'!$C$17),"N/A")} -> 580000 | I34: {=IF(B34>0,'Direct Costs 2026'!$C$19+'Direct Costs 2026'!$C$18*B34,"N/A")} -> 320000 | J34: {=IF(B34>0,SUM('Direct Costs 2026'!$C$20:$C$21),"N/A")} -> 98333.333 | K34: {=IF(B34>0,'Direct Costs 2026'!$C$26,"N/A")} -> 20000 | L34: {=IF(B34>0,'Direct Costs 2026'!$C$23,"N/A")} -> 140000 | M34: {=IF(B34>0,'Direct Costs 2026'!$C$45*B34,"N/A")} -> 1050000 | N34: {=IF(B34>0,_xlfn.IFERROR(VLOOKUP(C25,'Boats Data Sheet 2026'!$C$3:$I$57,7,0)*'Direct Costs 2026'!$C$36,"N/A"),"N/A")} -> 3657500 | O34: {=IF(B34>0,IF(OR(VLOOKUP(C25,'Boats Data Sheet 2026'!$C$3:$F$57,4,0)="Own",VLOOKUP(C25,'Boats Data Sheet 2026'!$C$3:$F$57,4,0)="Management"),('Direct Costs 2026'!$C$37+'Direct Costs 2026'!$C$39),"N/A"),"N/A")} -> 1112400 | P34: {=_xlfn.IFERROR('Direct Costs 2026'!$C$27*C34,"N/A")} -> 0 | Q34: {=_xlfn.IFERROR(C34+SUM(E34:P34),"N/A")} -> 7985733.3 | S34: {=IF(B34>0,'Allocation OH and Target 2026'!$E$31,"N/A")} -> 3100447.2 | T34: {=IF(B34>0,VLOOKUP(C25,'Allocation OH and Target 2026'!$C$35:$S$87,17,0),"N/A")} -> 1356004.9 | U34: {=_xlfn.IFERROR((S34+T34),"N/A")} -> 4456452 | W34: {=_xlfn.IFERROR(U34+Q34,"N/A")} -> 12442185 | X34: {=_xlfn.IFERROR(W34*0.5%,"N/A")} -> 62210.927 | Y34: {=_xlfn.IFERROR(W34*25%,"N/A")} -> 3110546.3 | Z34: {=IF(B34>0,SUM(W34:Y34),"N/A")} -> 15614943 | AA34: {=_xlfn.IFERROR((Z34-Z33),"N/A")} -> 239705 | AC34: {=IF(B34=6,AVERAGE(Z28:Z33),"N/A")} -> N/A
B35: {=IF(B34=0,0,IF(B34<VLOOKUP(C25,'Boats Data Sheet 2026'!$C$3:$H$57,6,0),B34+1,0))} -> 8 | C35: {=IF(B35>0,IF(VLOOKUP(C25,'Boats Data Sheet 2026'!$C$3:$J$57,8,0)="N/A",0,VLOOKUP(C25,'Boats Data Sheet 2026'!$C$3:$J$57,8,0)),"N/A")} -> 0 | D35: {=IF(B35>7,2,IF(B35=0,"N/A",1))} -> 2 | E35: {=_xlfn.IFERROR(SUM('Direct Costs 2026'!$C$4:$C$5)*D35,"N/A")} -> 1751000 | F35: {=_xlfn.IFERROR('Direct Costs 2026'!$C$43*B35,"N/A")} -> 48000 | G35: {=IF(B35>0,'Direct Costs 2026'!$C$25,"N/A")} -> 90000 | H35: {=IF(B35>0,('Direct Costs 2026'!$C$15+'Direct Costs 2026'!$C$14+'Direct Costs 2026'!$C$17),"N/A")} -> 580000 | I35: {=IF(B35>0,'Direct Costs 2026'!$C$19+'Direct Costs 2026'!$C$18*B35,"N/A")} -> 355000 | J35: {=IF(B35>0,SUM('Direct Costs 2026'!$C$20:$C$21),"N/A")} -> 98333.333 | K35: {=IF(B35>0,'Direct Costs 2026'!$C$26,"N/A")} -> 20000 | L35: {=IF(B35>0,'Direct Costs 2026'!$C$23,"N/A")} -> 140000 | M35: {=IF(B35>0,'Direct Costs 2026'!$C$45*B35,"N/A")} -> 1200000 | N35: {=IF(B35>0,_xlfn.IFERROR(VLOOKUP(C25,'Boats Data Sheet 2026'!$C$3:$I$57,7,0)*'Direct Costs 2026'!$C$36,"N/A"),"N/A")} -> 3657500 | O35: {=IF(B35>0,IF(OR(VLOOKUP(C25,'Boats Data Sheet 2026'!$C$3:$F$57,4,0)="Own",VLOOKUP(C25,'Boats Data Sheet 2026'!$C$3:$F$57,4,0)="Management"),('Direct Costs 2026'!$C$37+'Direct Costs 2026'!$C$39),"N/A"),"N/A")} -> 1112400 | P35: {=_xlfn.IFERROR('Direct Costs 2026'!$C$27*C35,"N/A")} -> 0 | Q35: {=_xlfn.IFERROR(C35+SUM(E35:P35),"N/A")} -> 9052233.3 | S35: {=IF(B35>0,'Allocation OH and Target 2026'!$E$31,"N/A")} -> 3100447.2 | T35: {=IF(B35>0,VLOOKUP(C25,'Allocation OH and Target 2026'!$C$35:$S$87,17,0),"N/A")} -> 1356004.9 | U35: {=_xlfn.IFERROR((S35+T35),"N/A")} -> 4456452 | W35: {=_xlfn.IFERROR(U35+Q35,"N/A")} -> 13508685 | X35: {=_xlfn.IFERROR(W35*0.5%,"N/A")} -> 67543.427 | Y35: {=_xlfn.IFERROR(W35*25%,"N/A")} -> 3377171.3 | Z35: {=IF(B35>0,SUM(W35:Y35),"N/A")} -> 16953400 | AA35: {=_xlfn.IFERROR((Z35-Z34),"N/A")} -> 1338457.5 | AC35: {=IF(B35=6,AVERAGE(Z28:Z33),"N/A")} -> N/A
B36: {=IF(B35=0,0,IF(B35<VLOOKUP(C25,'Boats Data Sheet 2026'!$C$3:$H$57,6,0),B35+1,0))} -> 9 | C36: {=IF(B36>0,IF(VLOOKUP(C25,'Boats Data Sheet 2026'!$C$3:$J$57,8,0)="N/A",0,VLOOKUP(C25,'Boats Data Sheet 2026'!$C$3:$J$57,8,0)),"N/A")} -> 0 | D36: {=IF(B36>7,2,IF(B36=0,"N/A",1))} -> 2 | E36: {=_xlfn.IFERROR(SUM('Direct Costs 2026'!$C$4:$C$5)*D36,"N/A")} -> 1751000 | F36: {=_xlfn.IFERROR('Direct Costs 2026'!$C$43*B36,"N/A")} -> 54000 | G36: {=IF(B36>0,'Direct Costs 2026'!$C$25,"N/A")} -> 90000 | H36: {=IF(B36>0,('Direct Costs 2026'!$C$15+'Direct Costs 2026'!$C$14+'Direct Costs 2026'!$C$17),"N/A")} -> 580000 | I36: {=IF(B36>0,'Direct Costs 2026'!$C$19+'Direct Costs 2026'!$C$18*B36,"N/A")} -> 390000 | J36: {=IF(B36>0,SUM('Direct Costs 2026'!$C$20:$C$21),"N/A")} -> 98333.333 | K36: {=IF(B36>0,'Direct Costs 2026'!$C$26,"N/A")} -> 20000 | L36: {=IF(B36>0,'Direct Costs 2026'!$C$23,"N/A")} -> 140000 | M36: {=IF(B36>0,'Direct Costs 2026'!$C$45*B36,"N/A")} -> 1350000 | N36: {=IF(B36>0,_xlfn.IFERROR(VLOOKUP(C25,'Boats Data Sheet 2026'!$C$3:$I$57,7,0)*'Direct Costs 2026'!$C$36,"N/A"),"N/A")} -> 3657500 | O36: {=IF(B36>0,IF(OR(VLOOKUP(C25,'Boats Data Sheet 2026'!$C$3:$F$57,4,0)="Own",VLOOKUP(C25,'Boats Data Sheet 2026'!$C$3:$F$57,4,0)="Management"),('Direct Costs 2026'!$C$37+'Direct Costs 2026'!$C$39),"N/A"),"N/A")} -> 1112400 | P36: {=_xlfn.IFERROR('Direct Costs 2026'!$C$27*C36,"N/A")} -> 0 | Q36: {=_xlfn.IFERROR(C36+SUM(E36:P36),"N/A")} -> 9243233.3 | S36: {=IF(B36>0,'Allocation OH and Target 2026'!$E$31,"N/A")} -> 3100447.2 | T36: {=IF(B36>0,VLOOKUP(C25,'Allocation OH and Target 2026'!$C$35:$S$87,17,0),"N/A")} -> 1356004.9 | U36: {=_xlfn.IFERROR((S36+T36),"N/A")} -> 4456452 | W36: {=_xlfn.IFERROR(U36+Q36,"N/A")} -> 13699685 | X36: {=_xlfn.IFERROR(W36*0.5%,"N/A")} -> 68498.427 | Y36: {=_xlfn.IFERROR(W36*25%,"N/A")} -> 3424921.3 | Z36: {=IF(B36>0,SUM(W36:Y36),"N/A")} -> 17193105 | AA36: {=_xlfn.IFERROR((Z36-Z35),"N/A")} -> 239705 | AC36: {=IF(B36=6,AVERAGE(Z28:Z33),"N/A")} -> N/A
B37: {=IF(B36=0,0,IF(B36<VLOOKUP(C25,'Boats Data Sheet 2026'!$C$3:$H$57,6,0),B36+1,0))} -> 10 | C37: {=IF(B37>0,IF(VLOOKUP(C25,'Boats Data Sheet 2026'!$C$3:$J$57,8,0)="N/A",0,VLOOKUP(C25,'Boats Data Sheet 2026'!$C$3:$J$57,8,0)),"N/A")} -> 0 | D37: {=IF(B37>7,2,IF(B37=0,"N/A",1))} -> 2 | E37: {=_xlfn.IFERROR(SUM('Direct Costs 2026'!$C$4:$C$5)*D37,"N/A")} -> 1751000 | F37: {=_xlfn.IFERROR('Direct Costs 2026'!$C$43*B37,"N/A")} -> 60000 | G37: {=IF(B37>0,'Direct Costs 2026'!$C$25,"N/A")} -> 90000 | H37: {=IF(B37>0,('Direct Costs 2026'!$C$15+'Direct Costs 2026'!$C$14+'Direct Costs 2026'!$C$17),"N/A")} -> 580000 | I37: {=IF(B37>0,'Direct Costs 2026'!$C$19+'Direct Costs 2026'!$C$18*B37,"N/A")} -> 425000 | J37: {=IF(B37>0,SUM('Direct Costs 2026'!$C$20:$C$21),"N/A")} -> 98333.333 | K37: {=IF(B37>0,'Direct Costs 2026'!$C$26,"N/A")} -> 20000 | L37: {=IF(B37>0,'Direct Costs 2026'!$C$23,"N/A")} -> 140000 | M37: {=IF(B37>0,'Direct Costs 2026'!$C$45*B37,"N/A")} -> 1500000 | N37: {=IF(B37>0,_xlfn.IFERROR(VLOOKUP(C25,'Boats Data Sheet 2026'!$C$3:$I$57,7,0)*'Direct Costs 2026'!$C$36,"N/A"),"N/A")} -> 3657500 | O37: {=IF(B37>0,IF(OR(VLOOKUP(C25,'Boats Data Sheet 2026'!$C$3:$F$57,4,0)="Own",VLOOKUP(C25,'Boats Data Sheet 2026'!$C$3:$F$57,4,0)="Management"),('Direct Costs 2026'!$C$37+'Direct Costs 2026'!$C$39),"N/A"),"N/A")} -> 1112400 | P37: {=_xlfn.IFERROR('Direct Costs 2026'!$C$27*C37,"N/A")} -> 0 | Q37: {=_xlfn.IFERROR(C37+SUM(E37:P37),"N/A")} -> 9434233.3 | S37: {=IF(B37>0,'Allocation OH and Target 2026'!$E$31,"N/A")} -> 3100447.2 | T37: {=IF(B37>0,VLOOKUP(C25,'Allocation OH and Target 2026'!$C$35:$S$87,17,0),"N/A")} -> 1356004.9 | U37: {=_xlfn.IFERROR((S37+T37),"N/A")} -> 4456452 | W37: {=_xlfn.IFERROR(U37+Q37,"N/A")} -> 13890685 | X37: {=_xlfn.IFERROR(W37*0.5%,"N/A")} -> 69453.427 | Y37: {=_xlfn.IFERROR(W37*25%,"N/A")} -> 3472671.3 | Z37: {=IF(B37>0,SUM(W37:Y37),"N/A")} -> 17432810 | AA37: {=_xlfn.IFERROR((Z37-Z36),"N/A")} -> 239705 | AC37: {=IF(B37=6,AVERAGE(Z28:Z33),"N/A")} -> N/A
B38: {=IF(B37=0,0,IF(B37<VLOOKUP(C25,'Boats Data Sheet 2026'!$C$3:$H$57,6,0),B37+1,0))} -> 11 | C38: {=IF(B38>0,IF(VLOOKUP(C25,'Boats Data Sheet 2026'!$C$3:$J$57,8,0)="N/A",0,VLOOKUP(C25,'Boats Data Sheet 2026'!$C$3:$J$57,8,0)),"N/A")} -> 0 | D38: {=IF(B38>7,2,IF(B38=0,"N/A",1))} -> 2 | E38: {=_xlfn.IFERROR(SUM('Direct Costs 2026'!$C$4:$C$5)*D38,"N/A")} -> 1751000 | F38: {=_xlfn.IFERROR('Direct Costs 2026'!$C$43*B38,"N/A")} -> 66000 | G38: {=IF(B38>0,'Direct Costs 2026'!$C$25,"N/A")} -> 90000 | H38: {=IF(B38>0,('Direct Costs 2026'!$C$15+'Direct Costs 2026'!$C$14+'Direct Costs 2026'!$C$17),"N/A")} -> 580000 | I38: {=IF(B38>0,'Direct Costs 2026'!$C$19+'Direct Costs 2026'!$C$18*B38,"N/A")} -> 460000 | J38: {=IF(B38>0,SUM('Direct Costs 2026'!$C$20:$C$21),"N/A")} -> 98333.333 | K38: {=IF(B38>0,'Direct Costs 2026'!$C$26,"N/A")} -> 20000 | L38: {=IF(B38>0,'Direct Costs 2026'!$C$23,"N/A")} -> 140000 | M38: {=IF(B38>0,'Direct Costs 2026'!$C$45*B38,"N/A")} -> 1650000 | N38: {=IF(B38>0,_xlfn.IFERROR(VLOOKUP(C25,'Boats Data Sheet 2026'!$C$3:$I$57,7,0)*'Direct Costs 2026'!$C$36,"N/A"),"N/A")} -> 3657500 | O38: {=IF(B38>0,IF(OR(VLOOKUP(C25,'Boats Data Sheet 2026'!$C$3:$F$57,4,0)="Own",VLOOKUP(C25,'Boats Data Sheet 2026'!$C$3:$F$57,4,0)="Management"),('Direct Costs 2026'!$C$37+'Direct Costs 2026'!$C$39),"N/A"),"N/A")} -> 1112400 | P38: {=_xlfn.IFERROR('Direct Costs 2026'!$C$27*C38,"N/A")} -> 0 | Q38: {=_xlfn.IFERROR(C38+SUM(E38:P38),"N/A")} -> 9625233.3 | S38: {=IF(B38>0,'Allocation OH and Target 2026'!$E$31,"N/A")} -> 3100447.2 | T38: {=IF(B38>0,VLOOKUP(C25,'Allocation OH and Target 2026'!$C$35:$S$87,17,0),"N/A")} -> 1356004.9 | U38: {=_xlfn.IFERROR((S38+T38),"N/A")} -> 4456452 | W38: {=_xlfn.IFERROR(U38+Q38,"N/A")} -> 14081685 | X38: {=_xlfn.IFERROR(W38*0.5%,"N/A")} -> 70408.427 | Y38: {=_xlfn.IFERROR(W38*25%,"N/A")} -> 3520421.3 | Z38: {=IF(B38>0,SUM(W38:Y38),"N/A")} -> 17672515 | AA38: {=_xlfn.IFERROR((Z38-Z37),"N/A")} -> 239705 | AC38: {=IF(B38=6,AVERAGE(Z28:Z33),"N/A")} -> N/A
B39: {=IF(B38=0,0,IF(B38<VLOOKUP(C25,'Boats Data Sheet 2026'!$C$3:$H$57,6,0),B38+1,0))} -> 12 | C39: {=IF(B39>0,IF(VLOOKUP(C25,'Boats Data Sheet 2026'!$C$3:$J$57,8,0)="N/A",0,VLOOKUP(C25,'Boats Data Sheet 2026'!$C$3:$J$57,8,0)),"N/A")} -> 0 | D39: {=IF(B39>7,2,IF(B39=0,"N/A",1))} -> 2 | E39: {=_xlfn.IFERROR(SUM('Direct Costs 2026'!$C$4:$C$5)*D39,"N/A")} -> 1751000 | F39: {=_xlfn.IFERROR('Direct Costs 2026'!$C$43*B39,"N/A")} -> 72000 | G39: {=IF(B39>0,'Direct Costs 2026'!$C$25,"N/A")} -> 90000 | H39: {=IF(B39>0,('Direct Costs 2026'!$C$15+'Direct Costs 2026'!$C$14+'Direct Costs 2026'!$C$17),"N/A")} -> 580000 | I39: {=IF(B39>0,'Direct Costs 2026'!$C$19+'Direct Costs 2026'!$C$18*B39,"N/A")} -> 495000 | J39: {=IF(B39>0,SUM('Direct Costs 2026'!$C$20:$C$21),"N/A")} -> 98333.333 | K39: {=IF(B39>0,'Direct Costs 2026'!$C$26,"N/A")} -> 20000 | L39: {=IF(B39>0,'Direct Costs 2026'!$C$23,"N/A")} -> 140000 | M39: {=IF(B39>0,'Direct Costs 2026'!$C$45*B39,"N/A")} -> 1800000 | N39: {=IF(B39>0,_xlfn.IFERROR(VLOOKUP(C25,'Boats Data Sheet 2026'!$C$3:$I$57,7,0)*'Direct Costs 2026'!$C$36,"N/A"),"N/A")} -> 3657500 | O39: {=IF(B39>0,IF(OR(VLOOKUP(C25,'Boats Data Sheet 2026'!$C$3:$F$57,4,0)="Own",VLOOKUP(C25,'Boats Data Sheet 2026'!$C$3:$F$57,4,0)="Management"),('Direct Costs 2026'!$C$37+'Direct Costs 2026'!$C$39),"N/A"),"N/A")} -> 1112400 | P39: {=_xlfn.IFERROR('Direct Costs 2026'!$C$27*C39,"N/A")} -> 0 | Q39: {=_xlfn.IFERROR(C39+SUM(E39:P39),"N/A")} -> 9816233.3 | S39: {=IF(B39>0,'Allocation OH and Target 2026'!$E$31,"N/A")} -> 3100447.2 | T39: {=IF(B39>0,VLOOKUP(C25,'Allocation OH and Target 2026'!$C$35:$S$87,17,0),"N/A")} -> 1356004.9 | U39: {=_xlfn.IFERROR((S39+T39),"N/A")} -> 4456452 | W39: {=_xlfn.IFERROR(U39+Q39,"N/A")} -> 14272685 | X39: {=_xlfn.IFERROR(W39*0.5%,"N/A")} -> 71363.427 | Y39: {=_xlfn.IFERROR(W39*25%,"N/A")} -> 3568171.3 | Z39: {=IF(B39>0,SUM(W39:Y39),"N/A")} -> 17912220 | AA39: {=_xlfn.IFERROR((Z39-Z38),"N/A")} -> 239705 | AC39: {=IF(B39=6,AVERAGE(Z28:Z33),"N/A")} -> N/A
B40: {=IF(B39=0,0,IF(B39<VLOOKUP(C25,'Boats Data Sheet 2026'!$C$3:$H$57,6,0),B39+1,0))} -> 13 | C40: {=IF(B40>0,IF(VLOOKUP(C25,'Boats Data Sheet 2026'!$C$3:$J$57,8,0)="N/A",0,VLOOKUP(C25,'Boats Data Sheet 2026'!$C$3:$J$57,8,0)),"N/A")} -> 0 | D40: {=IF(B40>7,2,IF(B40=0,"N/A",1))} -> 2 | E40: {=_xlfn.IFERROR(SUM('Direct Costs 2026'!$C$4:$C$5)*D40,"N/A")} -> 1751000 | F40: {=_xlfn.IFERROR('Direct Costs 2026'!$C$43*B40,"N/A")} -> 78000 | G40: {=IF(B40>0,'Direct Costs 2026'!$C$25,"N/A")} -> 90000 | H40: {=IF(B40>0,('Direct Costs 2026'!$C$15+'Direct Costs 2026'!$C$14+'Direct Costs 2026'!$C$17),"N/A")} -> 580000 | I40: {=IF(B40>0,'Direct Costs 2026'!$C$19+'Direct Costs 2026'!$C$18*B40,"N/A")} -> 530000 | J40: {=IF(B40>0,SUM('Direct Costs 2026'!$C$20:$C$21),"N/A")} -> 98333.333 | K40: {=IF(B40>0,'Direct Costs 2026'!$C$26,"N/A")} -> 20000 | L40: {=IF(B40>0,'Direct Costs 2026'!$C$23,"N/A")} -> 140000 | M40: {=IF(B40>0,'Direct Costs 2026'!$C$45*B40,"N/A")} -> 1950000 | N40: {=IF(B40>0,_xlfn.IFERROR(VLOOKUP(C25,'Boats Data Sheet 2026'!$C$3:$I$57,7,0)*'Direct Costs 2026'!$C$36,"N/A"),"N/A")} -> 3657500 | O40: {=IF(B40>0,IF(OR(VLOOKUP(C25,'Boats Data Sheet 2026'!$C$3:$F$57,4,0)="Own",VLOOKUP(C25,'Boats Data Sheet 2026'!$C$3:$F$57,4,0)="Management"),('Direct Costs 2026'!$C$37+'Direct Costs 2026'!$C$39),"N/A"),"N/A")} -> 1112400 | P40: {=_xlfn.IFERROR('Direct Costs 2026'!$C$27*C40,"N/A")} -> 0 | Q40: {=_xlfn.IFERROR(C40+SUM(E40:P40),"N/A")} -> 10007233 | S40: {=IF(B40>0,'Allocation OH and Target 2026'!$E$31,"N/A")} -> 3100447.2 | T40: {=IF(B40>0,VLOOKUP(C25,'Allocation OH and Target 2026'!$C$35:$S$87,17,0),"N/A")} -> 1356004.9 | U40: {=_xlfn.IFERROR((S40+T40),"N/A")} -> 4456452 | W40: {=_xlfn.IFERROR(U40+Q40,"N/A")} -> 14463685 | X40: {=_xlfn.IFERROR(W40*0.5%,"N/A")} -> 72318.427 | Y40: {=_xlfn.IFERROR(W40*25%,"N/A")} -> 3615921.3 | Z40: {=IF(B40>0,SUM(W40:Y40),"N/A")} -> 18151925 | AA40: {=_xlfn.IFERROR((Z40-Z39),"N/A")} -> 239705 | AC40: {=IF(B40=6,AVERAGE(Z28:Z33),"N/A")} -> N/A
B41: {=IF(B40=0,0,IF(B40<VLOOKUP(C25,'Boats Data Sheet 2026'!$C$3:$H$57,6,0),B40+1,0))} -> 14 | C41: {=IF(B41>0,IF(VLOOKUP(C25,'Boats Data Sheet 2026'!$C$3:$J$57,8,0)="N/A",0,VLOOKUP(C25,'Boats Data Sheet 2026'!$C$3:$J$57,8,0)),"N/A")} -> 0 | D41: {=IF(B41>7,2,IF(B41=0,"N/A",1))} -> 2 | E41: {=_xlfn.IFERROR(SUM('Direct Costs 2026'!$C$4:$C$5)*D41,"N/A")} -> 1751000 | F41: {=_xlfn.IFERROR('Direct Costs 2026'!$C$43*B41,"N/A")} -> 84000 | G41: {=IF(B41>0,'Direct Costs 2026'!$C$25,"N/A")} -> 90000 | H41: {=IF(B41>0,('Direct Costs 2026'!$C$15+'Direct Costs 2026'!$C$14+'Direct Costs 2026'!$C$17),"N/A")} -> 580000 | I41: {=IF(B41>0,'Direct Costs 2026'!$C$19+'Direct Costs 2026'!$C$18*B41,"N/A")} -> 565000 | J41: {=IF(B41>0,SUM('Direct Costs 2026'!$C$20:$C$21),"N/A")} -> 98333.333 | K41: {=IF(B41>0,'Direct Costs 2026'!$C$26,"N/A")} -> 20000 | L41: {=IF(B41>0,'Direct Costs 2026'!$C$23,"N/A")} -> 140000 | M41: {=IF(B41>0,'Direct Costs 2026'!$C$45*B41,"N/A")} -> 2100000 | N41: {=IF(B41>0,_xlfn.IFERROR(VLOOKUP(C25,'Boats Data Sheet 2026'!$C$3:$I$57,7,0)*'Direct Costs 2026'!$C$36,"N/A"),"N/A")} -> 3657500 | O41: {=IF(B41>0,IF(OR(VLOOKUP(C25,'Boats Data Sheet 2026'!$C$3:$F$57,4,0)="Own",VLOOKUP(C25,'Boats Data Sheet 2026'!$C$3:$F$57,4,0)="Management"),('Direct Costs 2026'!$C$37+'Direct Costs 2026'!$C$39),"N/A"),"N/A")} -> 1112400 | P41: {=_xlfn.IFERROR('Direct Costs 2026'!$C$27*C41,"N/A")} -> 0 | Q41: {=_xlfn.IFERROR(C41+SUM(E41:P41),"N/A")} -> 10198233 | S41: {=IF(B41>0,'Allocation OH and Target 2026'!$E$31,"N/A")} -> 3100447.2 | T41: {=IF(B41>0,VLOOKUP(C25,'Allocation OH and Target 2026'!$C$35:$S$87,17,0),"N/A")} -> 1356004.9 | U41: {=_xlfn.IFERROR((S41+T41),"N/A")} -> 4456452 | W41: {=_xlfn.IFERROR(U41+Q41,"N/A")} -> 14654685 | X41: {=_xlfn.IFERROR(W41*0.5%,"N/A")} -> 73273.427 | Y41: {=_xlfn.IFERROR(W41*25%,"N/A")} -> 3663671.3 | Z41: {=IF(B41>0,SUM(W41:Y41),"N/A")} -> 18391630 | AA41: {=_xlfn.IFERROR((Z41-Z40),"N/A")} -> 239705 | AC41: {=IF(B41=6,AVERAGE(Z28:Z33),"N/A")} -> N/A
B42: {=IF(B41=0,0,IF(B41<VLOOKUP(C25,'Boats Data Sheet 2026'!$C$3:$H$57,6,0),B41+1,0))} -> 0 | C42: {=IF(B42>0,IF(VLOOKUP(C25,'Boats Data Sheet 2026'!$C$3:$J$57,8,0)="N/A",0,VLOOKUP(C25,'Boats Data Sheet 2026'!$C$3:$J$57,8,0)),"N/A")} -> N/A | D42: {=IF(B42>7,2,IF(B42=0,"N/A",1))} -> N/A | E42: {=_xlfn.IFERROR(SUM('Direct Costs 2026'!$C$4:$C$5)*D42,"N/A")} -> N/A | F42: {=_xlfn.IFERROR('Direct Costs 2026'!$C$43*B42,"N/A")} -> 0 | G42: {=IF(B42>0,'Direct Costs 2026'!$C$25,"N/A")} -> N/A | H42: {=IF(B42>0,('Direct Costs 2026'!$C$15+'Direct Costs 2026'!$C$14+'Direct Costs 2026'!$C$17),"N/A")} -> N/A | I42: {=IF(B42>0,'Direct Costs 2026'!$C$19+'Direct Costs 2026'!$C$18*B42,"N/A")} -> N/A | J42: {=IF(B42>0,SUM('Direct Costs 2026'!$C$20:$C$21),"N/A")} -> N/A | K42: {=IF(B42>0,'Direct Costs 2026'!$C$26,"N/A")} -> N/A | L42: {=IF(B42>0,'Direct Costs 2026'!$C$23,"N/A")} -> N/A | M42: {=IF(B42>0,'Direct Costs 2026'!$C$45*B42,"N/A")} -> N/A | N42: {=IF(B42>0,_xlfn.IFERROR(VLOOKUP(C25,'Boats Data Sheet 2026'!$C$3:$I$57,7,0)*'Direct Costs 2026'!$C$36,"N/A"),"N/A")} -> N/A | O42: {=IF(B42>0,IF(OR(VLOOKUP(C25,'Boats Data Sheet 2026'!$C$3:$F$57,4,0)="Own",VLOOKUP(C25,'Boats Data Sheet 2026'!$C$3:$F$57,4,0)="Management"),('Direct Costs 2026'!$C$37+'Direct Costs 2026'!$C$39),"N/A"),"N/A")} -> N/A | P42: {=_xlfn.IFERROR('Direct Costs 2026'!$C$27*C42,"N/A")} -> N/A | Q42: {=_xlfn.IFERROR(C42+SUM(E42:P42),"N/A")} -> N/A | S42: {=IF(B42>0,'Allocation OH and Target 2026'!$E$31,"N/A")} -> N/A | T42: {=IF(B42>0,VLOOKUP(C25,'Allocation OH and Target 2026'!$C$35:$S$87,16,0),"N/A")} -> N/A | U42: {=_xlfn.IFERROR((S42+T42),"N/A")} -> N/A | W42: {=_xlfn.IFERROR(U42+Q42,"N/A")} -> N/A | X42: {=_xlfn.IFERROR(W42*0.5%,"N/A")} -> N/A | Y42: {=_xlfn.IFERROR(W42*25%,"N/A")} -> N/A | Z42: {=IF(B42>0,SUM(W42:Y42),"N/A")} -> N/A | AA42: {=_xlfn.IFERROR((Z42-Z41),"N/A")} -> N/A | AC42: {=IF(B42=6,AVERAGE(Z28:Z33),"N/A")} -> N/A
B43: {=IF(B42=0,0,IF(B42<VLOOKUP(C25,'Boats Data Sheet 2026'!$C$3:$H$57,6,0),B42+1,0))} -> 0 | C43: {=IF(B43>0,IF(VLOOKUP(C25,'Boats Data Sheet 2026'!$C$3:$J$57,8,0)="N/A",0,VLOOKUP(C25,'Boats Data Sheet 2026'!$C$3:$J$57,8,0)),"N/A")} -> N/A | D43: {=IF(B43>7,2,IF(B43=0,"N/A",1))} -> N/A | E43: {=_xlfn.IFERROR(SUM('Direct Costs 2026'!$C$4:$C$5)*D43,"N/A")} -> N/A | F43: {=_xlfn.IFERROR('Direct Costs 2026'!$C$43*B43,"N/A")} -> 0 | G43: {=IF(B43>0,'Direct Costs 2026'!$C$25,"N/A")} -> N/A | H43: {=IF(B43>0,('Direct Costs 2026'!$C$15+'Direct Costs 2026'!$C$14+'Direct Costs 2026'!$C$17),"N/A")} -> N/A | I43: {=IF(B43>0,'Direct Costs 2026'!$C$19+'Direct Costs 2026'!$C$18*B43,"N/A")} -> N/A | J43: {=IF(B43>0,SUM('Direct Costs 2026'!$C$20:$C$21),"N/A")} -> N/A | K43: {=IF(B43>0,'Direct Costs 2026'!$C$26,"N/A")} -> N/A | L43: {=IF(B43>0,'Direct Costs 2026'!$C$23,"N/A")} -> N/A | M43: {=IF(B43>0,'Direct Costs 2026'!$C$45*B43,"N/A")} -> N/A | N43: {=IF(B43>0,_xlfn.IFERROR(VLOOKUP(C25,'Boats Data Sheet 2026'!$C$3:$I$57,7,0)*'Direct Costs 2026'!$C$36,"N/A"),"N/A")} -> N/A | O43: {=IF(B43>0,IF(OR(VLOOKUP(C25,'Boats Data Sheet 2026'!$C$3:$F$57,4,0)="Own",VLOOKUP(C25,'Boats Data Sheet 2026'!$C$3:$F$57,4,0)="Management"),('Direct Costs 2026'!$C$37+'Direct Costs 2026'!$C$39),"N/A"),"N/A")} -> N/A | P43: {=_xlfn.IFERROR('Direct Costs 2026'!$C$27*C43,"N/A")} -> N/A | Q43: {=_xlfn.IFERROR(C43+SUM(E43:P43),"N/A")} -> N/A | S43: {=IF(B43>0,'Allocation OH and Target 2026'!$E$31,"N/A")} -> N/A | T43: {=IF(B43>0,VLOOKUP(C25,'Allocation OH and Target 2026'!$C$35:$S$87,16,0),"N/A")} -> N/A | U43: {=_xlfn.IFERROR((S43+T43),"N/A")} -> N/A | W43: {=_xlfn.IFERROR(U43+Q43,"N/A")} -> N/A | X43: {=_xlfn.IFERROR(W43*0.5%,"N/A")} -> N/A | Y43: {=_xlfn.IFERROR(W43*25%,"N/A")} -> N/A | Z43: {=IF(B43>0,SUM(W43:Y43),"N/A")} -> N/A | AA43: {=_xlfn.IFERROR((Z43-Z42),"N/A")} -> N/A | AC43: {=IF(B43=6,AVERAGE(Z28:Z33),"N/A")} -> N/A
B44: {=IF(B43=0,0,IF(B43<VLOOKUP(C25,'Boats Data Sheet 2026'!$C$3:$H$57,6,0),B43+1,0))} -> 0 | C44: {=IF(B44>0,IF(VLOOKUP(C25,'Boats Data Sheet 2026'!$C$3:$J$57,8,0)="N/A",0,VLOOKUP(C25,'Boats Data Sheet 2026'!$C$3:$J$57,8,0)),"N/A")} -> N/A | D44: {=IF(B44>7,2,IF(B44=0,"N/A",1))} -> N/A | E44: {=_xlfn.IFERROR(SUM('Direct Costs 2026'!$C$4:$C$5)*D44,"N/A")} -> N/A | F44: {=_xlfn.IFERROR('Direct Costs 2026'!$C$43*B44,"N/A")} -> 0 | G44: {=IF(B44>0,'Direct Costs 2026'!$C$25,"N/A")} -> N/A | H44: {=IF(B44>0,('Direct Costs 2026'!$C$15+'Direct Costs 2026'!$C$14+'Direct Costs 2026'!$C$17),"N/A")} -> N/A | I44: {=IF(B44>0,'Direct Costs 2026'!$C$19+'Direct Costs 2026'!$C$18*B44,"N/A")} -> N/A | J44: {=IF(B44>0,SUM('Direct Costs 2026'!$C$20:$C$21),"N/A")} -> N/A | K44: {=IF(B44>0,'Direct Costs 2026'!$C$26,"N/A")} -> N/A | L44: {=IF(B44>0,'Direct Costs 2026'!$C$23,"N/A")} -> N/A | M44: {=IF(B44>0,'Direct Costs 2026'!$C$45*B44,"N/A")} -> N/A | N44: {=IF(B44>0,_xlfn.IFERROR(VLOOKUP(C25,'Boats Data Sheet 2026'!$C$3:$I$57,7,0)*'Direct Costs 2026'!$C$36,"N/A"),"N/A")} -> N/A | O44: {=IF(B44>0,IF(OR(VLOOKUP(C25,'Boats Data Sheet 2026'!$C$3:$F$57,4,0)="Own",VLOOKUP(C25,'Boats Data Sheet 2026'!$C$3:$F$57,4,0)="Management"),('Direct Costs 2026'!$C$37+'Direct Costs 2026'!$C$39),"N/A"),"N/A")} -> N/A | P44: {=_xlfn.IFERROR('Direct Costs 2026'!$C$27*C44,"N/A")} -> N/A | Q44: {=_xlfn.IFERROR(C44+SUM(E44:P44),"N/A")} -> N/A | S44: {=IF(B44>0,'Allocation OH and Target 2026'!$E$31,"N/A")} -> N/A | T44: {=IF(B44>0,VLOOKUP(C25,'Allocation OH and Target 2026'!$C$35:$S$87,16,0),"N/A")} -> N/A | U44: {=_xlfn.IFERROR((S44+T44),"N/A")} -> N/A | W44: {=_xlfn.IFERROR(U44+Q44,"N/A")} -> N/A | X44: {=_xlfn.IFERROR(W44*0.5%,"N/A")} -> N/A | Y44: {=_xlfn.IFERROR(W44*25%,"N/A")} -> N/A | Z44: {=IF(B44>0,SUM(W44:Y44),"N/A")} -> N/A | AA44: {=_xlfn.IFERROR((Z44-Z43),"N/A")} -> N/A | AC44: {=IF(B44=6,AVERAGE(Z28:Z33),"N/A")} -> N/A
B45: {=IF(B44=0,0,IF(B44<VLOOKUP(C25,'Boats Data Sheet 2026'!$C$3:$H$57,6,0),B44+1,0))} -> 0 | C45: {=IF(B45>0,IF(VLOOKUP(C25,'Boats Data Sheet 2026'!$C$3:$J$57,8,0)="N/A",0,VLOOKUP(C25,'Boats Data Sheet 2026'!$C$3:$J$57,8,0)),"N/A")} -> N/A | D45: {=IF(B45>7,2,IF(B45=0,"N/A",1))} -> N/A | E45: {=_xlfn.IFERROR(SUM('Direct Costs 2026'!$C$4:$C$5)*D45,"N/A")} -> N/A | F45: {=_xlfn.IFERROR('Direct Costs 2026'!$C$43*B45,"N/A")} -> 0 | G45: {=IF(B45>0,'Direct Costs 2026'!$C$25,"N/A")} -> N/A | H45: {=IF(B45>0,('Direct Costs 2026'!$C$15+'Direct Costs 2026'!$C$14+'Direct Costs 2026'!$C$17),"N/A")} -> N/A | I45: {=IF(B45>0,'Direct Costs 2026'!$C$19+'Direct Costs 2026'!$C$18*B45,"N/A")} -> N/A | J45: {=IF(B45>0,SUM('Direct Costs 2026'!$C$20:$C$21),"N/A")} -> N/A | K45: {=IF(B45>0,'Direct Costs 2026'!$C$26,"N/A")} -> N/A | L45: {=IF(B45>0,'Direct Costs 2026'!$C$23,"N/A")} -> N/A | M45: {=IF(B45>0,'Direct Costs 2026'!$C$45*B45,"N/A")} -> N/A | N45: {=IF(B45>0,_xlfn.IFERROR(VLOOKUP(C25,'Boats Data Sheet 2026'!$C$3:$I$57,7,0)*'Direct Costs 2026'!$C$36,"N/A"),"N/A")} -> N/A | O45: {=IF(B45>0,IF(OR(VLOOKUP(C25,'Boats Data Sheet 2026'!$C$3:$F$57,4,0)="Own",VLOOKUP(C25,'Boats Data Sheet 2026'!$C$3:$F$57,4,0)="Management"),('Direct Costs 2026'!$C$37+'Direct Costs 2026'!$C$39),"N/A"),"N/A")} -> N/A | P45: {=_xlfn.IFERROR('Direct Costs 2026'!$C$27*C45,"N/A")} -> N/A | Q45: {=_xlfn.IFERROR(C45+SUM(E45:P45),"N/A")} -> N/A | S45: {=IF(B45>0,'Allocation OH and Target 2026'!$E$31,"N/A")} -> N/A | T45: {=IF(B45>0,VLOOKUP(C25,'Allocation OH and Target 2026'!$C$35:$S$87,16,0),"N/A")} -> N/A | U45: {=_xlfn.IFERROR((S45+T45),"N/A")} -> N/A | W45: {=_xlfn.IFERROR(U45+Q45,"N/A")} -> N/A | X45: {=_xlfn.IFERROR(W45*0.5%,"N/A")} -> N/A | Y45: {=_xlfn.IFERROR(W45*25%,"N/A")} -> N/A | Z45: {=IF(B45>0,SUM(W45:Y45),"N/A")} -> N/A | AA45: {=_xlfn.IFERROR((Z45-Z44),"N/A")} -> N/A | AC45: {=IF(B45=6,AVERAGE(Z28:Z33),"N/A")} -> N/A
A48: 3 | B48: Boat: | C48: Sanjaya | AE48: Average direct cost | AF48: {=AVERAGE(Q51:Q56)} -> 7660000 | AG48: Extra pax cost | AH48: {=AVERAGE(Q57:Q64)-AF48} -> 1764428.6 | AI48: Average profit margin | AJ48: {=AVERAGE(Y51:Y58)} -> 2756471.2 | AK48: Average total cost | AL48: {=AVERAGE(W51:W56)} -> 10760447 | AM48: 1-Pax cost | AN48: {=W51} -> 10370447
C49: DIRECT COSTS | S49: INDIRECT COST | W49: TARGER PRICING | AC49: Წ
B50: Guests u | C50: Boat Rent u | D50: Guides | E50: Guides Salary & Tax | F50: Towels | G50: Ice & Water | H50: Serangan Extra Fee | I50: Seran Retribution | J50: Seran Parking and Mooring | K50: Offering | L50: Fruits | M50: Lunch | N50: Fuel Pertamax | O50: Crew Salary & Tax u | P50: Boat Tax | Q50: TOTAL DIRECT | S50: Indirect and Admin Cost per tour | T50: 3D (Depretiation, Docking, Doc) fees per tour u | U50: TOTAL INDIRECT | W50: TOTAL COST | X50: Tax Markup 0.5% | Y50: Targer Net Profit Margin 25% | Z50: TARGET PRICE PER TOUR | AA50: Extra Pax Charge | AC50: RECOMMENED BASE PRICE PER TOUR
B51: 1 | C51: {=IF(B51>0,IF(VLOOKUP(C48,'Boats Data Sheet 2026'!$C$3:$J$57,8,0)="N/A",0,VLOOKUP(C48,'Boats Data Sheet 2026'!$C$3:$J$57,8,0)),"N/A")} -> 5675000 | D51: {=IF(B51>7,2,IF(B51=0,"N/A",1))} -> 1 | E51: {=_xlfn.IFERROR(SUM('Direct Costs 2026'!$C$4:$C$5)*D51,"N/A")} -> 875500 | F51: {=_xlfn.IFERROR('Direct Costs 2026'!$C$43*B51,"N/A")} -> 6000 | G51: {=IF(B51>0,'Direct Costs 2026'!$C$25,"N/A")} -> 90000 | H51: {=IF(B51>0,'Direct Costs 2026'!$C$22,"N/A")} -> 200000 | I51: 0 | J51: 0 | K51: {=IF(B51>0,'Direct Costs 2026'!$C$26,"N/A")} -> 20000 | L51: {=IF(B51>0,'Direct Costs 2026'!$C$23,"N/A")} -> 140000 | M51: {=IF(B51>0,'Direct Costs 2026'!$C$45*B51,"N/A")} -> 150000 | N51: {=IF(B51>0,_xlfn.IFERROR(VLOOKUP(C48,'Boats Data Sheet 2026'!$C$3:$I$57,7,0)*'Direct Costs 2026'!$C$36,"N/A"),"N/A")} -> N/A | O51: {=IF(B51>0,IF(OR(VLOOKUP(C48,'Boats Data Sheet 2026'!$C$3:$F$57,4,0)="Own",VLOOKUP(C48,'Boats Data Sheet 2026'!$C$3:$F$57,4,0)="Management"),('Direct Costs 2026'!$C$37+'Direct Costs 2026'!$C$39),"N/A"),"N/A")} -> N/A | P51: {=_xlfn.IFERROR('Direct Costs 2026'!$C$27*C51,"N/A")} -> 113500 | Q51: {=_xlfn.IFERROR(C51+SUM(E51:P51),"N/A")} -> 7270000 | S51: {=IF(B51>0,'Allocation OH and Target 2026'!$E$31,"N/A")} -> 3100447.2 | T51: {=IF(B51>0,VLOOKUP(C48,'Allocation OH and Target 2026'!$C$35:$S$87,16,0),"N/A")} -> 0 | U51: {=_xlfn.IFERROR((S51+T51),"N/A")} -> 3100447.2 | W51: {=_xlfn.IFERROR(U51+Q51,"N/A")} -> 10370447 | X51: {=_xlfn.IFERROR(W51*0.5%,"N/A")} -> 51852.236 | Y51: {=_xlfn.IFERROR(W51*25%,"N/A")} -> 2592611.8 | Z51: {=IF(B51>0,SUM(W51:Y51),"N/A")} -> 13014911 | AA51: 0 | AC51: {=IF(B51=6,AVERAGE(Z51:Z56),"N/A")} -> N/A
B52: {=IF(B51=0,0,IF(B51<VLOOKUP(C48,'Boats Data Sheet 2026'!$C$3:$H$57,6,0),B51+1,0))} -> 2 | C52: {=IF(B52>0,IF(VLOOKUP(C48,'Boats Data Sheet 2026'!$C$3:$J$57,8,0)="N/A",0,VLOOKUP(C48,'Boats Data Sheet 2026'!$C$3:$J$57,8,0)),"N/A")} -> 5675000 | D52: {=IF(B52>7,2,IF(B52=0,"N/A",1))} -> 1 | E52: {=_xlfn.IFERROR(SUM('Direct Costs 2026'!$C$4:$C$5)*D52,"N/A")} -> 875500 | F52: {=_xlfn.IFERROR('Direct Costs 2026'!$C$43*B52,"N/A")} -> 12000 | G52: {=IF(B52>0,'Direct Costs 2026'!$C$25,"N/A")} -> 90000 | H52: {=IF(B52>0,'Direct Costs 2026'!$C$22,"N/A")} -> 200000 | I52: 0 | J52: 0 | K52: {=IF(B52>0,'Direct Costs 2026'!$C$26,"N/A")} -> 20000 | L52: {=IF(B52>0,'Direct Costs 2026'!$C$23,"N/A")} -> 140000 | M52: {=IF(B52>0,'Direct Costs 2026'!$C$45*B52,"N/A")} -> 300000 | N52: {=IF(B52>0,_xlfn.IFERROR(VLOOKUP(C48,'Boats Data Sheet 2026'!$C$3:$I$57,7,0)*'Direct Costs 2026'!$C$36,"N/A"),"N/A")} -> N/A | O52: {=IF(B52>0,IF(OR(VLOOKUP(C48,'Boats Data Sheet 2026'!$C$3:$F$57,4,0)="Own",VLOOKUP(C48,'Boats Data Sheet 2026'!$C$3:$F$57,4,0)="Management"),('Direct Costs 2026'!$C$37+'Direct Costs 2026'!$C$39),"N/A"),"N/A")} -> N/A | P52: {=_xlfn.IFERROR('Direct Costs 2026'!$C$27*C52,"N/A")} -> 113500 | Q52: {=_xlfn.IFERROR(C52+SUM(E52:P52),"N/A")} -> 7426000 | S52: {=IF(B52>0,'Allocation OH and Target 2026'!$E$31,"N/A")} -> 3100447.2 | T52: {=IF(B52>0,VLOOKUP(C48,'Allocation OH and Target 2026'!$C$35:$S$87,16,0),"N/A")} -> 0 | U52: {=_xlfn.IFERROR((S52+T52),"N/A")} -> 3100447.2 | W52: {=_xlfn.IFERROR(U52+Q52,"N/A")} -> 10526447 | X52: {=_xlfn.IFERROR(W52*0.5%,"N/A")} -> 52632.236 | Y52: {=_xlfn.IFERROR(W52*25%,"N/A")} -> 2631611.8 | Z52: {=IF(B52>0,SUM(W52:Y52),"N/A")} -> 13210691 | AA52: {=_xlfn.IFERROR((Z52-Z51),"N/A")} -> 195780 | AC52: {=IF(B52=6,AVERAGE(Z51:Z56),"N/A")} -> N/A
B53: {=IF(B52=0,0,IF(B52<VLOOKUP(C48,'Boats Data Sheet 2026'!$C$3:$H$57,6,0),B52+1,0))} -> 3 | C53: {=IF(B53>0,IF(VLOOKUP(C48,'Boats Data Sheet 2026'!$C$3:$J$57,8,0)="N/A",0,VLOOKUP(C48,'Boats Data Sheet 2026'!$C$3:$J$57,8,0)),"N/A")} -> 5675000 | D53: {=IF(B53>7,2,IF(B53=0,"N/A",1))} -> 1 | E53: {=_xlfn.IFERROR(SUM('Direct Costs 2026'!$C$4:$C$5)*D53,"N/A")} -> 875500 | F53: {=_xlfn.IFERROR('Direct Costs 2026'!$C$43*B53,"N/A")} -> 18000 | G53: {=IF(B53>0,'Direct Costs 2026'!$C$25,"N/A")} -> 90000 | H53: {=IF(B53>0,'Direct Costs 2026'!$C$22,"N/A")} -> 200000 | I53: 0 | J53: 0 | K53: {=IF(B53>0,'Direct Costs 2026'!$C$26,"N/A")} -> 20000 | L53: {=IF(B53>0,'Direct Costs 2026'!$C$23,"N/A")} -> 140000 | M53: {=IF(B53>0,'Direct Costs 2026'!$C$45*B53,"N/A")} -> 450000 | N53: {=IF(B53>0,_xlfn.IFERROR(VLOOKUP(C48,'Boats Data Sheet 2026'!$C$3:$I$57,7,0)*'Direct Costs 2026'!$C$36,"N/A"),"N/A")} -> N/A | O53: {=IF(B53>0,IF(OR(VLOOKUP(C48,'Boats Data Sheet 2026'!$C$3:$F$57,4,0)="Own",VLOOKUP(C48,'Boats Data Sheet 2026'!$C$3:$F$57,4,0)="Management"),('Direct Costs 2026'!$C$37+'Direct Costs 2026'!$C$39),"N/A"),"N/A")} -> N/A | P53: {=_xlfn.IFERROR('Direct Costs 2026'!$C$27*C53,"N/A")} -> 113500 | Q53: {=_xlfn.IFERROR(C53+SUM(E53:P53),"N/A")} -> 7582000 | S53: {=IF(B53>0,'Allocation OH and Target 2026'!$E$31,"N/A")} -> 3100447.2 | T53: {=IF(B53>0,VLOOKUP(C48,'Allocation OH and Target 2026'!$C$35:$S$87,16,0),"N/A")} -> 0 | U53: {=_xlfn.IFERROR((S53+T53),"N/A")} -> 3100447.2 | W53: {=_xlfn.IFERROR(U53+Q53,"N/A")} -> 10682447 | X53: {=_xlfn.IFERROR(W53*0.5%,"N/A")} -> 53412.236 | Y53: {=_xlfn.IFERROR(W53*25%,"N/A")} -> 2670611.8 | Z53: {=IF(B53>0,SUM(W53:Y53),"N/A")} -> 13406471 | AA53: {=_xlfn.IFERROR((Z53-Z52),"N/A")} -> 195780 | AC53: {=IF(B53=6,AVERAGE(Z51:Z56),"N/A")} -> N/A
B54: {=IF(B53=0,0,IF(B53<VLOOKUP(C48,'Boats Data Sheet 2026'!$C$3:$H$57,6,0),B53+1,0))} -> 4 | C54: {=IF(B54>0,IF(VLOOKUP(C48,'Boats Data Sheet 2026'!$C$3:$J$57,8,0)="N/A",0,VLOOKUP(C48,'Boats Data Sheet 2026'!$C$3:$J$57,8,0)),"N/A")} -> 5675000 | D54: {=IF(B54>7,2,IF(B54=0,"N/A",1))} -> 1 | E54: {=_xlfn.IFERROR(SUM('Direct Costs 2026'!$C$4:$C$5)*D54,"N/A")} -> 875500 | F54: {=_xlfn.IFERROR('Direct Costs 2026'!$C$43*B54,"N/A")} -> 24000 | G54: {=IF(B54>0,'Direct Costs 2026'!$C$25,"N/A")} -> 90000 | H54: {=IF(B54>0,'Direct Costs 2026'!$C$22,"N/A")} -> 200000 | I54: 0 | J54: 0 | K54: {=IF(B54>0,'Direct Costs 2026'!$C$26,"N/A")} -> 20000 | L54: {=IF(B54>0,'Direct Costs 2026'!$C$23,"N/A")} -> 140000 | M54: {=IF(B54>0,'Direct Costs 2026'!$C$45*B54,"N/A")} -> 600000 | N54: {=IF(B54>0,_xlfn.IFERROR(VLOOKUP(C48,'Boats Data Sheet 2026'!$C$3:$I$57,7,0)*'Direct Costs 2026'!$C$36,"N/A"),"N/A")} -> N/A | O54: {=IF(B54>0,IF(OR(VLOOKUP(C48,'Boats Data Sheet 2026'!$C$3:$F$57,4,0)="Own",VLOOKUP(C48,'Boats Data Sheet 2026'!$C$3:$F$57,4,0)="Management"),('Direct Costs 2026'!$C$37+'Direct Costs 2026'!$C$39),"N/A"),"N/A")} -> N/A | P54: {=_xlfn.IFERROR('Direct Costs 2026'!$C$27*C54,"N/A")} -> 113500 | Q54: {=_xlfn.IFERROR(C54+SUM(E54:P54),"N/A")} -> 7738000 | S54: {=IF(B54>0,'Allocation OH and Target 2026'!$E$31,"N/A")} -> 3100447.2 | T54: {=IF(B54>0,VLOOKUP(C48,'Allocation OH and Target 2026'!$C$35:$S$87,16,0),"N/A")} -> 0 | U54: {=_xlfn.IFERROR((S54+T54),"N/A")} -> 3100447.2 | W54: {=_xlfn.IFERROR(U54+Q54,"N/A")} -> 10838447 | X54: {=_xlfn.IFERROR(W54*0.5%,"N/A")} -> 54192.236 | Y54: {=_xlfn.IFERROR(W54*25%,"N/A")} -> 2709611.8 | Z54: {=IF(B54>0,SUM(W54:Y54),"N/A")} -> 13602251 | AA54: {=_xlfn.IFERROR((Z54-Z53),"N/A")} -> 195780 | AC54: {=IF(B54=6,AVERAGE(Z51:Z56),"N/A")} -> N/A
B55: {=IF(B54=0,0,IF(B54<VLOOKUP(C48,'Boats Data Sheet 2026'!$C$3:$H$57,6,0),B54+1,0))} -> 5 | C55: {=IF(B55>0,IF(VLOOKUP(C48,'Boats Data Sheet 2026'!$C$3:$J$57,8,0)="N/A",0,VLOOKUP(C48,'Boats Data Sheet 2026'!$C$3:$J$57,8,0)),"N/A")} -> 5675000 | D55: {=IF(B55>7,2,IF(B55=0,"N/A",1))} -> 1 | E55: {=_xlfn.IFERROR(SUM('Direct Costs 2026'!$C$4:$C$5)*D55,"N/A")} -> 875500 | F55: {=_xlfn.IFERROR('Direct Costs 2026'!$C$43*B55,"N/A")} -> 30000 | G55: {=IF(B55>0,'Direct Costs 2026'!$C$25,"N/A")} -> 90000 | H55: {=IF(B55>0,'Direct Costs 2026'!$C$22,"N/A")} -> 200000 | I55: 0 | J55: 0 | K55: {=IF(B55>0,'Direct Costs 2026'!$C$26,"N/A")} -> 20000 | L55: {=IF(B55>0,'Direct Costs 2026'!$C$23,"N/A")} -> 140000 | M55: {=IF(B55>0,'Direct Costs 2026'!$C$45*B55,"N/A")} -> 750000 | N55: {=IF(B55>0,_xlfn.IFERROR(VLOOKUP(C48,'Boats Data Sheet 2026'!$C$3:$I$57,7,0)*'Direct Costs 2026'!$C$36,"N/A"),"N/A")} -> N/A | O55: {=IF(B55>0,IF(OR(VLOOKUP(C48,'Boats Data Sheet 2026'!$C$3:$F$57,4,0)="Own",VLOOKUP(C48,'Boats Data Sheet 2026'!$C$3:$F$57,4,0)="Management"),('Direct Costs 2026'!$C$37+'Direct Costs 2026'!$C$39),"N/A"),"N/A")} -> N/A | P55: {=_xlfn.IFERROR('Direct Costs 2026'!$C$27*C55,"N/A")} -> 113500 | Q55: {=_xlfn.IFERROR(C55+SUM(E55:P55),"N/A")} -> 7894000 | S55: {=IF(B55>0,'Allocation OH and Target 2026'!$E$31,"N/A")} -> 3100447.2 | T55: {=IF(B55>0,VLOOKUP(C48,'Allocation OH and Target 2026'!$C$35:$S$87,16,0),"N/A")} -> 0 | U55: {=_xlfn.IFERROR((S55+T55),"N/A")} -> 3100447.2 | W55: {=_xlfn.IFERROR(U55+Q55,"N/A")} -> 10994447 | X55: {=_xlfn.IFERROR(W55*0.5%,"N/A")} -> 54972.236 | Y55: {=_xlfn.IFERROR(W55*25%,"N/A")} -> 2748611.8 | Z55: {=IF(B55>0,SUM(W55:Y55),"N/A")} -> 13798031 | AA55: {=_xlfn.IFERROR((Z55-Z54),"N/A")} -> 195780 | AC55: {=IF(B55=6,AVERAGE(Z51:Z56),"N/A")} -> N/A
